Workbook

Sheet Main
A306: DR | B306: =CONCATENATE('Data resiliency'!$H$56,"/",'Data resiliency'!$A$56," Assessed") -> 0/13 Assessed
A307: AC | B307: =CONCATENATE('Access Control'!$H$57,"/",'Access Control'!$A$57," Assessed") -> 0/41 Assessed
A308: DL | B308: =CONCATENATE('Data Leakage'!$H$96,"/",'Data Leakage'!$A$96," Assessed") -> 0/82 Assessed
A309: SC | B309: =CONCATENATE('Security & Compliance'!$H$134,"/",'Security & Compliance'!$A$134," Assessed") -> 0/80 Assessed
A310: IR | B310: =CONCATENATE('Incident Response'!$H$101,"/",'Incident Response'!$A$101," Assessed") -> 0/63 Assessed

Sheet Data resiliency
A1: Category | B1: Product | C1: Feature | D1: Description | E1: Portal | F1: PS Configure | G1: PS Get | H1: Assessed
A2: Resilience DR | B2: Office 365 | C2: Data Resilience DR | D2: To help organizations meet complex incidents introduced by logical corruption or illicit modifications of stored information Office 365 has several features that can help salvage information.
A3: Resilience DR | B3: Exchange | C3: Exchange | D3: In Exchange Online both users and administrators can recover data. There may be situations where recoverable data is not available to end users where the recovery need to be conducted by customer administrators. Customer service administrators may need to make recoveries due to modifications of existing calendar items as an example.
A4: Resilience DR | B4: Exchange | C4: Single Item Recovery | D4: Customer administrators can search for and recover deleted email messages in a user's mailbox. This includes items that are permanently deleted (purged) by a person (by using the Recover Deleted Items feature in Outlook or Outlook Web App), or items deleted or modified by an automated process.
A5: Resilience DR | B5: Exchange | C5: Recoverable Items | D5: The Recoverable Items folder contains a number of subfolders the Deletions subfolder contains the items deleted from the Deleted Items folder. (In Outlook, a user can soft delete an item by pressing Shift+Delete.) This subfolder is exposed to users through the Recover Deleted Items feature in Outlook and Outlook Web App.
A6: Resilience DR | B6: Exchange | C6: Restore Deleted Mailboxes | D6: A soft-deleted mailbox is retained in the source database until the deleted mailbox retention period expires or until the Remove-StoreMailbox cmdlet is used to purge the soft-deleted mailbox.
A7: Resilience DR | B7: SharePoint | C7: SharePoint | D7: SharePoint has a rich set of capabilities to restore information that has been modified by mistake or maliciously.
A8: Resilience DR | B8: SharePoint | C8: SharePoint Recycle Bin | D8: SharePoint Online sites offer end-user and site collection administrator views to the Recycle Bin. The end user can see any items he or she deleted, a site collection administrator, can see all items deleted by any user within the site collection
A9: Resilience DR | B9: SharePoint | C9: SharePoint Versioning | D9: Anyone with permission to manage lists can turn versioning on or off for a library. Versioning is available for list items in all default list types—including calendars, issue tracking lists, and custom lists. It is also available for all file types that can be stored in libraries, including Web Part pages. Versioning is turned on by default when you create new OneDrive for Business libraries in Office 365, and it will automatically save the last ten versions of a document.
A10: Resilience DR | B10: SharePoint | C10: OneDrive for Business Deletion | D10: When a OneDrive for Business site collection is scheduled for deletion, the default action is to transfer ownership of the site to the manager. For this to occur, the user profile Manager property must be set for the original owner of the OneDrive for Business site.
A11: Discover DP | B11: Office 365 | C11: Discover (DP) | D11: With immense costs for legal review and ever growing amounts of data, organizations are struggling to find the right set of data. With legal review costs ranging from $10,000 per $40,000 per gigabyte there is a strong incentive to minimize the data organizations send to review and production. Office 365 has a rich set of tools that organizations can use to minimize the amount of data that need to be produced for legal review.
A12: Discover DP | B12: Office 365 | C12: Search from a Single Unified Portal | D12: The eDiscovery Center is used to manage new and existing eDiscovery cases and close eDiscovery cases that are no longer needed. This provide a systemic approach to eDiscovery across Office 365.
A13: Preserve DP | B13: Exchange | C13: PST Ingestion | D13: Organizations where users keep a lot of information in their PST files may run a risk of keeping information out of policy which can be damaging in a court case if not produced correctly. Exchange Online allow for customers to upload users PST files and ingest them in to Exchange Online. | E13: Office 365 Portal Import
A14: Preserve DP | B14: SharePoint | C14: Place Content on in-place Hold | D14: Query based hold in Office 365 allow organizations to not only hold information from SharePoint but also for Skype for business, Exchange and OneDrive for Business.
A56: =COUNTA(A2:A44) -> 13 | H56: =COUNTA(H2:H44) -> 0

Sheet Access Control
A1: Category | B1: Product | C1: Feature | D1: Description | E1: Portal | F1: PS Configure | G1: PS Get | H1: Assessed
A2: Admin AC | B2: O365 | C2: Access Control Admin (AC) | D2: The Access Control Admin category covers the aspects of a trusted administration model that is different from the model used for users. If the accounts used for administration can't be monitored or trusted it breaches the security of the entire system.
A3: Admin AC | B3: O365 | C3: Separation of Duties | D3: Depending on the size of your organization, you may want to designate several admins who serve different functions. The admin has access to all features in the admin center, and can create or edit users, assign admin roles to others, reset user passwords, manage user licenses, and manage domains, among other things. Office 365 includes a security model that enables separation of administration based on roles. Certain admin roles Office 365 have a corresponding role in Exchange Online, SharePoint Online, and Skype for Business Online. | E3: Select the user and edit user roles
A4: Admin AC | B4: Exchange | C4: Separate Exchange Administrators | D4: Depending on the size of your organization, you may want to designate several admins who serve different functions. The admin has access to all features in the admin center, and can create or edit users, assign admin roles to others, reset user passwords, manage user licenses, and manage domains, among other things. Office 365 includes a security model that enables separation of administration based on roles. Certain admin roles Office 365 have a corresponding role in Exchange Online, SharePoint Online, and Skype for Business Online. Segment permissions to ensure that a single administrator doesn't have greater access than necessary. | E4: Select the user and edit user roles | F4: Set-MsolRoleMember | G4: Get-MsolRoleMember
A5: Admin AC | B5: SharePoint | C5: Separate SharePoint Administrators | D5: Depending on the size of your organization, you may want to designate several admins who serve different functions. The admin has access to all features in the admin center, and can create or edit users, assign admin roles to others, reset user passwords, manage user licenses, and manage domains, among other things. Office 365 includes a security model that enables separation of administration based on roles. Certain admin roles Office 365 have a corresponding role in Exchange Online, SharePoint Online, and Skype for Business Online. Segment permissions to ensure that a single administrator doesn't have greater access than necessary. | E5: Select the user and edit user roles | F5: Set-MsolRoleMember | G5: Get-MsolRoleMember
A6: Admin AC | B6: Skype4B | C6: Separate Skype for Business Administrators | D6: Depending on the size of your organization, you may want to designate several admins who serve different functions. The admin has access to all features in the admin center, and can create or edit users, assign admin roles to others, reset user passwords, manage user licenses, and manage domains, among other things. Office 365 includes a security model that enables separation of administration based on roles. Certain admin roles Office 365 have a corresponding role in Exchange Online, SharePoint Online, and Skype for Business Online. Segment permissions to ensure that a single administrator doesn't have greater access than necessary. | E6: Select the user and edit user roles | F6: Set-MsolRoleMember | G6: Get-MsolRoleMember
A7: Admin AC | B7: Exchange | C7: Exchange Online Privileged Accounts | D7: Perform regular reviews of all users and groups with high levels of permissions. You can search the administrator audit logs to discover who made changes to organization, server, and recipient configuration. This can be helpful when you're trying to track the cause of unexpected behavior, to identify a malicious administrator, to investigate data leaks, or to verify that compliance requirements are being met. | E7: Permissions / Admin Groups
A8: Admin AC | B8: Exchange | C8: Administrator role group changes | D8: Verify that high-privileged roles have not been assigned to any un-authorized users. You can search the administrator audit logs or the Activity logs to discover who made changes to organization, server, and recipient configuration. This can be helpful when you're trying to track the cause of unexpected behavior, to identify a malicious administrator, to investigate data leaks, or to verify that compliance requirements are being met. | E8: Role Group Report | F8: On by default in Office 365 | G8: Get-AdminAuditLogConfig | FL AdminAuditLogEnabled, Search-AdminAuditLog
A9: Admin AC | B9: SharePoint | C9: SharePoint Online Permissions | D9: If you are a SharePoint Online admin, you probably want to control who can make changes on your site. Ensure that the proper users have administrative privileges to appropriate content. Each site collection has its own set of permission levels. SharePoint comes with some default permission levels that you can use, such as Contribute and View Only. But if one of those doesn’t meet your needs, you can create a new permissions level. It’s a best practice that you don’t change the default permission levels. See also https://support.office.com/en-us/article/How-to-create-and-edit-Permission-Levels-53c86040-07fa-4ea7-bc55-34ee96b437fe#__best_practices_for. | F9: Set-SPOSiteGroup, Set-SPOUser | G9: Get-SPOSiteGroup, Get-SPOUser
A10: Admin AC | B10: SharePoint | C10: Review Modification of permissions | D10: Changes to user accounts and permissions should happen regularly to quickly respond to potentially malicious activities. Knowing who has done what with which information is critical for many business requirements, such as regulatory compliance and records management. You can use the audit feature in SharePoint Online to track which users have taken what actions on the sites, content types, lists, libraries, list items, and library files within your site collections. | F10: Set-SPOSiteGroup, Set-SPOUser | G10: Get-SPOSiteGroup, Get-SPOUser
A11: Admin AC | B11: O365 | C11: Customer Lockbox | D11: Microsoft engineers do not have standing access to any service operation. All access is obtained through a rigorous access control technology called Lockbox that enforces access control through multiple levels of approval within Microsoft, providing just-in-time access with limited and time-bound authorization. In addition, all access control activities in the service are logged and audited. Customers are part of the Lockbox approval process for instances involving access to customer content. The customer-facing side of the approval process is called Customer Lockbox. Use of the Customer Lockbox feature ensures that a Microsoft engineer does not get access to customer content without the customer’s explicit approval. Customer Lockbox gives customers explicit approval tools in the rare case when a Microsoft engineer needs access to customer content to resolve a customer-reported issue.
A12: Admin AC | B12: O365 | C12: Review Delegated Partner Administrators | D12: Ensure that partner organizations don't have standing access to the environment unless warranted. This will limit the potential attack surface.
A13: Authentication IA | B13: O365 | C13: Authentication (IA) | D13: The Authentication category covers the options and features available for authentication within Office 365. The list contains Microsoft technologies available both on-premises and in the cloud. Please see this information from the main Customer Security Considerations Pivot if you are using the Fed Ramp control listing.
A14: Authentication IA | B14: O365 | C14: Token Life time | D14: This feature allows you to create token lifetime policies. These policies define how long tokens issued by Azure AD are considered valid. This influences how often users must enter their credentials. These policies can be set as defaults that apply to all applications in a tenant and they can also be linked to applications or service principals. The policies are managed through Azure PowerShell.
A15: Authentication IA | B15: AzureAD | C15: Passwords | D15: Weak passwords trump strong security, so have a good process for passwords and don't re-use them for other systems. Once you've picked strong passwords, handle them appropriately. consider using something stronger than – and in addition to – passwords to identify yourself to the system. Windows, for instance, supports the use of smart cards, which significantly strengthens the account checking the system can perform. You may also want to consider biometric products such as fingerprint and retina scanners. “Two-factor authentication” of this sort incorporates not only something you know (your password) but something you own (a card) or even something you are (a person with your unique fingerprint or retina) – dramatically increasing authentication strength.
A16: Authentication IA | B16: AzureAD | C16: Azure AD Password | D16: Make it difficult to crack or guess user passwords. | E16: Password Settings Portal complex use PowerShell | F16: Set-MsolPasswordPolicy, Set-MsolUser | G16: Get-MsolPasswordPolicy, Get-MsolUser
A17: Authentication IA | B17: AzureAD | C17: Deploying Password Management and training users to use it | D17: To make password reset actions effective organizations can use various methods to ensure that every user in the organization can use self-service password reset effectively in case they forget their password to lessen the administrative burden.
A18: Authentication IA | B18: AzureAD | C18: Review self-service password reset alt phone and email changes | D18: Modification of the contact details may show proof of illicit behavior in the environment.
A19: Authentication IA | B19: AzureAD | C19: Machine generate application passwords | D19: Use machine-generated passwords for administrator accounts or high-privileged accounts to provide a degree of obstruction. Passwords that aren't tied to an individual should be placed in an audited vault and updated on a regular basis.
A20: Authentication IA | B20: AzureAD | C20: Password Age Meets Policy | D20: If the password age doesn't meet the policy reset the password to protect the environment.
A21: Authentication IA | B21: AzureAD | C21: Password Age Policy < 60 Days | D21: This determines how long users can keep a password before they have to change it. The aim is to force users to change their passwords periodically. Generally, you use a shorter period when security is important.
A22: Authentication IA | B22: AzureAD | C22: Store secrets in a Key Vault | D22: Any script or code that uses authenticators should store it in a Secrets Management System. The same is true for other secrets such as certificates. Azure Key Vault helps safeguard cryptographic keys and secrets used by cloud applications and services. By using Key Vault, you can encrypt keys and secrets (such as authentication keys, storage account keys, data encryption keys, .PFX files, and passwords) by using keys that are protected by hardware security modules (HSMs). For added assurance, you can import or generate keys in HSMs. Key Vault streamlines the key management process and enables you to maintain control of keys that access and encrypt your data. Developers can create keys for development and testing in minutes, and then seamlessly migrate them to production keys. Security administrators can grant (and revoke) permission to keys, as needed.
A23: Authentication IA | B23: AzureAD | C23: Multi-factor authentication Office 365 | D23: Multi-factor authentication (MFA) is a method of authentication that requires the use of more than one verification method and adds a second layer of security to user sign-ins and transactions. You can also use any other MFA solutions that are offered with your on-premises directory. For example, the works with Office 365 program identity providers might offer different MFA solutions that you can manage according to the identity provider's specifications. For more information, see http://go.microsoft.com/fwlink/p/?LinkId=510953. | E23: Multi Factor Portal | F23: https://msdn.microsoft.com/en-us/library/azure/dn394289.aspx | G23: Get-MsolUser
A24: Authentication IA | B24: AzureAD | C24: Tenant Admins MFA Enabled | D24: Multi-factor authentication (MFA) is a method of authentication that requires the use of more than one verification method and adds a second layer of security to user sign-ins and transactions. You can also use any other MFA solutions that are offered with your on-premises directory. For example, the works with Office 365 program identity providers might offer different MFA solutions that you can manage according to the identity provider's specifications. For more information, see http://go.microsoft.com/fwlink/p/?LinkId=510953.
A25: Authentication IA | B25: AzureAD | C25: Users MFA Enabled | D25: Multi-factor authentication (MFA) is a method of authentication that requires the use of more than one verification method and adds a second layer of security to user sign-ins and transactions. You can also use any other MFA solutions that are offered with your on-premises directory. For example, the works with Office 365 program identity providers might offer different MFA solutions that you can manage according to the identity provider's specifications. For more information, see http://go.microsoft.com/fwlink/p/?LinkId=510953.
A26: Authentication IA | B26: AzureAD | C26: Phone Factor | D26: Make the connection to a specific user stronger by using a second factor that can be presented by the user when responding to a call. Any of the following may be used for the second factor of authentication: - Call my mobile phone. The user receives a phone call that asks them to press the pound key. Once the pound key is pressed, the user is logged in. - Text code to my mobile phone. The user receives a text message containing a six-digit code that they must enter into the portal. - Call my office phone. This is the same as Call my mobile phone, but it enables the user to select a different phone if they do not have their mobile phone with them. - Notify me through app. The user configured a smartphone app and they receive a notification in the app that they must confirm the login. Smartphone apps are available for Windows Phone, iPhone, and Android devices. - Show one-time code in app. The same smartphone app is used. Instead of receiving a notification, the user starts the app and enters the six-digit code from the app into the portal. | E26: Multi Factor Portal
A27: Authentication IA | B27: AzureAD | C27: Mobile App | D27: Make the connection to a specific user stronger by using a second factor that can be presented to an app running on the user's smartphone. Any of the following may be used for the second factor of authentication: - Call my mobile phone. The user receives a phone call that asks them to press the pound key. Once the pound key is pressed, the user is logged in. - Text code to my mobile phone. The user receives a text message containing a six-digit code that they must enter into the portal. - Call my office phone. This is the same as Call my mobile phone, but it enables the user to select a different phone if they do not have their mobile phone with them. - Notify me through app. The user configured a smartphone app and they receive a notification in the app that they must confirm the login. Smartphone apps are available for Windows Phone, iPhone, and Android devices. - Show one-time code in app. The same smartphone app is used. Instead of receiving a notification, the user starts the app and enters the six-digit code from the app into the portal. | E27: Multi Factor Portal
A28: Authentication IA | B28: AzureAD | C28: Text Message Second Factor | D28: Make the connection to a specific user stronger by using a second factor that can be presented by that user via a text message. Any of the following may be used for the second factor of authentication: - Call my mobile phone. The user receives a phone call that asks them to press the pound key. Once the pound key is pressed, the user is logged in. - Text code to my mobile phone. The user receives a text message containing a six-digit code that they must enter into the portal. - Call my office phone. This is the same as Call my mobile phone, but it enables the user to select a different phone if they do not have their mobile phone with them. - Notify me through app. The user configured a smartphone app and they receive a notification in the app that they must confirm the login. Smartphone apps are available for Windows Phone, iPhone, and Android devices. - Show one-time code in app. The same smartphone app is used. Instead of receiving a notification, the user starts the app and enters the six-digit code from the app into the portal. Make the connection to a specific user stronger by using a second factor that can be presented by that user via a text message. | E28: Multi Factor Portal
A29: Authentication IA | B29: AzureAD | C29: Conditional Access | D29: Conditional Access enables organizations to assess whether users are connecting with trusted devices and to block devices outside of policy. Personally owned devices of your users can be marked known to your organization by requiring the users to work place join their devices to the Azure Active Directory Device Registration service. Azure Active Directory Device Registration is the foundation for device-based conditional access scenarios. When a device is registered, Azure Active Directory Device Registration provisions the device with an identity which is used to authenticate the device when the user signs in. The authenticated device, and the attributes of the device, can then be used to enforce conditional access policies for applications that are hosted in the cloud and on-premises. When combined with a Mobile Device Management solution such as Intune, the device attributes in Azure Active Directory will be updated with additional information about the device. This allows you to create conditional access rules that enforce access from devices will meet your standards for security and compliance. Azure Active Directory Device Registration is available in your Azure Active Directory. The service includes support for iOS, Android, and Windows devices.
A30: Authentication IA | B30: SharePoint | C30: Conditional Access SharePoint | D30: Conditional access in SharePoint and OneDrive goes beyond user permissions: it is based on a combination of factors, such as the identity of a user or group, the network that the user is connected to, the device and application they are using, and the type of data they are trying to access. The access granted to the user adapts to this broader set of conditions. With location-based conditional access policies in SharePoint Online, you can limit access to specific corporate networks or locations. For example, if you restrict access to only your corporate network, users will not be able to access organizational data when they leave the office. This policy helps you prevent access to organization’s data from rogue or insecure networks. | F30: Set-SPOTenant- IPAddressEnforcement $true|$false, Set-SPOTenant -IPAddressAllowList “IPList” | G30: Get-SPOTenant
A31: Authentication IA | B31: Exchange | C31: Conditional Access Exchange | D31: Client access rules are like transport rules for client connections to your organization. You use conditions and exceptions to identify the connections based on the user or properties of the client or the connection, and actions that define what to do with those connections. You need to be assigned permissions before you can run this cmdlet. Although all parameters for this cmdlet are listed in this topic, you may not have access to some parameters if they're not included in the permissions assigned to you. Access the administrative documentation set for your Exchange Online release to review the Managing Client Access Rules self-service administration article to determine which role based access control (RBAC) role assignment is required
A32: Authentication IA | B32: AzureAD | C32: Conditional Access Mobile Devices | D32: Conditional Access enables organizations to assess whether users are connecting with trusted devices and to block devices outside of policy. Personally owned devices of your users can be marked known to your organization by requiring the users to work place join their devices to the Azure Active Directory Device Registration service. Azure Active Directory Device Registration is the foundation for device-based conditional access scenarios. When a device is registered, Azure Active Directory Device Registration provisions the device with an identity which is used to authenticate the device when the user signs in. The authenticated device, and the attributes of the device, can then be used to enforce conditional access policies for applications that are hosted in the cloud and on-premises. When combined with a Mobile Device Management solution such as Intune, the device attributes in Azure Active Directory will be updated with additional information about the device. This allows you to create conditional access rules that enforce access from devices will meet your standards for security and compliance. Azure Active Directory Device Registration is available in your Azure Active Directory. The service includes support for iOS, Android, and Windows devices. | E32: Compliance Center
A33: Identity IA | B33: AzureAD | C33: Disable Identities that are not active | D33: Reduce the number of active identities to reduce licensing costs and the identity attack surface. Periodically check for inactive users and disable accounts that are not active. For example, in Exchange Online, you can use the Get-StaleMailboxDetailReport cmdlet to view mailboxes that have not been accessed for at least the last 30 days. Identities for inactive mailboxes should be disabled. | E33: Inactive Mailbox Report | G33: Get-SpoActiveUserReport, Get-CsActiveUserReport, Get-StaleMailboxDetailReport
A34: Identity IA | B34: AzureAD | C34: Use dedicated Administrative accounts | D34: Do not elevate accounts used for user collaboration to admin privileges use dedicated identities for administrative accounts. Use a naming convention that make them discoverable. | G34: Get-MsolUser -Filter, Get-MailboxActivityReport
A35: Identity IA | B35: Office365 | C35: More than one Tenant Admin Designated | D35: Delegate Admin privileges to more than user in case that the primary admin cannot fulfil the administrative duties.
A36: Identity IA | B36: Office 365 | C36: More than 5 Tenant Admins | D36: Keep the number of high privileged administrators to a minimum to make the attack surface smaller.
A37: Users AC | B37: Exchange | C37: Inspect Mailbox Permissions | D37: Prevent unlawful information disclosure by regularly reviewing all mailbox permissions to ensure that the only appropriate permissions are set. Unusual or unexpected users or permissions should be investigated immediately. | G37: Get-MailboxFolderPermission
A38: Users AC | B38: Exchange | C38: Disable Remote PowerShell | D38: Remote PowerShell enables you to manage your Exchange Online organization from the command line. By default, all accounts you create in Exchange Online are allowed to use remote Shell to access your Exchange Online organization. You can enable or disable a user’s ability to connect to your Exchange Online organization using remote Shell. Disable PowerShell for all users and applications that do not need it. This will reduce the potential attack surface. Some client-side applications may use PowerShell functionality so perform an assessment before disabling. Skype for Business Online, SharePoint Online, and Azure disable access to PowerShell for non-administrators by default. | F38: Get-Content <text file> | Set-User -RemotePowerShellEnabled $false | G38: Get-User -ResultSize unlimited -Filter {RemotePowerShellEnabled -eq $true}
A39: Users AC | B39: Exchange | C39: Disable E-mail client protocols | D39: Reducing the attack surface of your tenant is important from both a security and a compliance standpoint. Disable un-used client access protocols for Exchange Online to limit the attack surface of your tenant.
A40: Users AC | B40: SharePoint | C40: Manage User Access SharePoint | D40: Understand how SharePoint permissions are built on the concepts of SharePoint groups, Permission levels and Permissions inheritance and site structure. Customize permission settings to better reflect the requirements of your organization. For example, you can stop permission inheritance at a specific location, and you can create new groups and new permission levels.
A41: Users AC | B41: SharePoint | C41: Inspect SharePoint Permissions | D41: Ensure that Site Collection administrators regularly verify that the permissions set on a Site Collection reflect the sensitivity of the content. Permission changes are logged and can be reviewed via the Office 365 activity reports. | F41: Get-SPOUser -Site "https://contoso.sharepoint.com/sites/finance"
A42: Users AC | B42: SharePoint | C42: SharePoint External Users | D42: Keep track of permissions assigned to external parties and review the user profiles associated with the permissions to reduce the risk of data being shared with the wrong party. | F42: Remove-SPOExternalUser | G42: Get-SPOExternalUser, Get-SPOexternaluser -Siteurl https://contoso.sharepoint.com/sites
A57: =COUNTA(A2:A55) -> 41 | H57: =COUNTA(H2:H55) -> 0
A91: =COUNTA(A2:A79) -> 42 | H91: =COUNTA(H2:H79) -> 1

Sheet Data Leakage
A1: Category | B1: Product | C1: Consideration | D1: Description | E1: Portal Configuration | F1: PS Configure | G1: PS Get | H1: Assessed
A2: Phishing ATP | B2: Office 365 | C2: Anti Spam/Phishing/Anti Malware (ATP) | D2: One of the most common causes that accounts and systems are compromised is due to Phishing campaigns. To meet the risks surrounding phishing and malware Office 365 has a robust set of tools to meet these advanced threats. Organizations need to educate users and implement safe guards to meet acceptable risk levels.
A3: Phishing ATP | B3: Exchange | C3: User Education | D3: It is key to educate users about phishing attacks, malicious and unwanted email, and to recognize possible scams. This enables users to determine for themselves what actions to take if they come across a phishing attempt or other similar scam. Internal notifications can help users with identification and early eradication of a threat.
A4: Phishing ATP | B4: Exchange | C4: ATP Protection | D4: Exchange Online Advanced Threat Protection protects mailboxes against new, sophisticated attacks in real-time by protecting against unsafe attachments and malicious links. All suspicious content goes through a real-time behavioral malware analysis that uses machine learning techniques to evaluate the content for suspicious activity. While the content is being scanned, the URLs are rewritten to go through Office 365. The URLs are examined in real time, at the time a user clicks them. Gain critical insights into who is being targeted in your organization and the category of attacks you are facing.
A5: Phishing ATP | B5: Exchange | C5: Detonation Chamber | D5: Exchange Online Advanced Threat Protection protects mailboxes against new, sophisticated attacks in real-time by protecting against unsafe attachments and malicious links. All suspicious content goes through a real-time behavioral malware analysis that uses machine learning techniques to evaluate the content for suspicious activity. Unsafe attachments are sandboxed in a detonation chamber before being sent to recipients.
A6: Phishing ATP | B6: Exchange | C6: Safe Links | D6: Exchange Online Advanced Threat Protection protects mailboxes against new, sophisticated attacks in real-time by protecting against unsafe attachments and malicious links. Safe Links help protect environments when users click a link. While the content is being scanned, the URLs are rewritten to go through Office 365. The URLs are examined in real-time, at the time a user clicks them. If a link is unsafe, the user is warned not to visit the site or informed that the site has been blocked.
A7: Phishing ATP | B7: Exchange | C7: Rich reporting and URL trace capabilities | D7: Exchange Online Advanced Threat Protection protects mailboxes against new, sophisticated attacks in real-time by protecting against unsafe attachments and malicious links. Reports of how your users are accessing different URLs from their mailboxes for getting a clear picture on what type of users are getting targeted. Also, you get details on what messages have been blocked due to unknown viruses or malware. | E7: ECP select mail flow and then url trace
A8: Phishing ATP | B8: Exchange | C8: Exchange Online Protection Configuration Best Practices | D8: Exchange Online Protection (EOP) is a cloud-hosted email filtering service built to protect customers from spam, phishing and malware, and to implement custom policy rules. Proper configuration of EOP is essential to keep out unwanted e-mail and keep the messaging system secure. Follow Microsoft's recommended best practices for configuring EOP features such as anti-spam, anti-malware, phishing and spoofing prevention, and more.
A9: Phishing ATP | B9: Exchange | C9: End User Spam Notification | D9: You can configure end-user spam notifications for the default company-wide content filter policy or for custom content filter policies that are applied to domains. Enabling end-user spam notification messages lets your end users self-manage their own spam-quarantined messages. End-user spam notifications cannot be used with policies applied to users or groups, or to a policy with exceptions.
A10: Phishing ATP | B10: Exchange | C10: Zero-hour Auto Purge (ZAP) | D10: ZAP change the verdict of an unread email from Clean to Spam and move this message from your Inbox to the Junk Email folder. This goes the other way around as well, so if a message was incorrectly marked as Spam (False Negative) and it was moved to Junk Email folder, ZAP will move the message in your Inbox folder. | F10: Set-HostedContentFilterPolicy | G10: Get-HostedContentFilterPolicy
A11: Phishing ATP | B11: Exchange | C11: Advanced spam filtering options | D11: Advanced spam filtering (ASF) options give administrators the ability to inspect various content attributes of a message. The presence of these attributes in a message either increases the spam score of the message (thereby increasing the potential for it to be identified as spam) or marks the message as spam. The ASF options target specific message properties, such as HTML tags and URL redirection, which are commonly found in spam messages. | E11: Protection Spam Filter
A12: Phishing ATP | B12: Exchange | C12: Setup SPF Record | D12: SPF records are TXT records that help to prevent other people from using your domain to send spam or other malicious email. Sender policy framework (SPF) records work by identifying the servers that are authorized to send email from your domain. An email system that receives an email from your domain looks at the SPF record, and if the email server that sent the message was an Office 365 server, the message is accepted. If the server that sent the message was your old mail system or a malicious system on the Internet, the message is considered un-safe. | E12: Select the domain click Find and Fix
A13: Phishing ATP | B13: Exchange | C13: SPF Record: Hard Fail | D13: When this setting is enabled, messages that fail an SPF check (meaning they were sent from an IP address not specified in the SPF record) will be marked as spam. Turning this setting on is recommended for organizations who are concerned about receiving phishing messages. SPF catches the case where the phisher spoofs the 5321 MailFrom. | E13: Navigate to Protection/ Spam filter
A14: Phishing ATP | B14: Exchange | C14: Conditional Sender ID filtering | D14: When this setting is enabled, any message that hard fails a conditional Sender ID check is marked as spam. This option combines an SPF check with a Sender ID check to help protect against message headers that contain forged senders. | E14: Navigate to Protection/ Spam filter
A15: Phishing ATP | B15: Exchange | C15: DKIM | D15: Exchange Online support inbound validation of Domain Keys Identified Mail (DKIM) messages. DKIM is a method for validating that a message was sent from the domain it says it originated from and that it was not spoofed by someone else. It ties an email message to the organization responsible for sending it. DKIM verification is automatically used for all messages sent over IPv6 communications.
A16: Phishing ATP | B16: Exchange | C16: DMARC | D16: DMARC is a technology designed to combat email spoofing and is useful to stop phishing. Specifically, it protects the case where a phisher has spoofed the 5322.From email address, which is the email address displayed in mail clients.
A17: Phishing ATP | B17: Exchange | C17: Top senders and recipients | D17: The top senders and recipients report can provide indications of e-mails being forwarded outside of the organization or other patterns that may indicate leakage of information.
A18: Phishing ATP | B18: Exchange | C18: Malware & SPAM Detections | D18: The malware and SPAM report may provide insight if particular users are more targeted than others within the organization. This may lead to more direct actions to educate the users affected as well as setting stricter Outlook rules.
A19: Phishing ATP | B19: Exchange | C19: Remove Potential Phishing messages | D19: In the case that a phishing campaign has by passed the defenses use the data leakage process to identify and remove the messages from the system. Check flags such as read status to understand how many people may have been exposed.
A20: Phishing ATP | B20: Exchange | C20: PowerShell cmdlets for Phishing and Anti Spam | D20: This is a reference to the PowerShell cmdlets available to configure anti-spam and anti-malware settings in Exchange Online.
A21: Client CM | B21: Client | C21: 10 immutable laws of security | D21: Do not forget the 10 immutable laws of security when you are securing your workstations. Ensure that the appropriate awareness trainings are done and settings that help users to adhere to them are in place.
A22: Client CM | B22: Client | C22: Windows Information Protection (WIP) | D22: Windows Information Protection (WIP), helps to protect against this potential data leakage without otherwise interfering with the employee experience. WIP also helps to protect enterprise apps and data against accidental data leak on enterprise-owned devices and personal devices that employees bring to work without requiring changes to your environment or other apps. Finally, another data protection technology, Azure Rights Management also works alongside WIP to extend data protection for data that leaves the device, such as when email attachments are sent from an enterprise aware version of a rights management mail client.
A23: Client CM | B23: Client | C23: Intune integration with Lookout | D23: You can control access from mobile devices to corporate resources, based on risk assessment conducted by Lookout, a device threat protection solution that is integrated with Microsoft Intune. The risk is based on telemetry that the Lookout service collects from devices for operating system (OS) vulnerabilities, installed malicious apps, and malicious network profiles. Based on Lookout's reported risk assessment enabled through Intune compliance policies, you can configure conditional access policies in Intune and allow or block devices that have been determined to be noncompliant due to threats detected on those devices.
A24: Data Loss DP | B24: Office 365 | C24: Data Loss Prevention (DP) | D24: Data loss prevention (DLP) is an important function for organizations to safeguard theirs and their customer’s information. Office 365 contains a rich feature set that can warn users if they are about to do something that violate policy as well as enforcing policy where necessary.
A25: Data Loss DP | B25: Exchange | C25: Data Loss Prevention Exchange | D25: Data loss prevention (DLP) is an important issue for many customers because of the extensive use of email for business critical communication that includes sensitive data. Exchange Online contains a number of DLP features that help organizations enforce policies, and analyze how users adhere to those policies. | E25: Compliance Management select Data Loss Prevention
A26: Data Loss DP | B26: Exchange | C26: DLP Procedures | D26: Data loss prevention (DLP) includes built-in templates and customizable policies to meet an organization's need to identify sensitive content. DLP policies are simple packages that contain sets of conditions, which are made up of transport rules, actions, and exceptions that you create in the Exchange admin center and then activate to filter email messages and attachments. You can also inform email senders that they may be about to violate one of your policies—even before they send an offending message by configuring Policy Tips. Policy Tips can be configured to present a brief note in Outlook, Outlook on the web, and OWA for devices, that provides information about possible policy violations during message creation. | E26: Compliance Management select Data Loss Prevention
A27: Data Loss DP | B27: Exchange | C27: DLP Policy Templates | D27: You can use data loss prevention (DLP) policy templates to get started with your DLP solution in Exchange Online. A DLP policy template is a model for a policy. You can select a template to begin the process of building your own customized DLP policy. Within your DLP policy, you can customize the rules to ensure that it meets your business needs for data loss prevention. Several policy templates are supplied by Microsoft, but these are not the only way to implement a data loss prevention solution in Exchange. Third-party templates and Windows File Classification Infrastructure templates can be imported to help prevent information from being leaked. | E27: Compliance Management select Data Loss Prevention
A28: Data Loss DP | B28: Exchange | C28: Keyword matching | D28: Data loss prevention (DLP) in Office 365 includes 80 sensitive information types that are ready for you to use in DLP policies. A sensitive information type is defined by a pattern that can be identified by a regular expression or a function. In addition, corroborative evidence such as keywords and checksums can be used to identify a sensitive information type. Confidence level and proximity are also used in the evaluation process. | E28: Compliance Management select Data Loss Prevention
A29: Data Loss DP | B29: Exchange | C29: Regular expression matching | D29: The flexibility of regular expression matching makes this a common choice for implementing matches for data such as driver’s license numbers, addresses and credit card numbers. Common regular expression syntax is used to define the regex patterns. | E29: Compliance Management select Data Loss Prevention
A30: Data Loss DP | B30: Exchange | C30: Structured data fingerprinting | D30: Document Fingerprinting makes it easier for organizations to protect information by identifying standard for Information Protection that are used within the organization. Document Fingerprinting is a Data Loss Prevention (DLP) feature that converts a standard form into a sensitive information type, which you can use to define transport rules and DLP policies. For example, you can create a document fingerprint based on a blank patent template and then create a DLP policy that detects and blocks all outgoing patent templates with sensitive content filled in. | E30: Compliance Management select Data Loss Prevention
A31: Data Loss DP | B31: Exchange | C31: Policy Tip | D31: Policy Tips are informative notices that are displayed to email senders while they’re composing a message. The purpose of the Policy Tip is to educate users that they might be violating the business practices or policies that you are enforcing with the data loss prevention (DLP) policies that organizations have established. | E31: Compliance Management select Data Loss Prevention
A32: Data Loss DP | B32: Exchange | C32: Report attempted Policy Violations | D32: View information about the number of messages that are detected by your data loss prevention (DLP) policies. This includes DLP policy matches and DLP rules matches for sent mail and received mail. You can also view the number of matches, overrides, and false positives for each policy within the past 24 hours in the Exchange Admin Center. | E32: Top DLP Policies
A33: Data Loss DP | B33: Exchange | C33: DLP Matches by Severity for Mail | D33: View information about the number of messages that are detected by your data loss prevention (DLP) policies. This includes DLP policy matches and DLP rules matches for sent mail and received mail. You can also view the number of matches, overrides, and false positives for each policy within the past 24 hours in the Exchange Admin Center. In addition, some reports are grouped by severity. The DLP Matches by Severity for Mail report is an example of a report that groups policy and rule matches based on severity. | E33: Matches based on Severity
A34: Data Loss DP | B34: Exchange | C34: Attachment handling Outlook on the web | D34: Administrators can set up both private and public attachment handling in Outlook on the web depending on how you configure your Outlook on the web mailbox policies. The settings for private (internal) and public (external) networks define how users can open, view, send, or receive attachments depending on whether a user is signed in to Outlook on the web on a computer that is part of a private or of a public network. This setting can be used to restrict access to documents from public networks as an example.
A35: Data Loss DP | B35: Exchange | C35: Attachment handling Exchange ActiveSync | D35: In Office 365, you can create mobile device mailbox policies to apply a common set of policies or security settings to a collection of users. A default mobile device mailbox policy is created in every Office 365 organization. Administrators can create policies to block attachments from being synchronized to mobile devices to limit exposure.
A36: Data Loss DP | B36: SharePoint | C36: Data Loss Prevention SharePoint | D36: Data loss prevention (DLP) in SharePoint Online provides you with a way to identify that data, so you can work with document owners to reduce any risk to your organization. DLP enables organizations to search and report on sensitive content.
A37: Data Loss DP | B37: Office | C37: DLP in Office 2016 applications | D37: Administrators can set up policies for SharePoint Online and OneDrive for Business that automatically apply to Word, Excel and PowerPoint 2016 applications. If users open a sensitive file from SharePoint Online or OneDrive for Business, they will be notified of the sensitive information in context within the Office application. Depending on the policy, the user can simply choose to ignore the policy or be asked to provide a business justification in order to continue working on the sensitive data. Users also have the option of turning off notification policies from within the Office applications. With these advanced capabilities, you will have the ability to create DLP policies across different services while maintaining a productive end-user experience.
A38: Data Loss DP | B38: Office | C38: Policy Tip | D38: Policy Tips are in-context notifications that educate users as soon as potential policy matches are detected while working in Excel, PowerPoint, and Word. For example, if you’re working in a spreadsheet that contains credit card numbers, Excel can notify you about the sensitive information before it is shared with others.
A39: Data Loss DP | B39: Office 365 | C39: Plan for File Classification | D39: File Classification Infrastructure uses classification rules to automatically scan files and classify them according to the contents of the file. Classification properties are defined centrally in Active Directory so that these definitions can be shared across file servers in the organization. You can create classification rules that scan files for a standard string or for a string that matches a pattern (regular expression). When a configured classification parameter is found in a file, that file is classified as configured in the classification rule. When deploying file classification across an organization, start by identifying the information that should be classified and the appropriate classification methods that should be used. Be sure to ensure that you consider any regulations, such as HIPAA, while you are listing the classification requirements.
A40: Data Loss DP | B40: Office 365 | C40: Azure Information Protection Classification | D40: Classify data based on source, context, and content at the time of creation or modification, either automatically or manually. Once classified, a persistent label is embedded in the data and actions such as visual marking and encryption can be taken based on the classification and label.
A41: Data Loss DP | B41: SharePoint | C41: Site classification feature | D41: Using the new site classification feature, you can apply a custom label to a SharePoint site and its associated Office 365 group. The label identifies the sensitivity of the information for the site and group. The site classification appears in the header of the site and group pages and serves as a reminder to users that your organization has guidance regarding the use and sharing of information on the site.
A42: Preserve DP | B42: SharePoint | C42: File Server Ingestion | D42: Because shared files are widely distributed across networks it is hard to identify key intellectual property but it also poses a risk in case of litigation. You can use the Microsoft Office 365 Import service to migrate files from your on-premises file shares or from your own premises SharePoint Server site. | E42: Office 365 Portal Import
A43: Encryption DP | B43: Office 365 | C43: Encryption of information (DP) | D43: The Information Encryption category covers the set of features in Office 365 that can be used to encrypt your data.
A44: Encryption DP | B44: Azure Information Protection | C44: Azure Information Protection | D44: Use Microsoft Azure Rights Management (Azure Information Protection) to help you protect your organization’s sensitive information from unauthorized access, and control how this information is used. Rights Management uses encryption, identity, and authorization policies to help secure your files and email. For example, you can configure a file so that it can be accessed only by people in your organization, or control whether the file can be edited, or restricted to read-only, or prevent it from being printed. You can configure emails similarly, and in addition, prevent them from being forwarded or prevent the use of the Reply All option. | E44: Portal Azure Information Protection | G44: Get-AadrmConfiguration
A45: Encryption DP | B45: Azure Information Protection | C45: Azure Information Protection Departmental Templates | D45: With Microsoft Azure Rights Management Services (Azure Information Protection), users are able to apply default templates that make it easy for them to apply policies to sensitive files that restrict access to authorized users in your organization. In addition, the Information Protection sharing application (https://technet.microsoft.com/library/dn339006.aspx) lets users define their own set of permissions. And, for the Outlook client and Outlook Web Access, users can select the Do Not Forward option for email messages.
A46: Encryption DP | B46: Azure Information Protection | C46: Revoke Access to protected documents | D46: After you have protected your documents by using the Azure Active Directory Rights Management Services (Information Protection) sharing application, you can track how people are using your protected documents, and if necessary, revoke access to them when you want to stop sharing. You can do this using the document tracking site, which can be accessed from Windows computers, Mac computers, and even from tablets and phones. After an appropriate period of time, users should revoke access to sensitive information that has been shared to protect the information from potential leakage.
A47: Encryption DP | B47: Azure Information Protection | C47: Expire documents after # days | D47: When sharing information, users should set an expiration date to prevent access to time-sensitive material. Time-sensitive files should not be able to be opened after a date that you specify. You will still be able to open the original file but after midnight (your current time zone) on the day that you specify, others will not be able to open the file.
A48: Encryption DP | B48: Azure Information Protection | C48: Bring your own key | D48: By default, Azure Information Protection generates your tenant key and manages most aspects of the tenant key lifecycle. This is the simplest option with the lowest administrative overheads. Alternatively, your organization might require complete control over your tenant key, which involves creating your tenant key and keeping the master copy on your premises. This scenario is often referred to as bring your own key (BYOK). BYOK works seamlessly with every application that integrates with Azure Information Protection. This includes cloud services such as SharePoint Online, on-premises servers that run Exchange and SharePoint that work with Azure Information Protection by using the Information Protection connector, and client applications such as Office 2013 and Office 2016. Azure Information Protection BYOK is not compatible with Exchange Online. If you want to use Exchange Online, we recommend that you deploy Azure Information Protection in the default key management mode now, where Microsoft generates and manages your key. You have the option to move to BYOK later, for example, when Exchange Online does support Azure Information Protection BYOK.
A49: Encryption DP | B49: Azure Information Protection | C49: Azure Information Protection Supported Clients | D49: To effectively use an encryption solution broad client support is required. Not all supported client devices currently support all Azure Active Directory Rights Management Services (Information Protection) capabilities. Information Protection supports computers running Windows 7 and higher, Mac OS X 10.8 and higher, Windows Phone 8.1 and higher, Android 4.0.3 and higher, and iOS 7 and higher on iPad and iPhone.
A50: Encryption DP | B50: Azure Information Protection | C50: SharePoint Information Protection Integration | D50: Within SharePoint, information right management (IRM) protection is applied to files at the list and library level. Before your organization can use IRM protection, you must first set up Azure Active Directory Rights Management Services (Information Protection). SharePoint Online IRM relies on Information Protection to encrypt and assign usage restrictions. You can for example protect content stored in SharePoint site collections using Information Protection. This protects lawfully-downloaded information from leakage independently of storage.
A51: Encryption DP | B51: Azure Information Protection | C51: Exchange Information Protection Integration | D51: To help prevent information leakage, Exchange Online includes information rights management (IRM) functionality that provides online and offline protection of email messages and attachments. IRM protection can be applied by users in Outlook and Outlook on the web, and it can be applied by administrators using transport protection rules or Outlook protection rules. IRM helps you and your users control who can access, forward, print, or copy sensitive data within an email. It provides online and offline protection of email messages and attachments, and allow users to control who can access, forward, print, or copy sensitive data within an email.
A52: Encryption DP | B52: Office 365 | C52: Enhanced Encryption with customer keys | D52: In 2016, we expect to enable customers to generate and control their own keys for encrypting content in Office 365.
A53: Encryption DP | B53: Exchange | C53: Exchange | D53: Exchange online provide several enterprise level features for encryption that help organizations meet encryption needs for B2B, B2C as well as corporate information.
A54: Encryption DP | B54: Exchange | C54: Exchange TLS encryption | D54: Exchange Online servers always encrypt connections to other Exchange Online servers in our datacenters with TLS 1.2. When you send mail to a recipient that is within your Office 365 organization, that email is automatically sent over a connection that is encrypted using TLS. Also, all email you send to other Office 365 customers are sent over connections that are encrypted using TLS and are secured using Perfect Forward Secrecy. By default, Exchange Online always uses opportunistic TLS. This means Exchange Online always tries to encrypt connections with the most secure version of TLS first, then works its way down the list of TLS ciphers until it finds one on which both parties can agree. Unless you have configured Exchange Online to ensure that messages to that recipient are only sent through secure connections, then by default the message will be sent unencrypted if the recipient organization doesn’t support TLS encryption. Opportunistic TLS is sufficient for most businesses. However, for business that have compliance requirements such as medical, banking, or government organizations, you can configure Exchange Online to require, or force, TLS. | E54: Go To Mail Flow and choose Connectors
A55: Encryption DP | B55: Exchange | C55: Partner Connector | D55: You can create connectors to apply security restrictions to mail exchanges with a partner organization or service provider. A partner can be an organization you do business with, such as a bank. It can also be a cloud email service provider that provides services such as archiving, anti-spam, and so on. For example. you can create a connector to enforce encryption via transport layer security (TLS). You can also apply other security restrictions such as specifying domain names or IP address ranges that your partner organization sends mail from. A partner connector provides the option to encrypt all traffic with partner organizations to avoid disclosure of information. | E55: Go To Mail Flow and choose Connectors
A56: Encryption DP | B56: Exchange | C56: S/MIME Message Signing and Encryption | D56: S/MIME (Secure/Multipurpose Internet Mail Extensions) is a widely accepted method, or more precisely a protocol, for sending digitally signed and encrypted messages. S/MIME allows you to encrypt emails and digitally sign them. When you use S/MIME with an email message, it helps the people who receive that message to be certain that what they see in their inbox is the exact message that started with the sender. Use S/MIME for cryptographic security services such as authentication, message integrity, and non-repudiation of origin (using digital signatures). It can also help enhance privacy and data security (using encryption) for electronic messaging.
A57: Encryption DP | B57: Exchange | C57: Office 365 Message Encryption | D57: Office 365 Message Encryption is an easy-to-use service that lets email users send encrypted messages to people inside or outside their organization. Designated recipients can view encrypted messages and return encrypted replies. Regardless of the destination email service—whether it’s Outlook.com, Yahoo, Gmail, or another service—email users can send confidential business communications with an added level of protection against unauthorized access. This allows for enterprise content inspection and it enables you to adhere to compliance policies. | E57: Go To Mail Flow and choose Rules
A58: Encryption DP | B58: Office | C58: Office Encryption | D58: Office contains settings that let you control the way that data is encrypted when you use Access, Excel, OneNote, PowerPoint, Project, and Word. Private keys can be stored in a centralized vault to allow for decryption if password is forgotten or if a user leaves the company.
A59: Incident IR | B59: Office 365 | C59: Data spillage | D59: Data spillage is when data is shared or transmitted against an organization or business policy. The data can be subject to a non-disclosure agreement, personally identifiable information, or other classified or unclassified data that has been distributed in an unauthorized manner. For example, a government agency mistakenly transmits classified data within an unclassified system or a commercial customer has a disgruntled employee who transmits company data against policy.
A60: Incident IR | B60: Office 365 | C60: Data Spillage E-mail compliance search | D60: Organizations can use the Compliance Search feature in Office 365 to search and remove an email message from all mailboxes in the organization. You can search and remove an email message from all mailboxes in your organization. This can help you find and remove potentially harmful or high-risk email, such as messages that contain dangerous attachment or virus, phishing messages, and messages that contain sensitive data. | F60: New-ComplianceSearchAction | G60: Get-ComplianceSearchAction
A61: Incident IR | B61: Exchange | C61: Data spillage Exchange | D61: You can use the Content Search feature in Office 365 to search for and delete an email message from all mailboxes in your organization. This can help you find and remove the spilled information that contain sensitive data.
A62: Incident IR | B62: SharePoint | C62: Data spillage SharePoint Compliance Search | D62: Compliance Search in the Office 365 Compliance Center can be used to search mailboxes, SharePoint Online sites, and OneDrive for Business locations in your Office 365 organization. Compliance Search is a new eDiscovery search tool with new and improved scaling and performance capabilities.
A63: Incident IR | B63: SharePoint | C63: SharePoint Recycle Bin | D63: It may be necessary to clean up the SharePoint recycle bin for the affected Site Collections in the case of a spillage of sensitive information. You have access to two recycle bin stages, a first-level Recycle Bin, and a Second-Stage Recycle Bin. This gives you greater control when users delete files, versions of files, list items, libraries, lists, and folders from a SharePoint site by providing a two-stage safety net before an item is permanently deleted from a site.
A64: Network NS | B64: Office 365 | C64: Network Services | D64: Office 365 provides secure networking out of the box by providing strong transport encryption mechanisms for service connections. In this section we list a few of the additional features organizations may decide to implement.
A65: Network NS | B65: Office 365 | C65: Express Route | D65: ExpressRoute provides organizations with dedicated network connectivity through a private connection from their network to Office 365. With ExpressRoute most Office 365 network traffic avoid the public Internet, providing additional data privacy.
A66: Network NS | B66: Office 365 | C66: IP,URL Filtering | D66: If your organization restricts computers on your network from connecting to the Internet, this article lists the endpoints (FQDNs, IPv4, and IPv6 address ranges) that you should include in your outbound allow lists and Internet Explorer Trusted Sites Zone of client computers to ensure your computers can successfully use Office 365. FQDN allow lists are the recommended approach due to the modern web architecture of Office 365. FQDN allow lists are the recommended approach due to the modern web architecture of Office 365.
A67: Network NS | B67: OnPrem | C67: Filter Traffic to ADFS servers | D67: Some organizations may want to block access from the internet to their tenant and not allow direct password attempts through the external facing ADFS server. Not permitting Office 365 access from unknown network sources can be controlled by Client Policies, it doesn't however prevent external users from submitting passwords to the ADFS infrastructure. It is possible to block all internet access except the Microsoft Online services to access the ADFS service. With modern authentication organizations may choose to not setup an ADFS proxy and only allow clients with access to the corporate network to receive tokens. Note that this should be thoroughly tested before implementation, please see the most current documentation for supported clients as well as administrative interfaces.
A68: Network NS | B68: OnPrem | C68: Limit access to VPN/Direct Access/Local Networks | D68: Organizations that is using VPN or Direct Access configured can limit access to Office 365 based on conditional access rules based on the IP scopes used by the organization.
A69: Users AC | B69: Office 365 | C69: Access Control Users (AC) | D69: The Access Control Users category covers the aspects of a trusted user model that is different from the model used for admins. Scenarios to make users productive are not purely ACL-based but contain a number of settings that can be used by organizations to adhere to their information security policies.
A70: Users AC | B70: Exchange | C70: Exchange | D70: Use the rich set of access control features in Exchange Online to help your organization prevent data leakage and unlawful access to data.
A71: Users AC | B71: Exchange | C71: Review forwarding being setup | D71: Regularly review all email forwarding settings to detect fraudulent activity. Email forwarding lets you to set up a mailbox to forward email messages sent to that mailbox to another user’s mailbox in or outside of your organization. But it's a method commonly used by hackers and malicious individuals to steal data and create and maintain a foothold in the environment. | G71: Get-Mailbox |{$_.ForwardingSMTPAddress -ne $null} |fl ForwardingSMTPAddress,DeliverToMailboxandForward, Get-InboxRule
A72: Users AC | B72: Exchange | C72: Restrict forwarding | D72: Control email forwarding by configuring remote domains. This enables you to reduce risk by forwarding email only to trusted domains. When you set a remote domain, you can control mail flow with more precision, specify message formatting and policy, and specify acceptable character sets for messages sent to or received from the remote domain. | E72: Mailflow Remote Domains | F72: Set-RemoteDomain | G72: Get-RemoteDomain
A73: Users AC | B73: Exchange | C73: Exchange External Sharing | D73: With Office 365, administrators can set up different levels of calendar access in Exchange Online to allow businesses to collaborate with other businesses and to let users share their schedules with others. Business-to-business calendar sharing is set up by creating organization relationships. User-to-user calendar sharing is set up by applying sharing policies. Regularly monitor all external sharing and sharing policies to ensure that they are appropriate, and to prevent the unwanted disclosure of sensitive data outside your organization. | E73: Portal External Sharing | G73: Get-OrganizationRelationship
A74: Users AC | B74: Exchange | C74: Exchange Address Book Policies | D74: Address book policies (ABPs) segment users into specific groups to provide customized views of your organization’s global address list (GAL). When creating an ABP, you assign a GAL, an offline address book (OAB), a room list, and one or more address lists to the policy. You can then assign the ABP to mailbox users, providing them with access to a customized GAL in Outlook and Outlook on the web. The goal is to provide a simpler mechanism to accomplish GAL segmentation for on-premises organizations that require multiple GALs. Use ABPs to maintain a degree of isolation if your organization does not want users to search for people in other business units.
A75: Users AC | B75: Exchange | C75: Mail-enabled security groups | D75: A mail-enabled security group can be used to distribute messages as well as to grant access permissions to resources in Active Directory. You can manage access to information by leveraging the approval flows for sending messages and adding members within mail-enabled security groups.
A76: Users AC | B76: SharePoint | C76: SharePoint Permission Strategy | D76: Develop a permissions strategy to keep the environment manageable and secure. An effective permissions strategy will enhance the manageability and performance of your site, ensure compliance with your organization’s data governance policies, and minimize the cost of maintenance for you and your organization.
A77: Users AC | B77: SharePoint | C77: Hide Users in the People Picker | D77: Configure the People Picker options hide certain groups from being displayed, and prevent users from searching for other users in high-security or isolated environments. | F77: Set-SPOTenant | G77: Get-SPOTenant
A78: Users AC | B78: SharePoint | C78: SharePoint External Sharing | D78: Set up an External Sharing Policy within the organization that includes which sites can be shared externally, with whom, and how. Regularly review which sites are shared externally and ensure that they are hosting content that can be shared with external parties. | E78: Portal External Sharing | F78: Set-SPOSite -SharingCapability, Set-SPOTenant -SharingCapability | G78: Get-SPOSite, Get-SPOTenant
A79: Users AC | B79: SharePoint | C79: Monitor External Sharing invitations | D79: In regulated industries, it’s often important to audit every conversation with external parties – including any text users add to their external sharing invitations. SharePoint Online has the ability to blind copy the full text of invitation emails to a dedicated archive mailbox. | F79: Set-SPOTenant -BccExternalSharingInvitations -BccExternalSharingInvitationsList | G79: Get-SPOTenant
A80: Users AC | B80: SharePoint | C80: SharePoint Guest Links | D80: Regularly check guest links generated in the system to ensure that they only publish information with the appropriate classification. You can use the Search feature in the Compliance Center to search for documents stored on SharePoint and OneDrive for Business sites that have been shared with people outside of your organization | E80: Portal External Sharing
A81: Users AC | B81: SharePoint | C81: Restrict External Sharing Invites to the E-mail address sent to | D81: If your organization performs Information Protection work that involves sharing documents or collaborating directly with vendors, clients, or customers, then you might want to use the external sharing features of SharePoint Online to share content with people outside your organization who do not have licenses for Office 365. See https://support.office.com/en-us/article/Manage-external-sharing-for-your-SharePoint-Online-environment-c8a462eb-0723-4b0b-8d0a-70feafe4be85 for more information about external sharing. When sharing information externally, consider requiring external users who have received invitations to sign-in with a Microsoft account before they can access the content. | F81: Set-SPOTenant -RequireAcceptingAccountMatchInvitedAccount | G81: Get-SPOTenant
A82: Users AC | B82: SharePoint | C82: Restrict OneDrive for Business synchronization to trusted domains | D82: Enable OneDrive for Business file sync to work only on Active Directory domain-joined computers, and specify which of your domains you want to allow to sync. The Set-SPOTenantSyncClientRestriction cmdlet enables the feature for a tenant and sets the domain GUIDs in the safe recipients. This blocks file sync on personally-owned and unmanaged PCs. | F82: Set-SPOTenantSyncClientRestriction | G82: Get-SPOTenantSyncClientRestriction
A83: Users AC | B83: Skype4B | C83: Restrict Skype for Business communication with external parties | D83: Investigate if your organization needs to implement restrictions on external communications. If necessary, disable the ability for your users to use Skype for Business to contact people in other organizations. | E83: Portal External Sharing
A96: =COUNTA(A2:A83) -> 82 | H96: =COUNTA(H2:H94) -> 0
A130: =COUNTA(A2:A118) -> 83 | H130: =COUNTA(H2:H118) -> 1

Sheet Security & Compliance
A1: Category | B1: Product | C1: Feature | D1: Description | E1: Portal | F1: PS Configure | G1: PS Get | H1: Assessed
A2: Auditing AU | B2: Office 365 | C2: Auditing (AU) | D2: The Auditing category covers key aspects of information security that enable examination and re-creation of events. Auditing allow organizations to solve issues as well as to detect and investigate security issues and incidents. If reviewing this from the FedRAMP view please go to the full Customer Security Considerations view.
A3: Auditing AU | B3: AzureAD | C3: Azure AD | D3: Use Azure Active Directory (Azure AD) access and usage reports to gain visibility into the integrity and security of your organization’s directory. With this information, a directory admin can better determine where possible security risks may lie so that they can adequately plan to mitigate those risks. Audit all account actions and use Azure AD reports to identify potential fraudulent activities.
A4: Auditing AU | B4: AzureAD | C4: Azure AD Audit Events | D4: Identify privileged actions that occur in Azure Active Directory, including elevation changes, password changes, and so forth. Automate this process by consuming the security audit feed with a Security Information and Event Management system. (SIEM)
A5: Auditing AU | B5: AzureAD | C5: Review Sign-Ins from unknown sources | D5: Use this report to identify users who have successfully signed in to your organization while assigned a client IP address that has been recognized by Microsoft as an anonymous proxy IP address. These proxies are often used by users who want to hide their computer’s IP address.
A6: Auditing AU | B6: AzureAD | C6: Review Sign-ins after multiple failures | D6: Use this report to identify users who have successfully signed in after multiple consecutive failed sign-in attempts.
A7: Auditing AU | B7: AzureAD | C7: Review Signs-ins from multiple geographies | D7: Use this report to identify successful sign-in activities from a user where two sign ins appeared to originate from different countries and the time between the sign ins makes it impossible for the user to have travelled between those countries.
A8: Auditing AU | B8: AzureAD | C8: Review AAD Logons for Anomalies | D8: Indicates users whose accounts may have been compromised.
A9: Auditing AU | B9: Exchange | C9: Exchange | D9: Leverage the rich set of auditing features in Exchange Online to audit administrator, user, application, and external user access. For example, you can use audit logging to troubleshoot configuration issues by tracking specific changes made by administrators, and to help you meet regulatory, compliance, and litigation requirements. Exchange Online includes both administrator audit logging and mailbox audit logging. These logs can help you determine who has accessed a mailbox and what they’ve done.
A10: Auditing AU | B10: Exchange | C10: Exchange Online Privileged Administrator changes | D10: You can search the administrator audit logs to discover who made changes to organization, server, and recipient configuration. This can be helpful when you're trying to track the cause of unexpected behavior, to identify a malicious administrator, or to verify that compliance requirements are being met. Regularly review all changes to privileged role groups to detect potentially harmful changes.
A11: Auditing AU | B11: Exchange | C11: {=[1]!'!CSC Main!R44C3'} -> #REF! | D11: These are the activities that can be logged by mailbox audit logging and searched through the Audit Log Search, by default mailbox audit logging is not turned on. Copied messages to another folder, Created item, Deleted messages from Deleted Items folder, Moved messages to another folder, Moved messages to Deleted Items folder, Purged messages from the mailbox, Sent message using Send As permissions, Sent message using Send On Behalf permissions, Updated message, User signed in to mailbox
A12: Auditing AU | B12: Exchange | C12: Detect non-owner mailbox access | D12: Audit non-owner access activity to identify potential leaks of information and to proactively review non-owner access to mailboxes. The Non-Owner Mailbox Access Report in the Exchange Admin Center lists the mailboxes that have been accessed by someone other than the person who owns the mailbox. When a mailbox is accessed by a non-owner, Exchange logs information about this action in a mailbox audit log that’s stored as an email message in a hidden folder in the mailbox being audited. Entries from this log are displayed as search results and include a list of mailboxes accessed by a non-owner, who accessed the mailbox and when, the actions performed by the non-owner, and whether the action was successful. By default, entries in the mailbox audit log are retained for 90 days. | F12: Get-Mailbox -ResultSize Unlimited -Filter {RecipientTypeDetails -eq "UserMailbox"} | Set-Mailbox -AuditEnabled $true | G12: Get-Mailbox | FT Name,AuditEnabled
A13: Auditing AU | B13: Exchange | C13: Detect changes to eDiscovery and legal hold | D13: Your organization may require all mailbox data to be preserved for a specific period. You can use Litigation Hold or In-Place Hold to meet this requirement. After you place a mailbox on Litigation Hold or In-Place Hold, mailbox items that are modified or that are permanently deleted are preserved in the Recoverable Items folder. Use the hold report to keep track of when Hold is enabled or disabled in a given time period. For each of these change types, the report includes the user who made the change and the time and date the change was made. Regularly review the report to audit changes to eDiscovery and Hold settings to ensure that users that should be under Hold remain under Hold.
A14: Auditing AU | B14: Exchange | C14: List mailboxes under hold | D14: Your organization may require all mailbox data to be preserved for a specific period. You can use Litigation Hold or In-Place Hold to meet this requirement. After you place a user on Litigation Hold or In-Place Hold, mailbox items that are modified or that are permanently deleted are preserved in the Recoverable Items folder. If your organization is required to keep users under Hold, regularly review the Hold report to audit changes to settings.
A15: Auditing AU | B15: Exchange | C15: Review configuration changes in organization | D15: You can use the Exchange Admin Center to search for and view entries in the administrator audit log. The administrator audit log records specific actions, based on Exchange Management Shell cmdlet, performed by administrators and users who have been assigned administrative privileges. Entries in the administrator audit log provide you with information about what cmdlet was run, which parameters were used, who ran the cmdlet, and what objects were affected. Regularly review all configuration changes to ensure that only valid and approved changes have been made to the organization's settings. | G15: Get-AdminAuditLogConfig | FL AdminAuditLogEnabled
A16: Auditing AU | B16: Exchange | C16: Review mailbox access by datacenter administrators | D16: In Exchange Online, actions performed by Microsoft and delegated administrators are logged in the administrator audit log. You can use the Exchange Admin Center or PowerShell to search for and view audit log entries to determine if external administrators performed any actions on or changed the configuration of your Exchange Online organization. You can also use PowerShell to export these audit log entries. Regularly audit all activities performed by external administrators, including Microsoft service administrators. | G16: Search-AdminAuditLog -ExternalAccess $true
A17: Auditing AU | B17: Office 365 | C17: Office 365 User administration activities | D17: These are the administration activities that are logged when an admin adds or changes a user account. Added user, Changed user license, Changed user password, Deleted user, Reset user password, Set property that forces user to change password, Set license properties, Updated user. These activities can be used to review administrator activity on a regular basis to ensure that the activities performed are in accordance to organizational principles.
A18: Auditing AU | B18: Office 365 | C18: Office 365 Group administration activities | D18: Search these logs to identify activities related to an admin or a user creates or changes an Office 365 group or when an admin creates a security group. The activities logged are Added group, Added member to group, Deleted group, Removed member from group, Updated group
A19: Auditing AU | B19: Office 365 | C19: Application administration activities | D19: When an administrator adds or changes an application that's registered in Azure AD these activities are logged. Added delegation entry, Added service principal, Added service principal credentials, Removed delegation entry, Removed service principal, Removed service principal credentials, Set delegation entry. Keeping track of these entries are important since applications can be used to access customer data hence a rouge admin could use applications in an attempt to circumvent security. Both the registration of applications and actions carried by the applications like accessing customer data are logged.
A20: Auditing AU | B20: Office 365 | C20: Office 365 Role administration activities | D20: It is important to keep track of the Azure AD roles in Office 365 to detect potential attempts to elevate permissions. The role administration logging is logging the following activities Add member to Role, Removed a user from a directory role, Set company contact information.
A21: Auditing AU | B21: Office 365 | C21: Directory administration activities | D21: These are the Azure AD directory and domain related activities that are logged when an administrator manages admin roles. Added domain to company, Added partner to company, Removed domain from company, Removed partner from company, Set company information, Set domain authentication, Set federation settings on the domain, Set password policy, Turned on Azure AD sync, Updated domain, Verified domain, Verified email verified domain. These activities are important to ensure that delegation to partner as an example is not done without prior approval.
A22: Auditing AU | B22: Office 365 | C22: Search for eDiscovery activities | D22: Content Search and eDiscovery-related activities that are performed in Office 365 Security & Compliance Center or by running the corresponding Windows PowerShell cmdlets are logged in the Office 365 audit log. The following tasks are logged, Creating and managing eDiscovery cases, Creating, starting, and editing Content Searches, Performing Content Search actions, such as previewing, exporting, and deleting search results, Configuring permissions filtering for Content Search, Managing the eDiscovery Administrator role
A23: Auditing AU | B23: SharePoint | C23: SharePoint (Activity Report) | D23: Regularly review the Office 365 Activity Report in the Compliance Center to review user and administrator activity in your Office 365 tenant. The report contains entries for activity in Exchange Online, SharePoint Online, and OneDrive for Business, and administrator activity reports in Azure Active Directory.
A24: Auditing AU | B24: SharePoint | C24: File and folder activities | D24: This section of the reporting capture the file and folder activities in SharePoint Online and OneDrive for Business such as, Accessed file, Checked in file, Checked out file, Copied file, Deleted file, Discarded file checkout, Downloaded file, Modified file, Moved file, Renamed file, Restored file, Uploaded file. These can be invaluable to detect potential fraudulent behavior. | F24: Search-UnifiedAuditLog, Set-UnifiedAuditSetting | G24: Get-UnifiedAuditSetting
A25: Auditing AU | B25: SharePoint | C25: Sharing and access request activities | D25: The user sharing and access request activities in SharePoint Online and OneDrive for Business provide insight in to the key areas like Accepted access request, Accepted sharing invitation, Created a company-wide link, Created access request, Created an anonymous link, Created sharing invitation, Denied access request , Removed a company-wide link, Removed an anonymous link, Shared file, folder, or site, Updated an anonymous link, Used an anonymous link, Unshared file, folder, or site, Used a company-wide link, Withdrew sharing invitation. | F25: Search-UnifiedAuditLog, Set-UnifiedAuditSetting | G25: Get-UnifiedAuditSetting
A26: Auditing AU | B26: SharePoint | C26: Synchronization Activities | D26: This category is used to track file synchronization activities in SharePoint Online and OneDrive for Business. It track tasks such as, Allowed computer to sync files, Blocked computer from syncing files, Downloaded files to computer, Downloaded file changes to computer, Uploaded files to document library, Uploaded file changes to document library | F26: Search-UnifiedAuditLog, Set-UnifiedAuditSetting | G26: Get-UnifiedAuditSetting
A27: Auditing AU | B27: SharePoint | C27: Site administration activities | D27: The list of audited site administration tasks in SharePoint Online is rich and can be used to detect unwanted changes in the SharePoint configuration. Added exempt user agent, Added site collection administrator, Added user to group, Allowed user to create groups, Changed exempt user agents, Changed a sharing policy, Created group, Created Sent To connection, Created site collection, Deleted group, Deleted Sent To connection, Enabled document preview, Enabled legacy workflow, Enabled Office on Demand, Enabled RSS feeds, Enabled result source for People Searches, Modified site permissions, Removed user from group, Removed user from site collection, Renamed site, Requested site admin permissions, Set host site, Updated group | F27: Search-UnifiedAuditLog, Set-UnifiedAuditSetting | G27: Get-UnifiedAuditSetting
A28: Auditing AU | B28: SharePoint | C28: SharePoint Search queries Log | D28: In case of a breach, review the keywords that have been used in searches to help identify the information being sought.
A29: Auditing AU | B29: Azure Information Protection | C29: Azure Information Protection Logging | D29: Use the Azure Active Directory Rights Management Services (Information Protection) logs to audit requests, including requests from users, actions performed by Information Protection administrators in organizations, and actions performed by Microsoft operators to support Information Protection deployments. Information Protection writes logs in W3C extended log format into an Azure storage account that you provide. Information Protection logging information is available to you in near-real time, so that you can continuously monitor your company’s use of Information Protection . 99.9% of logs are available within 15 minutes of an Information Protection-initiated action. For example, you might want to be alerted if there is a sudden increase of people reading Information Protection-protected data outside standard working hours, which could indicate that a malicious user is collecting information to sell to competitors. Or, if the same user apparently accesses data from two different IP addresses within a short time frame, which could indicate that a user account has been compromised. If you have an information leak, you are likely to be asked who recently accessed specific documents and what information did a suspected person access recently. You can answer these type of questions when you use Information Protection and logging because people who use protected content must always get an Information Protection license to open documents and pictures that are protected by Information Protection, even if these files are moved by email or copied to USB drives or other storage devices. This means that you can use Information Protection logs as a definitive source of information for forensic analysis when you protect your data by using Information Protection. | F29: Enable-AadrmUsageLogFeature | G29: Get-AadrmConfiguration
A30: Auditing AU | B30: Azure Information Protection | C30: Track Protected Documents | D30: After you have protected your documents by using the Azure Active Directory Rights Management Services (Information Protection) sharing application, you can track how people are using your protected documents, and if necessary, revoke access to them when you want to stop sharing. To do this, you use the document tracking site, which you can access from Windows computers, Mac computers, and even from tablets and phones. Use Azure Active Directory Information Protection to track usage of protected information. Senders can view which recipients have opened file(s), information about unauthorized access attempts, and view the most recent state of the file.
A31: Auditing AU | B31: Azure Information Protection | C31: Detect viewing of documents centrally | D31: Use the Azure Active Directory Rights Management Services (Information Protection) logs to audit requests, including requests from users, actions performed by Information Protection administrators in organizations, and actions performed by Microsoft operators to support Information Protection deployments. Information Protection writes logs in W3C extended log format into an Azure storage account that you provide. Azure Active Directory Rights Management Services (Information Protection) logging can help you detect the use of protected information that may be out of policy or for forensic investigations. You can automate this process by consuming the security audit feed with a Security Information and Event Management system.
A32: Auditing AU | B32: Office 365 | C32: Office 365 Activity API | D32: The Office 365 Management APIs provide a single extensibility platform for all Office 365 customers’ and partners’ management tasks, including service communications, security, compliance, reporting, auditing, user management, and reseller management. All of the Office 365 Management APIs will be consistent in design and implementation with the current suite of Office 365 REST APIs, using common industry-standard approaches, including OAuth v2, OData v4, and JSON. Like the other Office 365 APIs, applications are registered in Azure Active Directory, giving developers a consistent way to authenticate and authorize their apps.
A33: Auditing AU | B33: Office 365 | C33: Office 365 Management Audit Log | D33: You can use the Office 365 activity report in the Office 365 Compliance Center to view user and admin activity in your Office 365 organization. The report contains entries for admin activity (admin audit logging) and access to mailboxes (mailbox audit logging) in Exchange Online, user and admin activity in SharePoint Online and OneDrive for Business, and admin activity and user sign-in activity in Azure Active Directory. Use the Office 365 Activity API to consume a feed of activity data from Office 365 to your on-premises Security Information and Event Management solution.
A34: Auditing AU | B34: Office 365 | C34: Microsoft Operators | D34: Microsoft Data Center Operator events can be identified by the UserType member being set to 3. This allow for organizations to specifically monitor the access and changes made by Microsoft Operators.
A35: Auditing AU | B35: Office 365 | C35: Applications | D35: Access made by Applications deployed in the tenant can be identified by the UserType Value being set to 5 or 6. This allow for organizations to monitor applications and their behavior.
A36: Auditing AU | B36: OnPrem | C36: Performance Monitoring | D36: Active Directory Federation Services (AD FS) includes its own dedicated performance counters to help you monitor the performance of both federation servers and federation server proxy computers. Configure performance monitoring for AD FS and keep track of suspicious log on patterns for on-premises accounts.
A37: Auditing AU | B37: OnPrem | C37: Advanced Threat Analytics | D37: Microsoft Advanced Threat Analytics (ATA) helps you identify breaches and threats using behavioral analysis and provides a clear, actionable report on a simple attack timeline. It's a simple and fast way to understand what is happening within your network by identifying suspicious user and device activity with built-in intelligence and providing clear and relevant threat information on a simple attack timeline. ATA leverages deep packet inspection technology, as well as information from additional data sources (Security Information and Event Management and Active Directory) to build an Organizational Security Graph and detect advanced attacks in near real time. Use advanced threat analytics such as behavioral analysis to detect potential threats in your environment.
A38: Auditing AU | B38: OnPrem | C38: Azure AD Connect Health | D38: Azure AD Connect Health helps you monitor and gain insight into your on-premises identity infrastructure and the synchronization services available through Azure AD Connect. It offers you the ability to view alerts, performance, usage patterns, configuration settings, enables you to maintain a reliable connection to Office 365 and much more. Use Azure AD Connect to monitor the state of directory integration between your on-premises environment and Office 365.
A39: Auditing AU | B39: Exchange | C39: Exchange Online Protection Auditing Reports | D39: Auditing reports in Microsoft Exchange Online Protection (EOP) can help you meet regulatory, compliance, and litigation requirements for your organization. You can obtain auditing reports at any time to determine the changes that have been made to your EOP configuration. These reports can help you troubleshoot configuration issues or find the cause of security-related or compliance-related problems. Regularly review EOP audit reports to support security and compliance-related work.
A40: Auditing AU | B40: Exchange | C40: Exchange Online Protection Privileged Admin Changes | D40: When an administrator adds members to or removes members from administrator role groups, Microsoft Exchange Online Protection logs each occurrence. When you run an administrator role group report in the Exchange Admin Center, entries are displayed as search results and include the role groups affected, who changed the role group membership and when, and what membership updates were made. Use this report to monitor changes to the administrative permissions assigned to users in your organization. Regularly review all changes to privileged role groups to detect potentially harmful changes.
A41: Auditing AU | B41: Exchange | C41: Exchange Online Protection Administrator Audit Log | D41: In Exchange Online Protection (EOP) and Exchange Online, you can use the Exchange Admin Center to search for and view entries in the administrator audit log. The administrator audit log records specific actions performed by administrators and users who have been assigned administrative privileges. Entries in the administrator audit log provide you with information about what cmdlet was run, which parameters were used, who ran the cmdlet, and what objects were affected. Regularly review all changes to EOP configuration settings, especially those that affect mail flow.
... A58: Delete DM | B58: Office 365 | C58: Delete (DM) | D58: Organizations need to determine retention policies based on regulatory and internal government requirements. Keeping information longer than necessary may pose legal threats to the organization. Office 365 has several tools that help organizations handle information throughout the lifecycle.
A59: Delete DM | B59: SharePoint | C59: SharePoint | D59: SharePoint allow for compliance officers to create policies, which define things such as; The retention policy for a whole site and the team mailbox, if one is associated with the site. What causes a project to be closed. When a project should expire. | E59: Compliance Center select Retention Policies
A60: Delete DM | B60: SharePoint | C60: Document Deletion Policy | D60: Document deletion policies allow organizations to proactively delete documents in a site after a specific period of time — for example, an organization can delete documents in users’ OneDrive for Business sites five years after the documents were created. | E60: Compliance Center select Retention Policies
A61: Delete DM | B61: SharePoint | C61: Site Closure Policy | D61: Organizations can use site policies to help control site proliferation. A site policy defines the lifecycle of a site by specifying when the site will be closed and when it will be deleted.
A62: Delete DM | B62: Exchange | C62: Exchange | D62: Retention allows organizations to manage the lifecycle of content in Office 365 such as email by removing the content after it’s no longer required. Exchange allow for centralized as well as user managed policies. | E62: Compliance Center select Retention Policies
A63: Delete DM | B63: Exchange | C63: Retention Tags and Policies | D63: Exchange Online, Messaging records management (MRM) helps organizations to manage email lifecycle and reduce legal risks associated with e-mail and other communications. MRM makes it easier to keep messages needed to comply with company policy, government regulations, or legal needs, and to remove content that has no legal or business value. | E63: Compliance Center select Retention Policies | G63: Get-Mailbox -ResultSize unlimited | Where-Object {$_.RetentionPolicy -eq "RP-Finance"} | Format-Table Name,RetentionPolicy -Auto
A64: Preserve DP | B64: Office 365 | C64: Preserve (DP) | D64: To meet regulatory and internal governance requirements information in Office 365 may need to be preserved. Office 365 present a very flexible approach to securely preserving information allowing organizations to produce information in case of law or forensic investigations.
A65: Preserve DP | B65: Office 365 | C65: Hold From a Central Unified Portal | D65: Office 365 provides central administration for preserving information across the workloads through the Compliance Center. For ease of feature assessment we have split out the most common features and considerations in the list below. | E65: Select eDiscovery to create a new hold
A66: Preserve DP | B66: Exchange | C66: Preserve E-mail | D66: Failure to preserve email can expose an organization to legal and financial risks such as scrutiny of the organization's records retention and discovery processes, adverse legal judgments, sanctions, or fines. You can use In-Place Hold or Litigation Hold to accomplish the following goals: Place user mailboxes on hold and preserve mailbox items immutably. Use query-based In-Place Hold to search for and retain items matching specified criteria. Preserve items indefinitely or for a specific duration. Place a user on multiple holds for different cases or investigations. Keep holds transparent from the user.
A67: Preserve DP | B67: Exchange | C67: Preservation Lock | D67: Some organizations may need to comply with rules defined by regulatory bodies such as the Securities and Exchange Commission (SEC) Rule 17a-4, which requires that after a preservation policy is turned on, it cannot be turned off or made less restrictive. To meet this requirement, you can use Preservation Lock. After a policy’s been locked, no one—including the administrator—can turn off the policy or make it less restrictive.
A68: Preserve DP | B68: Exchange | C68: Placing All Mailboxes under hold | D68: Although most organizations don't need to preserve all e-mail content a frequent practice used is to preserve all e-mail content to not running the risk of missing something in case of a subpoena. To place all mailboxes under hold, follow these instructions. | E68: Currently PowerShell is the best option | G68: Get-Mailbox -ResultSize Unlimited -Filter {RecipientTypeDetails -eq "UserMailbox"} | Set-Mailbox -LitigationHoldEnabled $true -LitigationHoldDuration
A69: Preserve DP | B69: Exchange | C69: Query Based hold | D69: Query based hold in Office 365 allow organizations to not only hold information from Exchange but also for Skype for business and SharePoint. | E69: Select eDiscovery to create a new hold
A70: Preserve DP | B70: Exchange | C70: PST Ingestion | D70: Organizations where users keep a lot of information in their PST files may run a risk of keeping information out of policy which can be damaging in a court case if not produced correctly. Exchange Online allow for customers to upload users PST files and ingest them in to Exchange Online. | E70: Office 365 Portal Import
A71: Preserve DP | B71: Exchange | C71: Journaling | D71: Journaling allow for content to be journaled to on-premises archival systems.
A72: Preserve DP | B72: SharePoint | C72: SharePoint | D72: Before rolling out a solution for SharePoint and OneDrive for business it is important to note the big difference between a document management system and communication like e-mail or IM. Capturing all data may not represent the accurate picture since it could be compared of capturing all drafts and mutations an e-mail goes through before it is sent. SharePoint has several built in functions to meet organizations requirements of records management.
A73: Preserve DP | B73: SharePoint | C73: Place Content on in-place Hold | D73: Query based hold in Office 365 allow organizations to not only hold information from SharePoint but also for Skype for business, Exchange and OneDrive for Business.
A74: Preserve DP | B74: SharePoint | C74: Use Records Center | D74: The Records Center is intended to serve as a central repository in which an organization can store and manage all of its records such as legal or financial documents. The Records Center supports the entire records management process, from records collection through records management to records disposition.
A75: Preserve DP | B75: SharePoint | C75: File Server Ingestion | D75: Because shared files are widely distributed across networks it is hard to identify key intellectual property but it also poses a risk in case of litigation. You can use the Microsoft Office 365 Import service to migrate files from your on-premises file shares or from your own premises SharePoint Server site. | E75: Office 365 Portal Import
A76: Preserve DP | B76: Office 365 | C76: Non Microsoft System Data | D76: To accommodate customers who require archiving of non-Microsoft data in Office 365, we are partnering with 3rd parties to be able to ingest information from 3rd parties.
A77: Preserve DP | B77: Skype4B | C77: Skype for Business | D77: There are regulatory mandates that require Skype for business IM's and meeting content to be Archived. Office 365 allow for this data to be archived to user’s mailboxes.
A78: Preserve DP | B78: Skype4B | C78: Archive Meeting content and Lync conversations | D78: Organizations can archive Skype for Business Online content, such as IM conversations, to a user’s mailbox in Exchange Online. This functionality requires placing a Litigation Hold or an In-Place Hold on the user's mailbox. | E78: Select eDiscovery to create a new hold
A79: Preserve DP | B79: Skype4B | C79: For compliance, turn off non-archived features | D79: Checking this option turns off features that aren’t captured when the organization has set up an In-place hold. File transfer using instant messaging, Shared OneNote pages, PowerPoint annotations
A80: Identity IA | B80: Office 365 | D80: The Identity category covers aspects such as how identities are provisioned and controlled, where they are stored, and how to keep them in sync. Please see this information from the main Customer Security Considerations Pivot if you are using the FedRAMP control listing.
A81: Identity IA | B81: AzureAD | C81: Review that Identities created are approved | D81: Use an approval process to verify that all identities created in your environment are valid. This can help you to detect erroneous and suspicious activities. | E81: New and Deleted Mailboxes | G81: Get-MsolUser -Filter, Get-MailboxActivityReport
A82: Users AC | B82: SharePoint | C82: Monitor External Sharing invitations | D82: In regulated industries, it’s often important to audit every conversation with external parties – including any text users add to their external sharing invitations. SharePoint Online has the ability to blind copy the full text of invitation emails to a dedicated archive mailbox. | F82: Set-SPOTenant -BccExternalSharingInvitations -BccExternalSharingInvitationsList | G82: Get-SPOTenant
A134: =COUNTA(A3:A120) -> 80 | H134: =COUNTA(H3:H120) -> 0

Sheet Incident Response
A1: Category | B1: Product | C1: Consideration | D1: Description | E1: Portal Configuration | F1: PS Configure | G1: PS Get | H1: Assessed
A2: Admin AC | B2: Office 365 | C2: Access Control Admin (AC) | D2: The Access Control Admin category covers the aspects of a trusted administration model that is different from the model used for users. If the accounts used for administration can't be monitored or trusted it breaches the security of the entire system.
A3: Admin AC | B3: Exchange | C3: Administrator role group changes | D3: Verify that high-privileged roles have not been assigned to any un-authorized users. You can search the administrator audit logs or the Activity logs to discover who made changes to organization, server, and recipient configuration. This can be helpful when you're trying to track the cause of unexpected behavior, to identify a malicious administrator, to investigate data leaks, or to verify that compliance requirements are being met. | E3: Role Group Report | F3: On by default in Office 365 | G3: Get-AdminAuditLogConfig | FL AdminAuditLogEnabled, Search-AdminAuditLog
A4: Admin AC | B4: SharePoint | C4: SharePoint Online Permissions | D4: If you are a SharePoint Online admin, you probably want to control who can make changes on your site. Ensure that the proper users have administrative privileges to appropriate content. Each site collection has its own set of permission levels. SharePoint comes with some default permission levels that you can use, such as Contribute and View Only. But if one of those doesn’t meet your needs, you can create a new permissions level. It’s a best practice that you don’t change the default permission levels. See also https://support.office.com/en-us/article/How-to-create-and-edit-Permission-Levels-53c86040-07fa-4ea7-bc55-34ee96b437fe#__best_practices_for. | F4: Set-SPOSiteGroup, Set-SPOUser | G4: Get-SPOSiteGroup, Get-SPOUser
A5: Admin AC | B5: SharePoint | C5: Review Modification of permissions | D5: Changes to user accounts and permissions should happen regularly to quickly respond to potentially malicious activities. Knowing who has done what with which information is critical for many business requirements, such as regulatory compliance and records management. You can use the audit feature in SharePoint Online to track which users have taken what actions on the sites, content types, lists, libraries, list items, and library files within your site collections. | F5: Set-SPOSiteGroup, Set-SPOUser | G5: Get-SPOSiteGroup, Get-SPOUser
A6: Phishing ATP | B6: Office 365 | C6: Anti Spam/Phishing/Anti Malware (ATP) | D6: One of the most common causes that accounts and systems are compromised is due to Phishing campaigns. To meet the risks surrounding phishing and malware Office 365 has a robust set of tools to meet these advanced threats. Organizations need to educate users and implement safe guards to meet acceptable risk levels.
A7: Phishing ATP | B7: Exchange | C7: ATP Protection | D7: Exchange Online Advanced Threat Protection protects mailboxes against new, sophisticated attacks in real-time by protecting against unsafe attachments and malicious links. All suspicious content goes through a real-time behavioral malware analysis that uses machine learning techniques to evaluate the content for suspicious activity. While the content is being scanned, the URLs are rewritten to go through Office 365. The URLs are examined in real time, at the time a user clicks them. Gain critical insights into who is being targeted in your organization and the category of attacks you are facing.
A8: Phishing ATP | B8: Exchange | C8: Rich reporting and URL trace capabilities | D8: Exchange Online Advanced Threat Protection protects mailboxes against new, sophisticated attacks in real-time by protecting against unsafe attachments and malicious links. Reports of how your users are accessing different URLs from their mailboxes for getting a clear picture on what type of users are getting targeted. Also, you get details on what messages have been blocked due to unknown viruses or malware. | E8: ECP select mail flow and then url trace
A9: Phishing ATP | B9: Exchange | C9: Message Trace | D9: Message traces can be used to quickly identify the persons receiving a message. This may be useful in an early stage for phishing messages. | E9: Select mail flow and then message trace
A10: Phishing ATP | B10: Exchange | C10: Remove Potential Phishing messages | D10: In the case that a phishing campaign has by passed the defenses use the data leakage process to identify and remove the messages from the system. Check flags such as read status to understand how many people may have been exposed.
A11: Auditing AU | B11: Office 365 | C11: Auditing (AU) | D11: The Auditing category covers key aspects of information security that enable examination and re-creation of events. Auditing allow organizations to solve issues as well as to detect and investigate security issues and incidents. If reviewing this from the FedRAMP view please go to the full Customer Security Considerations view.
A12: Auditing AU | B12: AzureAD | C12: Azure AD | D12: Use Azure Active Directory (Azure AD) access and usage reports to gain visibility into the integrity and security of your organization’s directory. With this information, a directory admin can better determine where possible security risks may lie so that they can adequately plan to mitigate those risks. Audit all account actions and use Azure AD reports to identify potential fraudulent activities.
A13: Auditing AU | B13: AzureAD | C13: Azure AD Audit Events | D13: Identify privileged actions that occur in Azure Active Directory, including elevation changes, password changes, and so forth. Automate this process by consuming the security audit feed with a Security Information and Event Management system. (SIEM)
A14: Auditing AU | B14: AzureAD | C14: Review Sign-Ins from unknown sources | D14: Use this report to identify users who have successfully signed in to your organization while assigned a client IP address that has been recognized by Microsoft as an anonymous proxy IP address. These proxies are often used by users who want to hide their computer’s IP address.
A15: Auditing AU | B15: AzureAD | C15: Review Sign-ins after multiple failures | D15: Use this report to identify users who have successfully signed in after multiple consecutive failed sign-in attempts.
A16: Auditing AU | B16: AzureAD | C16: Review Signs-ins from multiple geographies | D16: Use this report to identify successful sign-in activities from a user where two sign ins appeared to originate from different countries and the time between the sign ins makes it impossible for the user to have travelled between those countries.
A17: Auditing AU | B17: AzureAD | C17: Review AAD Logons for Anomalies | D17: Indicates users whose accounts may have been compromised.
A18: Auditing AU | B18: Exchange | C18: Exchange | D18: Leverage the rich set of auditing features in Exchange Online to audit administrator, user, application, and external user access. For example, you can use audit logging to troubleshoot configuration issues by tracking specific changes made by administrators, and to help you meet regulatory, compliance, and litigation requirements. Exchange Online includes both administrator audit logging and mailbox audit logging. These logs can help you determine who has accessed a mailbox and what they’ve done.
A19: Auditing AU | B19: Exchange | C19: Exchange Online Privileged Administrator changes | D19: You can search the administrator audit logs to discover who made changes to organization, server, and recipient configuration. This can be helpful when you're trying to track the cause of unexpected behavior, to identify a malicious administrator, or to verify that compliance requirements are being met. Regularly review all changes to privileged role groups to detect potentially harmful changes.
A20: Auditing AU | B20: Exchange | C20: Exchange Mailbox Activities (Audit Log Search) | D20: These are the activities that can be logged by mailbox audit logging and searched through the Audit Log Search, by default mailbox audit logging is not turned on. Copied messages to another folder, Created item, Deleted messages from Deleted Items folder, Moved messages to another folder, Moved messages to Deleted Items folder, Purged messages from the mailbox, Sent message using Send As permissions, Sent message using Send On Behalf permissions, Updated message, User signed in to mailbox
A21: Auditing AU | B21: Exchange | C21: Detect non-owner mailbox access | D21: Audit non-owner access activity to identify potential leaks of information and to proactively review non-owner access to mailboxes. The Non-Owner Mailbox Access Report in the Exchange Admin Center lists the mailboxes that have been accessed by someone other than the person who owns the mailbox. When a mailbox is accessed by a non-owner, Exchange logs information about this action in a mailbox audit log that’s stored as an email message in a hidden folder in the mailbox being audited. Entries from this log are displayed as search results and include a list of mailboxes accessed by a non-owner, who accessed the mailbox and when, the actions performed by the non-owner, and whether the action was successful. By default, entries in the mailbox audit log are retained for 90 days. | F21: Get-Mailbox -ResultSize Unlimited -Filter {RecipientTypeDetails -eq "UserMailbox"} | Set-Mailbox -AuditEnabled $true | G21: Get-Mailbox | FT Name,AuditEnabled
A22: Auditing AU | B22: Exchange | C22: Review configuration changes in organization | D22: You can use the Exchange Admin Center to search for and view entries in the administrator audit log. The administrator audit log records specific actions, based on Exchange Management Shell cmdlet, performed by administrators and users who have been assigned administrative privileges. Entries in the administrator audit log provide you with information about what cmdlet was run, which parameters were used, who ran the cmdlet, and what objects were affected. Regularly review all configuration changes to ensure that only valid and approved changes have been made to the organization's settings. | G22: Get-AdminAuditLogConfig | FL AdminAuditLogEnabled
A23: Auditing AU | B23: Office 365 | C23: Office 365 User administration activities | D23: These are the administration activities that are logged when an admin adds or changes a user account. Added user, Changed user license, Changed user password, Deleted user, Reset user password, Set property that forces user to change password, Set license properties, Updated user. These activities can be used to review administrator activity on a regular basis to ensure that the activities performed are in accordance to organizational principles.
A24: Auditing AU | B24: Office 365 | C24: Office 365 Group administration activities | D24: Search these logs to identify activities related to an admin or a user creates or changes an Office 365 group or when an admin creates a security group. The activities logged are Added group, Added member to group, Deleted group, Removed member from group, Updated group
A25: Auditing AU | B25: Office 365 | C25: Application administration activities | D25: When an administrator adds or changes an application that's registered in Azure AD these activities are logged. Added delegation entry, Added service principal, Added service principal credentials, Removed delegation entry, Removed service principal, Removed service principal credentials, Set delegation entry. Keeping track of these entries are important since applications can be used to access customer data hence a rouge admin could use applications in an attempt to circumvent security. Both the registration of applications and actions carried by the applications like accessing customer data are logged.
A26: Auditing AU | B26: Office 365 | C26: Office 365 Role administration activities | D26: It is important to keep track of the Azure AD roles in Office 365 to detect potential attempts to elevate permissions. The role administration logging is logging the following activities Add member to Role, Removed a user from a directory role, Set company contact information.
A27: Auditing AU | B27: Office 365 | C27: Directory administration activities | D27: These are the Azure AD directory and domain related activities that are logged when an administrator manages admin roles. Added domain to company, Added partner to company, Removed domain from company, Removed partner from company, Set company information, Set domain authentication, Set federation settings on the domain, Set password policy, Turned on Azure AD sync, Updated domain, Verified domain, Verified email verified domain. These activities are important to ensure that delegation to partner as an example is not done without prior approval.
A28: Auditing AU | B28: Office 365 | C28: Search for eDiscovery activities | D28: Content Search and eDiscovery-related activities that are performed in Office 365 Security & Compliance Center or by running the corresponding Windows PowerShell cmdlets are logged in the Office 365 audit log. The following tasks are logged, Creating and managing eDiscovery cases, Creating, starting, and editing Content Searches, Performing Content Search actions, such as previewing, exporting, and deleting search results, Configuring permissions filtering for Content Search, Managing the eDiscovery Administrator role
A29: Auditing AU | B29: SharePoint | C29: SharePoint (Activity Report) | D29: Regularly review the Office 365 Activity Report in the Compliance Center to review user and administrator activity in your Office 365 tenant. The report contains entries for activity in Exchange Online, SharePoint Online, and OneDrive for Business, and administrator activity reports in Azure Active Directory.
A30: Auditing AU | B30: SharePoint | C30: File and folder activities | D30: This section of the reporting capture the file and folder activities in SharePoint Online and OneDrive for Business such as, Accessed file, Checked in file, Checked out file, Copied file, Deleted file, Discarded file checkout, Downloaded file, Modified file, Moved file, Renamed file, Restored file, Uploaded file. These can be invaluable to detect potential fraudulent behavior. | F30: Search-UnifiedAuditLog, Set-UnifiedAuditSetting | G30: Get-UnifiedAuditSetting
A31: Auditing AU | B31: SharePoint | C31: Sharing and access request activities | D31: The user sharing and access request activities in SharePoint Online and OneDrive for Business provide insight in to the key areas like Accepted access request, Accepted sharing invitation, Created a company-wide link, Created access request, Created an anonymous link, Created sharing invitation, Denied access request , Removed a company-wide link, Removed an anonymous link, Shared file, folder, or site, Updated an anonymous link, Used an anonymous link, Unshared file, folder, or site, Used a company-wide link, Withdrew sharing invitation. | F31: Search-UnifiedAuditLog, Set-UnifiedAuditSetting | G31: Get-UnifiedAuditSetting
A32: Auditing AU | B32: SharePoint | C32: Synchronization Activities | D32: This category is used to track file synchronization activities in SharePoint Online and OneDrive for Business. It track tasks such as, Allowed computer to sync files, Blocked computer from syncing files, Downloaded files to computer, Downloaded file changes to computer, Uploaded files to document library, Uploaded file changes to document library | F32: Search-UnifiedAuditLog, Set-UnifiedAuditSetting | G32: Get-UnifiedAuditSetting
A33: Auditing AU | B33: SharePoint | C33: Site administration activities | D33: The list of audited site administration tasks in SharePoint Online is rich and can be used to detect unwanted changes in the SharePoint configuration. Added exempt user agent, Added site collection administrator, Added user to group, Allowed user to create groups, Changed exempt user agents, Changed a sharing policy, Created group, Created Sent To connection, Created site collection, Deleted group, Deleted Sent To connection, Enabled document preview, Enabled legacy workflow, Enabled Office on Demand, Enabled RSS feeds, Enabled result source for People Searches, Modified site permissions, Removed user from group, Removed user from site collection, Renamed site, Requested site admin permissions, Set host site, Updated group | F33: Search-UnifiedAuditLog, Set-UnifiedAuditSetting | G33: Get-UnifiedAuditSetting
A34: Auditing AU | B34: SharePoint | C34: SharePoint Search queries Log | D34: In case of a breach, review the keywords that have been used in searches to help identify the information being sought.
A35: Auditing AU | B35: Azure Information Protection | C35: Azure Information Protection Logging | D35: Use the Azure Active Directory Rights Management Services (Information Protection) logs to audit requests, including requests from users, actions performed by Information Protection administrators in organizations, and actions performed by Microsoft operators to support Information Protection deployments. Information Protection writes logs in W3C extended log format into an Azure storage account that you provide. Information Protection logging information is available to you in near-real time, so that you can continuously monitor your company’s use of Information Protection . 99.9% of logs are available within 15 minutes of an Information Protection-initiated action. For example, you might want to be alerted if there is a sudden increase of people reading Information Protection-protected data outside standard working hours, which could indicate that a malicious user is collecting information to sell to competitors. Or, if the same user apparently accesses data from two different IP addresses within a short time frame, which could indicate that a user account has been compromised. If you have an information leak, you are likely to be asked who recently accessed specific documents and what information did a suspected person access recently. You can answer these type of questions when you use Information Protection and logging because people who use protected content must always get an Information Protection license to open documents and pictures that are protected by Information Protection, even if these files are moved by email or copied to USB drives or other storage devices. This means that you can use Information Protection logs as a definitive source of information for forensic analysis when you protect your data by using Information Protection. | F35: Enable-AadrmUsageLogFeature | G35: Get-AadrmConfiguration
A36: Auditing AU | B36: Azure Information Protection | C36: Track Protected Documents | D36: After you have protected your documents by using the Azure Active Directory Rights Management Services (Information Protection) sharing application, you can track how people are using your protected documents, and if necessary, revoke access to them when you want to stop sharing. To do this, you use the document tracking site, which you can access from Windows computers, Mac computers, and even from tablets and phones. Use Azure Active Directory Information Protection to track usage of protected information. Senders can view which recipients have opened file(s), information about unauthorized access attempts, and view the most recent state of the file.
A37: Auditing AU | B37: Azure Information Protection | C37: Detect viewing of documents centrally | D37: Use the Azure Active Directory Rights Management Services (Information Protection) logs to audit requests, including requests from users, actions performed by Information Protection administrators in organizations, and actions performed by Microsoft operators to support Information Protection deployments. Information Protection writes logs in W3C extended log format into an Azure storage account that you provide. Azure Active Directory Rights Management Services (Information Protection) logging can help you detect the use of protected information that may be out of policy or for forensic investigations. You can automate this process by consuming the security audit feed with a Security Information and Event Management system.
A38: Auditing AU | B38: Office 365 | C38: Office 365 Activity API | D38: The Office 365 Management APIs provide a single extensibility platform for all Office 365 customers’ and partners’ management tasks, including service communications, security, compliance, reporting, auditing, user management, and reseller management. All of the Office 365 Management APIs will be consistent in design and implementation with the current suite of Office 365 REST APIs, using common industry-standard approaches, including OAuth v2, OData v4, and JSON. Like the other Office 365 APIs, applications are registered in Azure Active Directory, giving developers a consistent way to authenticate and authorize their apps.
A39: Auditing AU | B39: Office 365 | C39: Office 365 Management Audit Log | D39: You can use the Office 365 activity report in the Office 365 Compliance Center to view user and admin activity in your Office 365 organization. The report contains entries for admin activity (admin audit logging) and access to mailboxes (mailbox audit logging) in Exchange Online, user and admin activity in SharePoint Online and OneDrive for Business, and admin activity and user sign-in activity in Azure Active Directory. Use the Office 365 Activity API to consume a feed of activity data from Office 365 to your on-premises Security Information and Event Management solution.
A40: Auditing AU | B40: OnPrem | C40: Active Directory Federation Services | D40: Active Directory Federation Services (AD FS) includes its own dedicated performance counters to help you monitor the performance of both federation servers and federation server proxy computers. Configure performance monitoring for AD FS and keep track of suspicious log on patterns for on-premises accounts.
A41: Auditing AU | B41: OnPrem | C41: Performance Monitoring | D41: Active Directory Federation Services (AD FS) includes its own dedicated performance counters to help you monitor the performance of both federation servers and federation server proxy computers. Configure performance monitoring for AD FS and keep track of suspicious log on patterns for on-premises accounts.
A42: Auditing AU | B42: OnPrem | C42: Advanced Threat Analytics | D42: Microsoft Advanced Threat Analytics (ATA) helps you identify breaches and threats using behavioral analysis and provides a clear, actionable report on a simple attack timeline. It's a simple and fast way to understand what is happening within your network by identifying suspicious user and device activity with built-in intelligence and providing clear and relevant threat information on a simple attack timeline. ATA leverages deep packet inspection technology, as well as information from additional data sources (Security Information and Event Management and Active Directory) to build an Organizational Security Graph and detect advanced attacks in near real time. Use advanced threat analytics such as behavioral analysis to detect potential threats in your environment.
A43: Auditing AU | B43: OnPrem | C43: Azure AD Connect Health | D43: Azure AD Connect Health helps you monitor and gain insight into your on-premises identity infrastructure and the synchronization services available through Azure AD Connect. It offers you the ability to view alerts, performance, usage patterns, configuration settings, enables you to maintain a reliable connection to Office 365 and much more. Use Azure AD Connect to monitor the state of directory integration between your on-premises environment and Office 365.
A44: Auditing AU | B44: Exchange | C44: Exchange Online Protection Auditing Reports | D44: Auditing reports in Microsoft Exchange Online Protection (EOP) can help you meet regulatory, compliance, and litigation requirements for your organization. You can obtain auditing reports at any time to determine the changes that have been made to your EOP configuration. These reports can help you troubleshoot configuration issues or find the cause of security-related or compliance-related problems. Regularly review EOP audit reports to support security and compliance-related work.
A45: Auditing AU | B45: Exchange | C45: Exchange Online Protection Privileged Admin Changes | D45: When an administrator adds members to or removes members from administrator role groups, Microsoft Exchange Online Protection logs each occurrence. When you run an administrator role group report in the Exchange Admin Center, entries are displayed as search results and include the role groups affected, who changed the role group membership and when, and what membership updates were made. Use this report to monitor changes to the administrative permissions assigned to users in your organization. Regularly review all changes to privileged role groups to detect potentially harmful changes.
A46: Auditing AU | B46: Exchange | C46: Exchange Online Protection Administrator Audit Log | D46: In Exchange Online Protection (EOP) and Exchange Online, you can use the Exchange Admin Center to search for and view entries in the administrator audit log. The administrator audit log records specific actions performed by administrators and users who have been assigned administrative privileges. Entries in the administrator audit log provide you with information about what cmdlet was run, which parameters were used, who ran the cmdlet, and what objects were affected. Regularly review all changes to EOP configuration settings, especially those that affect mail flow.
A47: Auditing AU | B47: Office 365 | C47: Advanced Security Management | D47: Advanced Security Management in Office 365 gives you insights into suspicious activity in Office 365 so you can investigate situations that are potentially problematic and, if needed, take action to address security issues. You can also get Productivity app discovery, which lets you use the information from your organization's log files to understand and act on your users' app usage in Office 365 and other cloud apps.
... A49: Client CM | B49: Client | C49: Review Sign ins from possibly infected devices | D49: This report attempts to identify your users' devices that that have become infected and are now part of a botnet (also known as a zombie army). We correlate IP addresses of users' sign ins against IP addresses that we know to be in contact with botnet servers. It is important to identify compromised devices since they possibly carry more than one type of malware that threatens the system. Reach out to the user to get more information.
A50: Client CM | B50: Client | C50: Remote Wipe | D50: If a device is stolen this function helps limiting the possibility of extracting information from the phone by completely wiping the information. | E50: RemoteWipe
A51: Authentication IA | B51: Office 365 | C51: Authentication (IA) | D51: The Authentication category covers the options and features available for authentication within Office 365. The list contains Microsoft technologies available both on-premises and in the cloud. Please see this information from the main Customer Security Considerations Pivot if you are using the FedRAMP control listing.
A52: Authentication IA | B52: Office 365 | C52: Token Life time | D52: This feature allows you to create token lifetime policies. These policies define how long tokens issued by Azure AD are considered valid. This influences how often users must enter their credentials. These policies can be set as defaults that apply to all applications in a tenant and they can also be linked to applications or service principals. The policies are managed through Azure PowerShell.
A53: Authentication IA | B53: AzureAD | C53: Process to roll passwords | D53: Reset all passwords for high-privileged accounts to complicate a continued foothold in the environment in the event of a breach.
A54: Identity IA | B54: AzureAD | C54: Review that Identities created are approved | D54: Use an approval process to verify that all identities created in your environment are valid. This can help you to detect erroneous and suspicious activities. | E54: New and Deleted Mailboxes | G54: Get-MsolUser -Filter, Get-MailboxActivityReport
A55: Incident IR | B55: Office 365 | C55: Incident Response (IR) | D55: There are many things to take in to account when planning for incident response. In this section we have listed a number of considerations and actions in relation to Incident Response. Remember to create custom plans based on the other functions listed in the Customer master list. On top of incident plans organizations should have a process to integrate with the organizational problem resolution process. See the full Incident Response pivot to get a broader view on how to Prevent Detect Respond and Recover from incidents.
A56: Incident IR | B56: Office 365 | C56: Keep the contact details in the Office 365 Portal up to date | D56: Microsoft will provide notifications and updates to defined contacts within customer estate, these will need to be maintained | E56: Management Portal
A57: Incident IR | B57: AzureAD | C57: Disable Account | D57: In some cases, it may be necessary to block access to a specific account. Currently we cannot immediately terminate access to an account. This method will prevent future authentication. | E57: Select user go to settings and set status Blocked | F57: Set-MsolUser –UserPrincipalName –BlockCredential $True,
A58: Incident IR | B58: AzureAD | C58: Reset Password | D58: When a user's password is changed, the refresh token is invalidated. This results in the Office 365 session to be terminated.
A59: Incident IR | B59: Exchange | C59: Delete Mailbox when disable account | D59: When disabling an account deleting the mailbox helps make sure that e-mails are not forwarded or sent from the mailbox. The mailbox can be recovered using the Undo-SoftDeletedMailbox within 30 days.
A60: Incident IR | B60: SharePoint | C60: Inactivate Office 365 sessions | D60: This feature provides IT administrators the ability to invalidate a particular users Office 365 sessions across all their devices. | F60: Revoke-SPOUserSession
A61: Incident IR | B61: Office 365 | C61: Log Incident with partner or Microsoft | D61: There need to be an escalation chain defined for when and who to contact in case of a security incident. Note that this may include several instances within the organization. If a partner is used the escalation may best be directed to the partner initially.
A62: Incident IR | B62: Office 365 | C62: Configuration checklist | D62: To properly understand dependencies across the environment it is beneficial to visualize them by creating maps. This helps visualizing how the solution fits together without reading through an endless amount of configuration checklists and architectural documents. Linking the visualized service map to the baseline configuration will make it easier to spot potential deviations as well as the impact that new solutions may have on the environment.
A63: Users AC | B63: Office 365 | C63: Access Control Users (AC) | D63: The Access Control Users category covers the aspects of a trusted user model that is different from the model used for admins. Scenarios to make users productive are not purely ACL-based but contain a number of settings that can be used by organizations to adhere to their information security policies.
A64: Users AC | B64: Exchange | C64: Review forwarding being setup | D64: Regularly review all email forwarding settings to detect fraudulent activity. Email forwarding lets you to set up a mailbox to forward email messages sent to that mailbox to another user’s mailbox in or outside of your organization. But it's a method commonly used by hackers and malicious individuals to steal data and create and maintain a foothold in the environment. | G64: Get-Mailbox |{$_.ForwardingSMTPAddress -ne $null} |fl ForwardingSMTPAddress,DeliverToMailboxandForward, Get-InboxRule
A101: =COUNTA(A2:A68) -> 63 | H101: =COUNTA(H2:H68) -> 0
A104: =COUNTA(A2:A92) -> 63 | H104: =COUNTA(H2:H92) -> 0

Sheet ALL
A1: Category | B1: Product | C1: Feature | D1: Description | E1: Portal | F1: PS Configure | G1: PS Get
A2: Admin AC | B2: O365 | C2: Access Control Admin (AC) | D2: The Access Control Admin category covers the aspects of a trusted administration model that is different from the model used for users. If the accounts used for administration can't be monitored or trusted it breaches the security of the entire system.
A3: Admin AC | B3: O365 | C3: Separation of Duties | D3: Depending on the size of your organization, you may want to designate several admins who serve different functions. The admin has access to all features in the admin center, and can create or edit users, assign admin roles to others, reset user passwords, manage user licenses, and manage domains, among other things. Office 365 includes a security model that enables separation of administration based on roles. Certain admin roles Office 365 have a corresponding role in Exchange Online, SharePoint Online, and Skype for Business Online. | E3: Select the user and edit user roles
A4: Admin AC | B4: Exchange | C4: Separate Exchange Administrators | D4: Depending on the size of your organization, you may want to designate several admins who serve different functions. The admin has access to all features in the admin center, and can create or edit users, assign admin roles to others, reset user passwords, manage user licenses, and manage domains, among other things. Office 365 includes a security model that enables separation of administration based on roles. Certain admin roles Office 365 have a corresponding role in Exchange Online, SharePoint Online, and Skype for Business Online. Segment permissions to ensure that a single administrator doesn't have greater access than necessary. | E4: Select the user and edit user roles | F4: Set-MsolRoleMember | G4: Get-MsolRoleMember
A5: Admin AC | B5: SharePoint | C5: Separate SharePoint Administrators | D5: Depending on the size of your organization, you may want to designate several admins who serve different functions. The admin has access to all features in the admin center, and can create or edit users, assign admin roles to others, reset user passwords, manage user licenses, and manage domains, among other things. Office 365 includes a security model that enables separation of administration based on roles. Certain admin roles Office 365 have a corresponding role in Exchange Online, SharePoint Online, and Skype for Business Online. Segment permissions to ensure that a single administrator doesn't have greater access than necessary. | E5: Select the user and edit user roles | F5: Set-MsolRoleMember | G5: Get-MsolRoleMember
A6: Admin AC | B6: Skype4B | C6: Separate Skype for Business Administrators | D6: Depending on the size of your organization, you may want to designate several admins who serve different functions. The admin has access to all features in the admin center, and can create or edit users, assign admin roles to others, reset user passwords, manage user licenses, and manage domains, among other things. Office 365 includes a security model that enables separation of administration based on roles. Certain admin roles Office 365 have a corresponding role in Exchange Online, SharePoint Online, and Skype for Business Online. Segment permissions to ensure that a single administrator doesn't have greater access than necessary. | E6: Select the user and edit user roles | F6: Set-MsolRoleMember | G6: Get-MsolRoleMember
A7: Admin AC | B7: AzureAD | C7: Azure Administrative Units | D7: Limit permissions to allow only relevant staff access to a limited administration surface. This reduces the risk of sharing information between business units. You can achieve this by using administrative units, which are new Azure Active Directory (Azure AD) containers of resources that can be used for delegating administrative permissions over subsets of users, and applying policies to a subset of users. In Azure AD, administrative units enable central administrators to delegate permissions to regional administrators or to set policy at a granular level. This is useful in organizations with independent divisions; for example, a large university that is made up of many autonomous schools (Business school, Engineering school, etc.) which are independent from each other. Such divisions have their own IT administrators who control access, manage users, and set policies specifically for their division. Central administrators want to be able grant these divisional administrators permissions over the users in their particular divisions. More specifically, using this example, a central administrator can, for instance, create an administrative unit for a particular school (Business school) and populate it with only the Business school users. Then a central administrator can add the Business school IT staff to a scoped role, in other words, grant the IT staff of Business school administrative permissions only over the Business school administrative unit.
A8: Admin AC | B8: AzureAD | C8: Azure AD Privileged Identity Management | D8: Azure AD Privileged Identity Management lets you manage, control and monitor your privileged identities and their access to resources in Azure AD, and in other Microsoft online services such as Office 365 or Microsoft Intune. This feature provide the ability to implement just in time elevation for privileged actions.
A9: Admin AC | B9: Exchange | C9: Exchange Online Privileged Accounts | D9: Perform regular reviews of all users and groups with high levels of permissions. You can search the administrator audit logs to discover who made changes to organization, server, and recipient configuration. This can be helpful when you're trying to track the cause of unexpected behavior, to identify a malicious administrator, to investigate data leaks, or to verify that compliance requirements are being met. | E9: Permissions / Admin Groups
A10: Admin AC | B10: Exchange | C10: Administrator role group changes | D10: Verify that high-privileged roles have not been assigned to any un-authorized users. You can search the administrator audit logs or the Activity logs to discover who made changes to organization, server, and recipient configuration. This can be helpful when you're trying to track the cause of unexpected behavior, to identify a malicious administrator, to investigate data leaks, or to verify that compliance requirements are being met. | E10: Role Group Report | F10: On by default in Office 365 | G10: Get-AdminAuditLogConfig | FL AdminAuditLogEnabled, Search-AdminAuditLog
A11: Admin AC | B11: SharePoint | C11: SharePoint Online Permissions | D11: If you are a SharePoint Online admin, you probably want to control who can make changes on your site. Ensure that the proper users have administrative privileges to appropriate content. Each site collection has its own set of permission levels. SharePoint comes with some default permission levels that you can use, such as Contribute and View Only. But if one of those doesn’t meet your needs, you can create a new permissions level. It’s a best practice that you don’t change the default permission levels. See also https://support.office.com/en-us/article/How-to-create-and-edit-Permission-Levels-53c86040-07fa-4ea7-bc55-34ee96b437fe#__best_practices_for. | F11: Set-SPOSiteGroup, Set-SPOUser | G11: Get-SPOSiteGroup, Get-SPOUser
A12: Admin AC | B12: SharePoint | C12: Review Modification of permissions | D12: Changes to user accounts and permissions should happen regularly to quickly respond to potentially malicious activities. Knowing who has done what with which information is critical for many business requirements, such as regulatory compliance and records management. You can use the audit feature in SharePoint Online to track which users have taken what actions on the sites, content types, lists, libraries, list items, and library files within your site collections. | F12: Set-SPOSiteGroup, Set-SPOUser | G12: Get-SPOSiteGroup, Get-SPOUser
A13: Admin AC | B13: O365 | C13: Customer Lockbox | D13: Microsoft engineers do not have standing access to any service operation. All access is obtained through a rigorous access control technology called Lockbox that enforces access control through multiple levels of approval within Microsoft, providing just-in-time access with limited and time-bound authorization. In addition, all access control activities in the service are logged and audited. Customers are part of the Lockbox approval process for instances involving access to customer content. The customer-facing side of the approval process is called Customer Lockbox. Use of the Customer Lockbox feature ensures that a Microsoft engineer does not get access to customer content without the customer’s explicit approval. Customer Lockbox gives customers explicit approval tools in the rare case when a Microsoft engineer needs access to customer content to resolve a customer-reported issue.
A14: Admin AC | B14: O365 | C14: Review Delegated Partner Administrators | D14: Ensure that partner organizations don't have standing access to the environment unless warranted. This will limit the potential attack surface.
A15: Phishing ATP | B15: O365 | C15: Anti Spam/Phishing/Anti Malware (ATP) | D15: One of the most common causes that accounts and systems are compromised is due to Phishing campaigns. To meet the risks surrounding phishing and malware Office 365 has a robust set of tools to meet these advanced threats. Organizations need to educate users and implement safe guards to meet acceptable risk levels.
A16: Phishing ATP | B16: Exchange | C16: User Education | D16: It is key to educate users about phishing attacks, malicious and unwanted email, and to recognize possible scams. This enables users to determine for themselves what actions to take if they come across a phishing attempt or other similar scam. Internal notifications can help users with identification and early eradication of a threat.
A17: Phishing ATP | B17: Exchange | C17: ATP Protection | D17: Exchange Online Advanced Threat Protection protects mailboxes against new, sophisticated attacks in real-time by protecting against unsafe attachments and malicious links. All suspicious content goes through a real-time behavioral malware analysis that uses machine learning techniques to evaluate the content for suspicious activity. While the content is being scanned, the URLs are rewritten to go through Office 365. The URLs are examined in real time, at the time a user clicks them. Gain critical insights into who is being targeted in your organization and the category of attacks you are facing.
A18: Phishing ATP | B18: Exchange | C18: Detonation Chamber | D18: Exchange Online Advanced Threat Protection protects mailboxes against new, sophisticated attacks in real-time by protecting against unsafe attachments and malicious links. All suspicious content goes through a real-time behavioral malware analysis that uses machine learning techniques to evaluate the content for suspicious activity. Unsafe attachments are sandboxed in a detonation chamber before being sent to recipients.
A19: Phishing ATP | B19: Exchange | C19: Safe Links | D19: Exchange Online Advanced Threat Protection protects mailboxes against new, sophisticated attacks in real-time by protecting against unsafe attachments and malicious links. Safe Links help protect environments when users click a link. While the content is being scanned, the URLs are rewritten to go through Office 365. The URLs are examined in real-time, at the time a user clicks them. If a link is unsafe, the user is warned not to visit the site or informed that the site has been blocked.
A20: Phishing ATP | B20: Exchange | C20: Rich reporting and URL trace capabilities | D20: Exchange Online Advanced Threat Protection protects mailboxes against new, sophisticated attacks in real-time by protecting against unsafe attachments and malicious links. Reports of how your users are accessing different URLs from their mailboxes for getting a clear picture on what type of users are getting targeted. Also, you get details on what messages have been blocked due to unknown viruses or malware. | E20: ECP select mail flow and then url trace
A21: Phishing ATP | B21: Exchange | C21: Exchange Online Protection Configuration Best Practices | D21: Exchange Online Protection (EOP) is a cloud-hosted email filtering service built to protect customers from spam, phishing and malware, and to implement custom policy rules. Proper configuration of EOP is essential to keep out unwanted e-mail and keep the messaging system secure. Follow Microsoft's recommended best practices for configuring EOP features such as anti-spam, anti-malware, phishing and spoofing prevention, and more.
A22: Phishing ATP | B22: Exchange | C22: End User Spam Notification | D22: You can configure end-user spam notifications for the default company-wide content filter policy or for custom content filter policies that are applied to domains. Enabling end-user spam notification messages lets your end users self-manage their own spam-quarantined messages. End-user spam notifications cannot be used with policies applied to users or groups, or to a policy with exceptions.
A23: Phishing ATP | B23: Exchange | C23: Zero-hour Auto Purge (ZAP) | D23: ZAP change the verdict of an unread email from Clean to Spam and move this message from your Inbox to the Junk Email folder. This goes the other way around as well, so if a message was incorrectly marked as Spam (False Negative) and it was moved to Junk Email folder, ZAP will move the message in your Inbox folder. | F23: Set-HostedContentFilterPolicy | G23: Get-HostedContentFilterPolicy
A24: Phishing ATP | B24: Exchange | C24: Advanced spam filtering options | D24: Advanced spam filtering (ASF) options give administrators the ability to inspect various content attributes of a message. The presence of these attributes in a message either increases the spam score of the message (thereby increasing the potential for it to be identified as spam) or marks the message as spam. The ASF options target specific message properties, such as HTML tags and URL redirection, which are commonly found in spam messages. | E24: Protection Spam Filter
A25: Phishing ATP | B25: Exchange | C25: Setup SPF Record | D25: SPF records are TXT records that help to prevent other people from using your domain to send spam or other malicious email. Sender policy framework (SPF) records work by identifying the servers that are authorized to send email from your domain. An email system that receives an email from your domain looks at the SPF record, and if the email server that sent the message was an Office 365 server, the message is accepted. If the server that sent the message was your old mail system or a malicious system on the Internet, the message is considered un-safe. | E25: Select the domain click Find and Fix
A26: Phishing ATP | B26: Exchange | C26: SPF Record: Hard Fail | D26: When this setting is enabled, messages that fail an SPF check (meaning they were sent from an IP address not specified in the SPF record) will be marked as spam. Turning this setting on is recommended for organizations who are concerned about receiving phishing messages. SPF catches the case where the phisher spoofs the 5321 MailFrom. | E26: Navigate to Protection/ Spam filter
A27: Phishing ATP | B27: Exchange | C27: Conditional Sender ID filtering | D27: When this setting is enabled, any message that hard fails a conditional Sender ID check is marked as spam. This option combines an SPF check with a Sender ID check to help protect against message headers that contain forged senders. | E27: Navigate to Protection/ Spam filter
A28: Phishing ATP | B28: Exchange | C28: DKIM | D28: Exchange Online support inbound validation of Domain Keys Identified Mail (DKIM) messages. DKIM is a method for validating that a message was sent from the domain it says it originated from and that it was not spoofed by someone else. It ties an email message to the organization responsible for sending it. DKIM verification is automatically used for all messages sent over IPv6 communications.
A29: Phishing ATP | B29: Exchange | C29: DMARC | D29: DMARC is a technology designed to combat email spoofing and is useful to stop phishing. Specifically, it protects the case where a phisher has spoofed the 5322.From email address, which is the email address displayed in mail clients.
A30: Phishing ATP | B30: Exchange | C30: Top senders and recipients | D30: The top senders and recipients report can provide indications of e-mails being forwarded outside of the organization or other patterns that may indicate leakage of information.
A31: Phishing ATP | B31: Exchange | C31: Malware & SPAM Detections | D31: The malware and SPAM report may provide insight if particular users are more targeted than others within the organization. This may lead to more direct actions to educate the users affected as well as setting stricter Outlook rules.
A32: Phishing ATP | B32: Exchange | C32: Message Trace | D32: Message traces can be used to quickly identify the persons receiving a message. This may be useful in an early stage for phishing messages. | E32: Select mail flow and then message trace
A33: Phishing ATP | B33: Exchange | C33: Remove Potential Phishing messages | D33: In the case that a phishing campaign has by passed the defenses use the data leakage process to identify and remove the messages from the system. Check flags such as read status to understand how many people may have been exposed.
A34: Phishing ATP | B34: Exchange | C34: PowerShell cmdlets for Phishing and Anti Spam | D34: This is a reference to the PowerShell cmdlets available to configure anti-spam and anti-malware settings in Exchange Online.
A35: Auditing AU | B35: O365 | C35: Auditing (AU) | D35: The Auditing category covers key aspects of information security that enable examination and re-creation of events. Auditing allow organizations to solve issues as well as to detect and investigate security issues and incidents. If reviewing this from the Fed ramp view please go to the full Customer Security Considerations view.
A36: Auditing AU | B36: AzureAD | C36: Azure AD | D36: Use Azure Active Directory (Azure AD) access and usage reports to gain visibility into the integrity and security of your organization’s directory. With this information, a directory admin can better determine where possible security risks may lie so that they can adequately plan to mitigate those risks. Audit all account actions and use Azure AD reports to identify potential fraudulent activities.
A37: Auditing AU | B37: AzureAD | C37: Azure AD Audit Events | D37: Identify privileged actions that occur in Azure Active Directory, including elevation changes, password changes, and so forth. Automate this process by consuming the security audit feed with a Security Information and Event Management system. (SIEM)
A38: Auditing AU | B38: AzureAD | C38: Review Sign-Ins from unknown sources | D38: Use this report to identify users who have successfully signed in to your organization while assigned a client IP address that has been recognized by Microsoft as an anonymous proxy IP address. These proxies are often used by users who want to hide their computer’s IP address.
A39: Auditing AU | B39: AzureAD | C39: Review Sign-ins after multiple failures | D39: Use this report to identify users who have successfully signed in after multiple consecutive failed sign-in attempts.
A40: Auditing AU | B40: AzureAD | C40: Review Signs-ins from multiple geographies | D40: Use this report to identify successful sign-in activities from a user where two sign ins appeared to originate from different countries and the time between the sign ins makes it impossible for the user to have travelled between those countries.
A41: Auditing AU | B41: AzureAD | C41: Review AAD Logons for Anomalies | D41: Indicates users whose accounts may have been compromised.
A42: Auditing AU | B42: Exchange | C42: Exchange | D42: Leverage the rich set of auditing features in Exchange Online to audit administrator, user, application, and external user access. For example, you can use audit logging to troubleshoot configuration issues by tracking specific changes made by administrators, and to help you meet regulatory, compliance, and litigation requirements. Exchange Online includes both administrator audit logging and mailbox audit logging. These logs can help you determine who has accessed a mailbox and what they’ve done.
A43: Auditing AU | B43: Exchange | C43: Exchange Online Privileged Administrator changes | D43: You can search the administrator audit logs to discover who made changes to organization, server, and recipient configuration. This can be helpful when you're trying to track the cause of unexpected behavior, to identify a malicious administrator, or to verify that compliance requirements are being met. Regularly review all changes to privileged role groups to detect potentially harmful changes.
A44: Auditing AU | B44: Exchange | C44: {=[1]!'!CSC Main!R44C3'} -> #REF! | D44: These are the activities that can be logged by mailbox audit logging and searched through the Audit Log Search, by default mailbox audit logging is not turned on. Copied messages to another folder, Created item, Deleted messages from Deleted Items folder, Moved messages to another folder, Moved messages to Deleted Items folder, Purged messages from the mailbox, Sent message using Send As permissions, Sent message using Send On Behalf permissions, Updated message, User signed in to mailbox | F44: Get-Mailbox -ResultSize Unlimited -Filter {RecipientTypeDetails -eq "UserMailbox"} | Set-Mailbox -AuditEnabled $true | G44: Get-Mailbox | FT Name,AuditEnabled
A45: Auditing AU | B45: Exchange | C45: Detect non-owner mailbox access | D45: Audit non-owner access activity to identify potential leaks of information and to proactively review non-owner access to mailboxes. The Non-Owner Mailbox Access Report in the Exchange Admin Center lists the mailboxes that have been accessed by someone other than the person who owns the mailbox. When a mailbox is accessed by a non-owner, Exchange logs information about this action in a mailbox audit log that’s stored as an email message in a hidden folder in the mailbox being audited. Entries from this log are displayed as search results and include a list of mailboxes accessed by a non-owner, who accessed the mailbox and when, the actions performed by the non-owner, and whether the action was successful. By default, entries in the mailbox audit log are retained for 90 days. | F45: Get-Mailbox -ResultSize Unlimited -Filter {RecipientTypeDetails -eq "UserMailbox"} | Set-Mailbox -AuditEnabled $true | G45: Get-Mailbox | FT Name,AuditEnabled
A46: Auditing AU | B46: Exchange | C46: Detect changes to eDiscovery and legal hold | D46: Your organization may require all mailbox data to be preserved for a specific period. You can use Litigation Hold or In-Place Hold to meet this requirement. After you place a mailbox on Litigation Hold or In-Place Hold, mailbox items that are modified or that are permanently deleted are preserved in the Recoverable Items folder. Use the hold report to keep track of when Hold is enabled or disabled in a given time period. For each of these change types, the report includes the user who made the change and the time and date the change was made. Regularly review the report to audit changes to eDiscovery and Hold settings to ensure that users that should be under Hold remain under Hold.
A47: Auditing AU | B47: Exchange | C47: List mailboxes under hold | D47: Your organization may require all mailbox data to be preserved for a specific period. You can use Litigation Hold or In-Place Hold to meet this requirement. After you place a user on Litigation Hold or In-Place Hold, mailbox items that are modified or that are permanently deleted are preserved in the Recoverable Items folder. If your organization is required to keep users under Hold, regularly review the Hold report to audit changes to settings.
A48: Auditing AU | B48: Exchange | C48: Review configuration changes in organization | D48: You can use the Exchange Admin Center to search for and view entries in the administrator audit log. The administrator audit log records specific actions, based on Exchange Management Shell cmdlet, performed by administrators and users who have been assigned administrative privileges. Entries in the administrator audit log provide you with information about what cmdlet was run, which parameters were used, who ran the cmdlet, and what objects were affected. Regularly review all configuration changes to ensure that only valid and approved changes have been made to the organization's settings. | G48: Get-AdminAuditLogConfig | FL AdminAuditLogEnabled
A49: Auditing AU | B49: Exchange | C49: Review mailbox access by datacenter administrators | D49: In Exchange Online, actions performed by Microsoft and delegated administrators are logged in the administrator audit log. You can use the Exchange Admin Center or PowerShell to search for and view audit log entries to determine if external administrators performed any actions on or changed the configuration of your Exchange Online organization. You can also use PowerShell to export these audit log entries. Regularly audit all activities performed by external administrators, including Microsoft service administrators. | G49: Search-AdminAuditLog -ExternalAccess $true
A50: Auditing AU | B50: O365 | C50: Office 365 User administration activities | D50: These are the administration activities that are logged when an admin adds or changes a user account. Added user, Changed user license, Changed user password, Deleted user, Reset user password, Set property that forces user to change password, Set license properties, Updated user. These activities can be used to review administrator activity on a regular basis to ensure that the activities performed are in accordance to organizational principles.
A51: Auditing AU | B51: O365 | C51: Office 365 Group administration activities | D51: Search these logs to identify activities related to an admin or a user creates or changes an Office 365 group or when an admin creates a security group. The activities logged are Added group, Added member to group, Deleted group, Removed member from group, Updated group
A52: Auditing AU | B52: O365 | C52: Application administration activities | D52: When an administrator adds or changes an application that's registered in Azure AD these activities are logged. Added delegation entry, Added service principal, Added service principal credentials, Removed delegation entry, Removed service principal, Removed service principal credentials, Set delegation entry. Keeping track of these entries are important since applications can be used to access customer data hence a rouge admin could use applications in an attempt to circumvent security. Both the registration of applications and actions carried by the applications like accessing customer data are logged.
A53: Auditing AU | B53: O365 | C53: Office 365 Role administration activities | D53: It is important to keep track of the Azure AD roles in Office 365 to detect potential attempts to elevate permissions. The role administration logging is logging the following activities Add member to Role, Removed a user from a directory role, Set company contact information.
A54: Auditing AU | B54: O365 | C54: Directory administration activities | D54: These are the Azure AD directory and domain related activities that are logged when an administrator manages admin roles. Added domain to company, Added partner to company, Removed domain from company, Removed partner from company, Set company information, Set domain authentication, Set federation settings on the domain, Set password policy, Turned on Azure AD sync, Updated domain, Verified domain, Verified email verified domain. These activities are important to ensure that delegation to partner as an example is not done without prior approval.
A55: Auditing AU | B55: O365 | C55: Search for eDiscovery activities | D55: Content Search and eDiscovery-related activities that are performed in Office 365 Security & Compliance Center or by running the corresponding Windows PowerShell cmdlets are logged in the Office 365 audit log. The following tasks are logged, Creating and managing eDiscovery cases, Creating, starting, and editing Content Searches, Performing Content Search actions, such as previewing, exporting, and deleting search results, Configuring permissions filtering for Content Search, Managing the eDiscovery Administrator role
A56: Auditing AU | B56: SharePoint | C56: SharePoint (Activity Report) | D56: Regularly review the Office 365 Activity Report in the Compliance Center to review user and administrator activity in your Office 365 tenant. The report contains entries for activity in Exchange Online, SharePoint Online, and OneDrive for Business, and administrator activity reports in Azure Active Directory.
A57: Auditing AU | B57: SharePoint | C57: File and folder activities | D57: This section of the reporting capture the file and folder activities in SharePoint Online and OneDrive for Business such as, Accessed file, Checked in file, Checked out file, Copied file, Deleted file, Discarded file checkout, Downloaded file, Modified file, Moved file, Renamed file, Restored file, Uploaded file. These can be invaluable to detect potential fraudulent behavior. | F57: Search-UnifiedAuditLog, Set-UnifiedAuditSetting | G57: Get-UnifiedAuditSetting
A58: Auditing AU | B58: SharePoint | C58: Sharing and access request activities | D58: The user sharing and access request activities in SharePoint Online and OneDrive for Business provide insight in to the key areas like Accepted access request, Accepted sharing invitation, Created a company-wide link, Created access request, Created an anonymous link, Created sharing invitation, Denied access request , Removed a company-wide link, Removed an anonymous link, Shared file, folder, or site, Updated an anonymous link, Used an anonymous link, Unshared file, folder, or site, Used a company-wide link, Withdrew sharing invitation. | F58: Search-UnifiedAuditLog, Set-UnifiedAuditSetting | G58: Get-UnifiedAuditSetting
A59: Auditing AU | B59: SharePoint | C59: Synchronization Activities | D59: This category is used to track file synchronization activities in SharePoint Online and OneDrive for Business. It track tasks such as, Allowed computer to sync files, Blocked computer from syncing files, Downloaded files to computer, Downloaded file changes to computer, Uploaded files to document library, Uploaded file changes to document library | F59: Search-UnifiedAuditLog, Set-UnifiedAuditSetting | G59: Get-UnifiedAuditSetting
A60: Auditing AU | B60: SharePoint | C60: Site administration activities | D60: The list of audited site administration tasks in SharePoint Online is rich and can be used to detect unwanted changes in the SharePoint configuration. Added exempt user agent, Added site collection administrator, Added user to group, Allowed user to create groups, Changed exempt user agents, Changed a sharing policy, Created group, Created Sent To connection, Created site collection, Deleted group, Deleted Sent To connection, Enabled document preview, Enabled legacy workflow, Enabled Office on Demand, Enabled RSS feeds, Enabled result source for People Searches, Modified site permissions, Removed user from group, Removed user from site collection, Renamed site, Requested site admin permissions, Set host site, Updated group | F60: Search-UnifiedAuditLog, Set-UnifiedAuditSetting | G60: Get-UnifiedAuditSetting
A61: Auditing AU | B61: SharePoint | C61: SharePoint Search queries Log | D61: In case of a breach, review the keywords that have been used in searches to help identify the information being sought.
A62: Auditing AU | B62: Azure Information Protection | C62: Azure Information Protection Logging | D62: Use the Azure Active Directory Rights Management Services (Information Protection) logs to audit requests, including requests from users, actions performed by Information Protection administrators in organizations, and actions performed by Microsoft operators to support Information Protection deployments. Information Protection writes logs in W3C extended log format into an Azure storage account that you provide. Information Protection logging information is available to you in near-real time, so that you can continuously monitor your company’s use of Information Protection . 99.9% of logs are available within 15 minutes of an Information Protection-initiated action. For example, you might want to be alerted if there is a sudden increase of people reading Information Protection-protected data outside standard working hours, which could indicate that a malicious user is collecting information to sell to competitors. Or, if the same user apparently accesses data from two different IP addresses within a short time frame, which could indicate that a user account has been compromised. If you have an information leak, you are likely to be asked who recently accessed specific documents and what information did a suspected person access recently. You can answer these type of questions when you use Information Protection and logging because people who use protected content must always get an Information Protection license to open documents and pictures that are protected by Information Protection, even if these files are moved by email or copied to USB drives or other storage devices. This means that you can use Information Protection logs as a definitive source of information for forensic analysis when you protect your data by using Information Protection. | F62: Enable-AadrmUsageLogFeature | G62: Get-AadrmConfiguration
A63: Auditing AU | B63: Azure Information Protection | C63: Track Protected Documents | D63: After you have protected your documents by using the Azure Active Directory Rights Management Services (Information Protection) sharing application, you can track how people are using your protected documents, and if necessary, revoke access to them when you want to stop sharing. To do this, you use the document tracking site, which you can access from Windows computers, Mac computers, and even from tablets and phones. Use Azure Active Directory Information Protection to track usage of protected information. Senders can view which recipients have opened file(s), information about unauthorized access attempts, and view the most recent state of the file.
A64: Auditing AU | B64: Azure Information Protection | C64: Detect viewing of documents centrally | D64: Use the Azure Active Directory Rights Management Services (Information Protection) logs to audit requests, including requests from users, actions performed by Information Protection administrators in organizations, and actions performed by Microsoft operators to support Information Protection deployments. Information Protection writes logs in W3C extended log format into an Azure storage account that you provide. Azure Active Directory Rights Management Services (Information Protection) logging can help you detect the use of protected information that may be out of policy or for forensic investigations. You can automate this process by consuming the security audit feed with a Security Information and Event Management system.
A65: Auditing AU | B65: O365 | C65: Office 365 Activity API | D65: The Office 365 Management APIs provide a single extensibility platform for all Office 365 customers’ and partners’ management tasks, including service communications, security, compliance, reporting, auditing, user management, and reseller management. All of the Office 365 Management APIs will be consistent in design and implementation with the current suite of Office 365 REST APIs, using common industry-standard approaches, including OAuth v2, OData v4, and JSON. Like the other Office 365 APIs, applications are registered in Azure Active Directory, giving developers a consistent way to authenticate and authorize their apps.
A66: Auditing AU | B66: O365 | C66: Office 365 Management Audit Log | D66: You can use the Office 365 activity report in the Office 365 Compliance Center to view user and admin activity in your Office 365 organization. The report contains entries for admin activity (admin audit logging) and access to mailboxes (mailbox audit logging) in Exchange Online, user and admin activity in SharePoint Online and OneDrive for Business, and admin activity and user sign-in activity in Azure Active Directory. Use the Office 365 Activity API to consume a feed of activity data from Office 365 to your on-premises Security Information and Event Management solution.
A67: Auditing AU | B67: O365 | C67: Microsoft Operators | D67: Microsoft Data Center Operator events can be identified by the UserType member being set to 3. This allow for organizations to specifically monitor the access and changes made by Microsoft Operators.
A68: Auditing AU | B68: O365 | C68: Applications | D68: Access made by Applications deployed in the tenant can be identified by the UserType Value being set to 5 or 6. This allow for organizations to monitor applications and their behavior.
A69: Auditing AU | B69: OnPrem | C69: Active Directory Federation Services | D69: Active Directory Federation Services (AD FS) includes its own dedicated performance counters to help you monitor the performance of both federation servers and federation server proxy computers. Configure performance monitoring for AD FS and keep track of suspicious log on patterns for on-premises accounts.
A70: Auditing AU | B70: OnPrem | C70: Performance Monitoring | D70: Active Directory Federation Services (AD FS) includes its own dedicated performance counters to help you monitor the performance of both federation servers and federation server proxy computers. Configure performance monitoring for AD FS and keep track of suspicious log on patterns for on-premises accounts.
A71: Auditing AU | B71: OnPrem | C71: Advanced Threat Analytics | D71: Microsoft Advanced Threat Analytics (ATA) helps you identify breaches and threats using behavioral analysis and provides a clear, actionable report on a simple attack timeline. It's a simple and fast way to understand what is happening within your network by identifying suspicious user and device activity with built-in intelligence and providing clear and relevant threat information on a simple attack timeline. ATA leverages deep packet inspection technology, as well as information from additional data sources (Security Information and Event Management and Active Directory) to build an Organizational Security Graph and detect advanced attacks in near real time. Use advanced threat analytics such as behavioral analysis to detect potential threats in your environment.
A72: Auditing AU | B72: OnPrem | C72: Azure AD Connect Health | D72: Azure AD Connect Health helps you monitor and gain insight into your on-premises identity infrastructure and the synchronization services available through Azure AD Connect. It offers you the ability to view alerts, performance, usage patterns, configuration settings, enables you to maintain a reliable connection to Office 365 and much more. Use Azure AD Connect to monitor the state of directory integration between your on-premises environment and Office 365.
A73: Auditing AU | B73: Exchange | C73: Exchange Online Protection Auditing Reports | D73: Auditing reports in Microsoft Exchange Online Protection (EOP) can help you meet regulatory, compliance, and litigation requirements for your organization. You can obtain auditing reports at any time to determine the changes that have been made to your EOP configuration. These reports can help you troubleshoot configuration issues or find the cause of security-related or compliance-related problems. Regularly review EOP audit reports to support security and compliance-related work.
A74: Auditing AU | B74: Exchange | C74: Exchange Online Protection Privileged Admin Changes | D74: When an administrator adds members to or removes members from administrator role groups, Microsoft Exchange Online Protection logs each occurrence. When you run an administrator role group report in the Exchange Admin Center, entries are displayed as search results and include the role groups affected, who changed the role group membership and when, and what membership updates were made. Use this report to monitor changes to the administrative permissions assigned to users in your organization. Regularly review all changes to privileged role groups to detect potentially harmful changes.
... A81: Client CM | B81: Client | C81: Microsoft Security Compliance Manager | D81: Security compliance Manager provides ready-to-deploy policies and DCM (Desired Configuration Management) configuration packs based on Microsoft security guide recommendations and industry best practices, allowing you to easily manage configuration drift and address compliance requirements for Windows operating systems, Office applications, and other Microsoft applications.
A82: Client CM | B82: Client | C82: Keep Browsers up to date | D82: Keeping browsers up to date is key for safety and security as well as user experience. There are many vulnerabilities that make use of outdated browsers. Identity theft, phishing sites, viruses, Trojans, spyware, adware, to name a few of the malwares exploiting browser vulnerabilities. | E82: Select Browser Used Report | G82: Get-O365ClientBrowserDetailReport
A83: Client CM | B83: Client | C83: Windows Information Protection (WIP) | D83: Windows Information Protection (WIP), helps to protect against this potential data leakage without otherwise interfering with the employee experience. WIP also helps to protect enterprise apps and data against accidental data leak on enterprise-owned devices and personal devices that employees bring to work without requiring changes to your environment or other apps. Finally, another data protection technology, Azure Rights Management also works alongside WIP to extend data protection for data that leaves the device, such as when email attachments are sent from an enterprise aware version of a rights management mail client.
A84: Client CM | B84: Client | C84: Certificate Pinning | D84: Certificate and Public Key Pinning is a technical guide to implementing certificate and public key pinning. Windows 10 has built in functionality for certificate pinning while previous versions rely on EMET to provide this functionality.
A85: Client CM | B85: Client | C85: Force Outlook Autodiscovery | D85: By default, Outlook uses several methods to reach the AutoDiscover service. For example, for a computer that is not joined to a domain, Outlook tries to connect to the predefined URLs (for example, https://autodiscover.contoso.com/autodiscover/autodiscover.xml) by using DNS. If that fails, Outlook tries the HTTP redirect method. If that does not work, Outlook tries to use the SRV record lookup method. If all lookup methods fail, Outlook cannot obtain "Outlook Anywhere" configuration and URL settings. This setting forces the method used.
A86: Client CM | B86: Client | C86: PC with other OS
A87: Client CM | B87: Client | C87: Keep OS up to date | D87: Keeping the Operating systems up to date is key to protect from malicious code that makes the system vulnerable for attack. Office 365 has reports that provide information about devices connecting to the system. | E87: Select OS Used Report | G87: Get-O365ClientOSDetailReport
A88: Client CM | B88: Client | C88: Keep Browsers up to date | D88: Keeping browsers up to date is key for safety and security as well as user experience. There are many vulnerabilities that make use of outdated browsers. Identity theft, phishing sites, viruses, Trojans, spyware, adware, to name a few of the malwares exploiting browser vulnerabilities. | E88: Select Browser Used Report | G88: Get-O365ClientBrowserDetailReport
A89: Client CM | B89: Client | C89: Anti Malware
A90: Client CM | B90: Client | C90: Intune | D90: Microsoft Intune is the management arm of Microsoft Enterprise Mobility + Security. Enterprise mobility is about enabling your employees to be productive on all of their devices while keeping your organization's information protected.
A91: Client CM | B91: Client | C91: Intune conditional Access Policy | D91: Intune Compliance policy settings are used to evaluate the compliance of the device. Conditional access policy uses the evaluation to restrict or allow access to a specific service. When a conditional access policy is used in combination with a compliance policy, only compliant devices will be allowed to access the service. The compliance policy and the conditional access policy are deployed to the user. Any device that the user uses to access the services is checked for compliance with the policies.
A92: Client CM | B92: Client | C92: Intune integration with Lookout | D92: You can control access from mobile devices to corporate resources, based on risk assessment conducted by Lookout, a device threat protection solution that is integrated with Microsoft Intune. The risk is based on telemetry that the Lookout service collects from devices for operating system (OS) vulnerabilities, installed malicious apps, and malicious network profiles. Based on Lookout's reported risk assessment enabled through Intune compliance policies, you can configure conditional access policies in Intune and allow or block devices that have been determined to be noncompliant due to threats detected on those devices.
A93: Client CM | B93: Client | C93: Remote Wipe | D93: If a device is stolen this function helps limiting the possibility of extracting information from the phone by completely wiping the information. | E93: RemoteWipe
A94: Client CM | B94: Client | C94: Policy Settings | D94: Strong password, not jailbroken, wipe if the incorrect password is used # of times and other policies that can be enforced if not met Office 365 will block the connection. | E94: Compliance Center
A95: Client CM | B95: Client | C95: Keep Device OS up to Date | D95: Keeping the Operating systems up to date is key to protect from malicious code that makes the system vulnerable for attack. Office 365 has reports that provide information about devices connecting to the system. | E95: Select OS Used Report | G95: Get-O365ClientOSDetailReport
A96: Client CM | B96: Client | C96: Mobile Devices
A97: Client CM | B97: Client | C97: Require password | D97: Ensure to enforce a healthy password policy on the devices. A weak password may trump other security investments made.
A98: Client CM | B98: Client | C98: Prevent simple passwords Mobile device does not prevent simple passwords | D98: Ensure to enforce a healthy password policy on the devices. A simple password may trump other security investments made,
A99: Client CM | B99: Client | C99: Require alphanumeric password | D99: Ensure to enforce a healthy password policy on the devices. A weak password may trump other security investments made.
A100: Client CM | B100: Client | C100: Require minimum password length | D100: Ensure to enforce a healthy password policy on the devices. A weak password may trump other security investments made.
A101: Client CM | B101: Client | C101: Require wipe on sign-in failures | D101: Ensure to enforce a healthy password policy on the devices. A weak password may trump other security investments made.
A102: Client CM | B102: Client | C102: Lock mobile device on inactivity | D102: Ensure to enforce a healthy password policy on the devices. A weak password may trump other security investments made.
A103: Client CM | B103: Client | C103: Expire password on Mobile Device | D103: Ensure to enforce a healthy password policy on the devices. A weak password may trump other security investments made.
A104: Client CM | B104: Client | C104: Prevent password re-use on the device | D104: Ensure to enforce a healthy password policy on the devices. A weak password may trump other security investments made.
A105: Client CM | B105: Client | C105: Require encryption on Mobile Device | D105: The encryption helps to safeguard information in the event a device is stolen or lost and someone attempt to extract information from the stolen device.
A106: Client CM | B106: Client | C106: Prevent jail broken or rooted devices from connecting | D106: Jail broken devices introduces a number of vulnerabilities to the overall system and should be blocked to maintain security of the system.
...

Sheet Malicious Admin
A1: Category | B1: Product | C1: Feature | D1: Description | E1: Portal | F1: PS Configure | G1: PS Get
A2: Admin AC | B2: Office 365 | C2: Separation of Duties | D2: Depending on the size of your organization, you may want to designate several admins who serve different functions. The admin has access to all features in the admin center, and can create or edit users, assign admin roles to others, reset user passwords, manage user licenses, and manage domains, among other things. Office 365 includes a security model that enables separation of administration based on roles. Certain admin roles Office 365 have a corresponding role in Exchange Online, SharePoint Online, and Skype for Business Online. | E2: Select the user and edit user roles
A3: Admin AC | B3: Exchange | C3: Separate Exchange Administrators | D3: Depending on the size of your organization, you may want to designate several admins who serve different functions. The admin has access to all features in the admin center, and can create or edit users, assign admin roles to others, reset user passwords, manage user licenses, and manage domains, among other things. Office 365 includes a security model that enables separation of administration based on roles. Certain admin roles Office 365 have a corresponding role in Exchange Online, SharePoint Online, and Skype for Business Online. Segment permissions to ensure that a single administrator doesn't have greater access than necessary. | E3: Select the user and edit user roles | F3: Set-MsolRoleMember | G3: Get-MsolRoleMember
A4: Admin AC | B4: SharePoint | C4: Separate SharePoint Administrators | D4: Depending on the size of your organization, you may want to designate several admins who serve different functions. The admin has access to all features in the admin center, and can create or edit users, assign admin roles to others, reset user passwords, manage user licenses, and manage domains, among other things. Office 365 includes a security model that enables separation of administration based on roles. Certain admin roles Office 365 have a corresponding role in Exchange Online, SharePoint Online, and Skype for Business Online. Segment permissions to ensure that a single administrator doesn't have greater access than necessary. | E4: Select the user and edit user roles | F4: Set-MsolRoleMember | G4: Get-MsolRoleMember
A5: Admin AC | B5: Skype4B | C5: Separate Skype for Business Administrators | D5: Depending on the size of your organization, you may want to designate several admins who serve different functions. The admin has access to all features in the admin center, and can create or edit users, assign admin roles to others, reset user passwords, manage user licenses, and manage domains, among other things. Office 365 includes a security model that enables separation of administration based on roles. Certain admin roles Office 365 have a corresponding role in Exchange Online, SharePoint Online, and Skype for Business Online. Segment permissions to ensure that a single administrator doesn't have greater access than necessary. | E5: Select the user and edit user roles | F5: Set-MsolRoleMember | G5: Get-MsolRoleMember
A6: Admin AC | B6: AzureAD | C6: Azure AD Privileged Identity Management | D6: Azure AD Privileged Identity Management lets you manage, control and monitor your privileged identities and their access to resources in Azure AD, and in other Microsoft online services such as Office 365 or Microsoft Intune. This feature provide the ability to implement just in time elevation for privileged actions.
A7: Admin AC | B7: Exchange | C7: Exchange Online Privileged Accounts | D7: Perform regular reviews of all users and groups with high levels of permissions. You can search the administrator audit logs to discover who made changes to organization, server, and recipient configuration. This can be helpful when you're trying to track the cause of unexpected behavior, to identify a malicious administrator, to investigate data leaks, or to verify that compliance requirements are being met. | E7: Permissions / Admin Groups
A8: Admin AC | B8: Exchange | C8: Administrator role group changes | D8: Verify that high-privileged roles have not been assigned to any un-authorized users. You can search the administrator audit logs or the Activity logs to discover who made changes to organization, server, and recipient configuration. This can be helpful when you're trying to track the cause of unexpected behavior, to identify a malicious administrator, to investigate data leaks, or to verify that compliance requirements are being met. | E8: Role Group Report | F8: On by default in Office 365 | G8: Get-AdminAuditLogConfig | FL AdminAuditLogEnabled, Search-AdminAuditLog
A9: Admin AC | B9: SharePoint | C9: SharePoint Online Permissions | D9: If you are a SharePoint Online admin, you probably want to control who can make changes on your site. Ensure that the proper users have administrative privileges to appropriate content. Each site collection has its own set of permission levels. SharePoint comes with some default permission levels that you can use, such as Contribute and View Only. But if one of those doesn’t meet your needs, you can create a new permissions level. It’s a best practice that you don’t change the default permission levels. See also https://support.office.com/en-us/article/How-to-create-and-edit-Permission-Levels-53c86040-07fa-4ea7-bc55-34ee96b437fe#__best_practices_for. | F9: Set-SPOSiteGroup, Set-SPOUser | G9: Get-SPOSiteGroup, Get-SPOUser
A10: Admin AC | B10: SharePoint | C10: Review Modification of permissions | D10: Changes to user accounts and permissions should happen regularly to quickly respond to potentially malicious activities. Knowing who has done what with which information is critical for many business requirements, such as regulatory compliance and records management. You can use the audit feature in SharePoint Online to track which users have taken what actions on the sites, content types, lists, libraries, list items, and library files within your site collections. | F10: Set-SPOSiteGroup, Set-SPOUser | G10: Get-SPOSiteGroup, Get-SPOUser
A11: Admin AC | B11: Office 365 | C11: Review Delegated Partner Administrators | D11: Ensure that partner organizations don't have standing access to the environment unless warranted. This will limit the potential attack surface.
A12: Auditing AU | B12: AzureAD | C12: Azure AD | D12: Use Azure Active Directory (Azure AD) access and usage reports to gain visibility into the integrity and security of your organization’s directory. With this information, a directory admin can better determine where possible security risks may lie so that they can adequately plan to mitigate those risks. Audit all account actions and use Azure AD reports to identify potential fraudulent activities.
A13: Auditing AU | B13: AzureAD | C13: Azure AD Audit Events | D13: Identify privileged actions that occur in Azure Active Directory, including elevation changes, password changes, and so forth. Automate this process by consuming the security audit feed with a Security Information and Event Management system. (SIEM)
A14: Auditing AU | B14: Exchange | C14: Exchange Online Privileged Administrator changes | D14: You can search the administrator audit logs to discover who made changes to organization, server, and recipient configuration. This can be helpful when you're trying to track the cause of unexpected behavior, to identify a malicious administrator, or to verify that compliance requirements are being met. Regularly review all changes to privileged role groups to detect potentially harmful changes.
A15: Auditing AU | B15: Exchange | C15: Detect non-owner mailbox access | D15: Audit non-owner access activity to identify potential leaks of information and to proactively review non-owner access to mailboxes. The Non-Owner Mailbox Access Report in the Exchange Admin Center lists the mailboxes that have been accessed by someone other than the person who owns the mailbox. When a mailbox is accessed by a non-owner, Exchange logs information about this action in a mailbox audit log that’s stored as an email message in a hidden folder in the mailbox being audited. Entries from this log are displayed as search results and include a list of mailboxes accessed by a non-owner, who accessed the mailbox and when, the actions performed by the non-owner, and whether the action was successful. By default, entries in the mailbox audit log are retained for 90 days. | F15: Get-Mailbox -ResultSize Unlimited -Filter {RecipientTypeDetails -eq "UserMailbox"} | Set-Mailbox -AuditEnabled $true | G15: Get-Mailbox | FT Name,AuditEnabled
A16: Auditing AU | B16: Exchange | C16: Detect changes to eDiscovery and legal hold | D16: Your organization may require all mailbox data to be preserved for a specific period. You can use Litigation Hold or In-Place Hold to meet this requirement. After you place a mailbox on Litigation Hold or In-Place Hold, mailbox items that are modified or that are permanently deleted are preserved in the Recoverable Items folder. Use the hold report to keep track of when Hold is enabled or disabled in a given time period. For each of these change types, the report includes the user who made the change and the time and date the change was made. Regularly review the report to audit changes to eDiscovery and Hold settings to ensure that users that should be under Hold remain under Hold.
A17: Auditing AU | B17: Exchange | C17: Review configuration changes in organization | D17: You can use the Exchange Admin Center to search for and view entries in the administrator audit log. The administrator audit log records specific actions, based on Exchange Management Shell cmdlet, performed by administrators and users who have been assigned administrative privileges. Entries in the administrator audit log provide you with information about what cmdlet was run, which parameters were used, who ran the cmdlet, and what objects were affected. Regularly review all configuration changes to ensure that only valid and approved changes have been made to the organization's settings. | G17: Get-AdminAuditLogConfig | FL AdminAuditLogEnabled
A18: Auditing AU | B18: Office 365 | C18: Office 365 User administration activities | D18: These are the administration activities that are logged when an admin adds or changes a user account. Added user, Changed user license, Changed user password, Deleted user, Reset user password, Set property that forces user to change password, Set license properties, Updated user. These activities can be used to review administrator activity on a regular basis to ensure that the activities performed are in accordance to organizational principles.
A19: Auditing AU | B19: Office 365 | C19: Office 365 Group administration activities | D19: Search these logs to identify activities related to an admin or a user creates or changes an Office 365 group or when an admin creates a security group. The activities logged are Added group, Added member to group, Deleted group, Removed member from group, Updated group
A20: Auditing AU | B20: Office 365 | C20: Application administration activities | D20: When an administrator adds or changes an application that's registered in Azure AD these activities are logged. Added delegation entry, Added service principal, Added service principal credentials, Removed delegation entry, Removed service principal, Removed service principal credentials, Set delegation entry. Keeping track of these entries are important since applications can be used to access customer data hence a rouge admin could use applications in an attempt to circumvent security. Both the registration of applications and actions carried by the applications like accessing customer data are logged.
A21: Auditing AU | B21: Office 365 | C21: Office 365 Role administration activities | D21: It is important to keep track of the Azure AD roles in Office 365 to detect potential attempts to elevate permissions. The role administration logging is logging the following activities Add member to Role, Removed a user from a directory role, Set company contact information.
