Workbook
Name KEY_Control_Frequency: KEY!$E$17:$E$24
Name KEY_Control_Function: KEY!$C$17:$C$22
Name KEY_Control_Owner: KEY!$H$17:$H$21
Name KEY_Control_Status: KEY!$G$17:$G$20
Name KEY_Control_Type: KEY!$A$17:$A$19
Name Key_Risk_Irating: KEY!$J$3:$J$7
Name KEY_Risk_Lrating: KEY!$G$3:$G$7
Name KEY_Risk_Rating: KEY!$C$3:$C$7
Name KEY_Risk_Source: KEY!$A$3:$A$7
Name KEY_Risk_Status: KEY!$E$3:$E$8
Name Slicer_SOURCE: #N/A
Name Slicer_Status: #N/A

Sheet Index
B1: RISK INDEX
B2: Category | C2: Threat ID | D2: Threat Action | E2: TOTAL Risks | F2: HIGH Risks | G2: MED Risks | H2: LOW Risks | I2: Unaddressed Risks
B3: Physical | C3: PHY-001 | D3: Loss of Property | E3: =COUNTIF('Risk Register'!#REF!,"*"&C3&"*") -> #REF! | F3: =COUNTIFS('Risk Register'!#REF!,"*"&C3&"*",'Risk Register'!M:M,">=16") -> #REF! | G3: =COUNTIFS('Risk Register'!#REF!,"*"&C3&"*",'Risk Register'!M:M,">=7",'Risk Register'!M:M,"<=15") -> #REF! | H3: =COUNTIFS('Risk Register'!#REF!,"*"&C3&"*",'Risk Register'!M:M,"<=6") -> #REF! | I3: =SUM(COUNTIFS('Risk Register'!#REF!,"*"&C3&"*",'Risk Register'!S6:S55,{"Not Considered","Partial Controls"})) -> #REF!
B4: Physical | C4: PHY-002 | D4: Theft of Property | E4: =COUNTIF('Risk Register'!#REF!,"*"&C4&"*") -> #REF! | F4: =COUNTIFS('Risk Register'!#REF!,"*"&C4&"*",'Risk Register'!M:M,">=16") -> #REF! | G4: =COUNTIFS('Risk Register'!#REF!,"*"&C4&"*",'Risk Register'!M:M,">=7",'Risk Register'!M:M,"<=15") -> #REF! | H4: =COUNTIFS('Risk Register'!#REF!,"*"&C4&"*",'Risk Register'!M:M,"<=6") -> #REF!
B5: Physical | C5: PHY-003 | D5: Accidental Destruction of Property | E5: =COUNTIF('Risk Register'!#REF!,"*"&C5&"*") -> #REF! | F5: =COUNTIFS('Risk Register'!#REF!,"*"&C5&"*",'Risk Register'!M:M,">=16") -> #REF! | G5: =COUNTIFS('Risk Register'!#REF!,"*"&C5&"*",'Risk Register'!M:M,">=7",'Risk Register'!M:M,"<=15") -> #REF! | H5: =COUNTIFS('Risk Register'!#REF!,"*"&C5&"*",'Risk Register'!M:M,"<=6") -> #REF!
B6: Physical | C6: PHY-004 | D6: Natural Destruction of Property | E6: =COUNTIF('Risk Register'!#REF!,"*"&C6&"*") -> #REF! | F6: =COUNTIFS('Risk Register'!#REF!,"*"&C6&"*",'Risk Register'!M:M,">=16") -> #REF! | G6: =COUNTIFS('Risk Register'!#REF!,"*"&C6&"*",'Risk Register'!M:M,">=7",'Risk Register'!M:M,"<=15") -> #REF! | H6: =COUNTIFS('Risk Register'!#REF!,"*"&C6&"*",'Risk Register'!M:M,"<=6") -> #REF!
B7: Physical | C7: PHY-005 | D7: Intentional Destruction of Property | E7: =COUNTIF('Risk Register'!#REF!,"*"&C7&"*") -> #REF! | F7: =COUNTIFS('Risk Register'!#REF!,"*"&C7&"*",'Risk Register'!M:M,">=16") -> #REF! | G7: =COUNTIFS('Risk Register'!#REF!,"*"&C7&"*",'Risk Register'!M:M,">=7",'Risk Register'!M:M,"<=15") -> #REF! | H7: =COUNTIFS('Risk Register'!#REF!,"*"&C7&"*",'Risk Register'!M:M,"<=6") -> #REF!
B8: Physical | C8: PHY-006 | D8: Intentional Sabotage of Property | E8: =COUNTIF('Risk Register'!#REF!,"*"&C8&"*") -> #REF! | F8: =COUNTIFS('Risk Register'!#REF!,"*"&C8&"*",'Risk Register'!M:M,">=16") -> #REF! | G8: =COUNTIFS('Risk Register'!#REF!,"*"&C8&"*",'Risk Register'!M:M,">=7",'Risk Register'!M:M,"<=15") -> #REF! | H8: =COUNTIFS('Risk Register'!#REF!,"*"&C8&"*",'Risk Register'!M:M,"<=6") -> #REF!
B9: Physical | C9: PHY-007 | D9: Intentional Vandalism of Property | E9: =COUNTIF('Risk Register'!#REF!,"*"&C9&"*") -> #REF! | F9: =COUNTIFS('Risk Register'!#REF!,"*"&C9&"*",'Risk Register'!M:M,">=16") -> #REF! | G9: =COUNTIFS('Risk Register'!#REF!,"*"&C9&"*",'Risk Register'!M:M,">=7",'Risk Register'!M:M,"<=15") -> #REF! | H9: =COUNTIFS('Risk Register'!#REF!,"*"&C9&"*",'Risk Register'!M:M,"<=6") -> #REF!
B10: Physical | C10: PHY-008 | D10: Electrical System Failure | E10: =COUNTIF('Risk Register'!#REF!,"*"&C10&"*") -> #REF! | F10: =COUNTIFS('Risk Register'!#REF!,"*"&C10&"*",'Risk Register'!M:M,">=16") -> #REF! | G10: =COUNTIFS('Risk Register'!#REF!,"*"&C10&"*",'Risk Register'!M:M,">=7",'Risk Register'!M:M,"<=15") -> #REF! | H10: =COUNTIFS('Risk Register'!#REF!,"*"&C10&"*",'Risk Register'!M:M,"<=6") -> #REF!
B11: Physical | C11: PHY-009 | D11: HVAC Failure | E11: =COUNTIF('Risk Register'!#REF!,"*"&C11&"*") -> #REF! | F11: =COUNTIFS('Risk Register'!#REF!,"*"&C11&"*",'Risk Register'!M:M,">=16") -> #REF! | G11: =COUNTIFS('Risk Register'!#REF!,"*"&C11&"*",'Risk Register'!M:M,">=7",'Risk Register'!M:M,"<=15") -> #REF! | H11: =COUNTIFS('Risk Register'!#REF!,"*"&C11&"*",'Risk Register'!M:M,"<=6") -> #REF!
B12: Physical | C12: PHY-010 | D12: Structural Facility Failure | E12: =COUNTIF('Risk Register'!#REF!,"*"&C12&"*") -> #REF! | F12: =COUNTIFS('Risk Register'!#REF!,"*"&C12&"*",'Risk Register'!M:M,">=16") -> #REF! | G12: =COUNTIFS('Risk Register'!#REF!,"*"&C12&"*",'Risk Register'!M:M,">=7",'Risk Register'!M:M,"<=15") -> #REF! | H12: =COUNTIFS('Risk Register'!#REF!,"*"&C12&"*",'Risk Register'!M:M,"<=6") -> #REF!
B13: Physical | C13: PHY-011 | D13: Water Distribution System Failure | E13: =COUNTIF('Risk Register'!#REF!,"*"&C13&"*") -> #REF! | F13: =COUNTIFS('Risk Register'!#REF!,"*"&C13&"*",'Risk Register'!M:M,">=16") -> #REF! | G13: =COUNTIFS('Risk Register'!#REF!,"*"&C13&"*",'Risk Register'!M:M,">=7",'Risk Register'!M:M,"<=15") -> #REF! | H13: =COUNTIFS('Risk Register'!#REF!,"*"&C13&"*",'Risk Register'!M:M,"<=6") -> #REF!
B14: Physical | C14: PHY-012 | D14: Sanitation System Failure | E14: =COUNTIF('Risk Register'!#REF!,"*"&C14&"*") -> #REF! | F14: =COUNTIFS('Risk Register'!#REF!,"*"&C14&"*",'Risk Register'!M:M,">=16") -> #REF! | G14: =COUNTIFS('Risk Register'!#REF!,"*"&C14&"*",'Risk Register'!M:M,">=7",'Risk Register'!M:M,"<=15") -> #REF! | H14: =COUNTIFS('Risk Register'!#REF!,"*"&C14&"*",'Risk Register'!M:M,"<=6") -> #REF!
B15: Physical | C15: PHY-013 | D15: Natural Gas Distribution of Failure | E15: =COUNTIF('Risk Register'!#REF!,"*"&C15&"*") -> #REF! | F15: =COUNTIFS('Risk Register'!#REF!,"*"&C15&"*",'Risk Register'!M:M,">=16") -> #REF! | G15: =COUNTIFS('Risk Register'!#REF!,"*"&C15&"*",'Risk Register'!M:M,">=7",'Risk Register'!M:M,"<=15") -> #REF! | H15: =COUNTIFS('Risk Register'!#REF!,"*"&C15&"*",'Risk Register'!M:M,"<=6") -> #REF!
... B77: Technical | C77: TEC-041 | D77: Application Exploitation via Authentication Bypass | E77: =COUNTIF('Risk Register'!#REF!,"*"&C77&"*") -> #REF! | F77: =COUNTIFS('Risk Register'!#REF!,"*"&C77&"*",'Risk Register'!M:M,">=16") -> #REF! | G77: =COUNTIFS('Risk Register'!#REF!,"*"&C77&"*",'Risk Register'!M:M,">=7",'Risk Register'!M:M,"<=15") -> #REF! | H77: =COUNTIFS('Risk Register'!#REF!,"*"&C77&"*",'Risk Register'!M:M,"<=6") -> #REF!

Sheet Risk Register
B1: RISK REGISTER
B5: RISK ID | C5: SOURCE | D5: DATE Identified | E5: Risk Name | F5: Risk Description | G5: Framework Reference | H5: Likelihood | I5: SCORE Likelihood | J5: Impact | K5: SCORE Impact | L5: SCORE Risk | M5: Risk Rating | N5: Mitigation Plan | O5: Mitigation Milestones & Changes | P5: Point of Contact | Q5: Control(s) or Mitigation Action | R5: Control Reference | S5: Status | T5: DATE Status | U5: Review Needed?
B6: RR001 | H6: Probable | I6: =VLOOKUP(Tbl_RiskRegister[[#This Row],[Likelihood]],KEY!$G$3:$H$7,2,) -> 4 | J6: Critical Impact | K6: =VLOOKUP(Tbl_RiskRegister[[#This Row],[Impact]],KEY!$J$3:$K$7,2,0) -> 7 | L6: =Tbl_RiskRegister[[#This Row],[SCORE Likelihood]]*Tbl_RiskRegister[[#This Row],[SCORE Impact]] -> 28 | M6: =IF(Tbl_RiskRegister[[#This Row],[SCORE Risk]]<=7,"Low",(IF(Tbl_RiskRegister[[#This Row],[SCORE Risk]]<=19,"Medium",(IF(Tbl_RiskRegister[[#This Row],[SCORE Risk]]>19,"High","Error"))))) -> High | S6: Not Considered | U6: =IF(T6=0,"",(IF((TODAY()-T6)>365,"YES","No")))
B7: RR002 | H7: Probable | I7: =VLOOKUP(Tbl_RiskRegister[[#This Row],[Likelihood]],KEY!$G$3:$H$7,2,) -> 4 | J7: Substanative Impact | K7: =VLOOKUP(Tbl_RiskRegister[[#This Row],[Impact]],KEY!$J$3:$K$7,2,0) -> 5 | L7: =Tbl_RiskRegister[[#This Row],[SCORE Likelihood]]*Tbl_RiskRegister[[#This Row],[SCORE Impact]] -> 20 | M7: =IF(Tbl_RiskRegister[[#This Row],[SCORE Risk]]<=7,"Low",(IF(Tbl_RiskRegister[[#This Row],[SCORE Risk]]<=19,"Medium",(IF(Tbl_RiskRegister[[#This Row],[SCORE Risk]]>19,"High","Error"))))) -> High
B8: RR003 | H8: Possible | I8: =VLOOKUP(Tbl_RiskRegister[[#This Row],[Likelihood]],KEY!$G$3:$H$7,2,) -> 3 | J8: Substanative Impact | K8: =VLOOKUP(Tbl_RiskRegister[[#This Row],[Impact]],KEY!$J$3:$K$7,2,0) -> 5 | L8: =Tbl_RiskRegister[[#This Row],[SCORE Likelihood]]*Tbl_RiskRegister[[#This Row],[SCORE Impact]] -> 15 | M8: =IF(Tbl_RiskRegister[[#This Row],[SCORE Risk]]<=7,"Low",(IF(Tbl_RiskRegister[[#This Row],[SCORE Risk]]<=19,"Medium",(IF(Tbl_RiskRegister[[#This Row],[SCORE Risk]]>19,"High","Error"))))) -> Medium | S8: Not Considered
B9: RR004 | H9: Possible | I9: =VLOOKUP(Tbl_RiskRegister[[#This Row],[Likelihood]],KEY!$G$3:$H$7,2,) -> 3 | J9: Substanative Impact | K9: =VLOOKUP(Tbl_RiskRegister[[#This Row],[Impact]],KEY!$J$3:$K$7,2,0) -> 5 | L9: =Tbl_RiskRegister[[#This Row],[SCORE Likelihood]]*Tbl_RiskRegister[[#This Row],[SCORE Impact]] -> 15 | M9: =IF(Tbl_RiskRegister[[#This Row],[SCORE Risk]]<=7,"Low",(IF(Tbl_RiskRegister[[#This Row],[SCORE Risk]]<=19,"Medium",(IF(Tbl_RiskRegister[[#This Row],[SCORE Risk]]>19,"High","Error"))))) -> Medium
B10: RR005 | H10: Almost Certain | I10: =VLOOKUP(Tbl_RiskRegister[[#This Row],[Likelihood]],KEY!$G$3:$H$7,2,) -> 5 | J10: Substanative Impact | K10: =VLOOKUP(Tbl_RiskRegister[[#This Row],[Impact]],KEY!$J$3:$K$7,2,0) -> 5 | L10: =Tbl_RiskRegister[[#This Row],[SCORE Likelihood]]*Tbl_RiskRegister[[#This Row],[SCORE Impact]] -> 25 | M10: =IF(Tbl_RiskRegister[[#This Row],[SCORE Risk]]<=7,"Low",(IF(Tbl_RiskRegister[[#This Row],[SCORE Risk]]<=19,"Medium",(IF(Tbl_RiskRegister[[#This Row],[SCORE Risk]]>19,"High","Error"))))) -> High | N10: Develop, Approve IS Policy Education & Ack plan | O10: In Development | R10: CC 1.3.3 | S10: Deficient Controls | T10: 44411
B11: RR006 | H11: Possible | I11: =VLOOKUP(Tbl_RiskRegister[[#This Row],[Likelihood]],KEY!$G$3:$H$7,2,) -> 3 | J11: Substanative Impact | K11: =VLOOKUP(Tbl_RiskRegister[[#This Row],[Impact]],KEY!$J$3:$K$7,2,0) -> 5 | L11: =Tbl_RiskRegister[[#This Row],[SCORE Likelihood]]*Tbl_RiskRegister[[#This Row],[SCORE Impact]] -> 15 | M11: =IF(Tbl_RiskRegister[[#This Row],[SCORE Risk]]<=7,"Low",(IF(Tbl_RiskRegister[[#This Row],[SCORE Risk]]<=19,"Medium",(IF(Tbl_RiskRegister[[#This Row],[SCORE Risk]]>19,"High","Error"))))) -> Medium
B12: RR007 | H12: Possible | I12: =VLOOKUP(Tbl_RiskRegister[[#This Row],[Likelihood]],KEY!$G$3:$H$7,2,) -> 3 | J12: Substanative Impact | K12: =VLOOKUP(Tbl_RiskRegister[[#This Row],[Impact]],KEY!$J$3:$K$7,2,0) -> 5 | L12: =Tbl_RiskRegister[[#This Row],[SCORE Likelihood]]*Tbl_RiskRegister[[#This Row],[SCORE Impact]] -> 15 | M12: =IF(Tbl_RiskRegister[[#This Row],[SCORE Risk]]<=7,"Low",(IF(Tbl_RiskRegister[[#This Row],[SCORE Risk]]<=19,"Medium",(IF(Tbl_RiskRegister[[#This Row],[SCORE Risk]]>19,"High","Error"))))) -> Medium | N12: Define Logging/Auditing Plan Determine Retention Goals
B13: RR008 | H13: Possible | I13: =VLOOKUP(Tbl_RiskRegister[[#This Row],[Likelihood]],KEY!$G$3:$H$7,2,) -> 3 | J13: Substanative Impact | K13: =VLOOKUP(Tbl_RiskRegister[[#This Row],[Impact]],KEY!$J$3:$K$7,2,0) -> 5 | L13: =Tbl_RiskRegister[[#This Row],[SCORE Likelihood]]*Tbl_RiskRegister[[#This Row],[SCORE Impact]] -> 15 | M13: =IF(Tbl_RiskRegister[[#This Row],[SCORE Risk]]<=7,"Low",(IF(Tbl_RiskRegister[[#This Row],[SCORE Risk]]<=19,"Medium",(IF(Tbl_RiskRegister[[#This Row],[SCORE Risk]]>19,"High","Error"))))) -> Medium
B14: RR009 | H14: Possible | I14: =VLOOKUP(Tbl_RiskRegister[[#This Row],[Likelihood]],KEY!$G$3:$H$7,2,) -> 3 | J14: Substanative Impact | K14: =VLOOKUP(Tbl_RiskRegister[[#This Row],[Impact]],KEY!$J$3:$K$7,2,0) -> 5 | L14: =Tbl_RiskRegister[[#This Row],[SCORE Likelihood]]*Tbl_RiskRegister[[#This Row],[SCORE Impact]] -> 15 | M14: =IF(Tbl_RiskRegister[[#This Row],[SCORE Risk]]<=7,"Low",(IF(Tbl_RiskRegister[[#This Row],[SCORE Risk]]<=19,"Medium",(IF(Tbl_RiskRegister[[#This Row],[SCORE Risk]]>19,"High","Error"))))) -> Medium
B15: RR010 | H15: Possible | I15: =VLOOKUP(Tbl_RiskRegister[[#This Row],[Likelihood]],KEY!$G$3:$H$7,2,) -> 3 | J15: Substanative Impact | K15: =VLOOKUP(Tbl_RiskRegister[[#This Row],[Impact]],KEY!$J$3:$K$7,2,0) -> 5 | L15: =Tbl_RiskRegister[[#This Row],[SCORE Likelihood]]*Tbl_RiskRegister[[#This Row],[SCORE Impact]] -> 15 | M15: =IF(Tbl_RiskRegister[[#This Row],[SCORE Risk]]<=7,"Low",(IF(Tbl_RiskRegister[[#This Row],[SCORE Risk]]<=19,"Medium",(IF(Tbl_RiskRegister[[#This Row],[SCORE Risk]]>19,"High","Error"))))) -> Medium
B16: RR011 | H16: Possible | I16: =VLOOKUP(Tbl_RiskRegister[[#This Row],[Likelihood]],KEY!$G$3:$H$7,2,) -> 3 | J16: Substanative Impact | K16: =VLOOKUP(Tbl_RiskRegister[[#This Row],[Impact]],KEY!$J$3:$K$7,2,0) -> 5 | L16: =Tbl_RiskRegister[[#This Row],[SCORE Likelihood]]*Tbl_RiskRegister[[#This Row],[SCORE Impact]] -> 15 | M16: =IF(Tbl_RiskRegister[[#This Row],[SCORE Risk]]<=7,"Low",(IF(Tbl_RiskRegister[[#This Row],[SCORE Risk]]<=19,"Medium",(IF(Tbl_RiskRegister[[#This Row],[SCORE Risk]]>19,"High","Error"))))) -> Medium
B17: RR012 | H17: Possible | I17: =VLOOKUP(Tbl_RiskRegister[[#This Row],[Likelihood]],KEY!$G$3:$H$7,2,) -> 3 | J17: Substanative Impact | K17: =VLOOKUP(Tbl_RiskRegister[[#This Row],[Impact]],KEY!$J$3:$K$7,2,0) -> 5 | L17: =Tbl_RiskRegister[[#This Row],[SCORE Likelihood]]*Tbl_RiskRegister[[#This Row],[SCORE Impact]] -> 15 | M17: =IF(Tbl_RiskRegister[[#This Row],[SCORE Risk]]<=7,"Low",(IF(Tbl_RiskRegister[[#This Row],[SCORE Risk]]<=19,"Medium",(IF(Tbl_RiskRegister[[#This Row],[SCORE Risk]]>19,"High","Error"))))) -> Medium
B18: RR013 | H18: Possible | I18: =VLOOKUP(Tbl_RiskRegister[[#This Row],[Likelihood]],KEY!$G$3:$H$7,2,) -> 3 | J18: Substanative Impact | K18: =VLOOKUP(Tbl_RiskRegister[[#This Row],[Impact]],KEY!$J$3:$K$7,2,0) -> 5 | L18: =Tbl_RiskRegister[[#This Row],[SCORE Likelihood]]*Tbl_RiskRegister[[#This Row],[SCORE Impact]] -> 15 | M18: =IF(Tbl_RiskRegister[[#This Row],[SCORE Risk]]<=7,"Low",(IF(Tbl_RiskRegister[[#This Row],[SCORE Risk]]<=19,"Medium",(IF(Tbl_RiskRegister[[#This Row],[SCORE Risk]]>19,"High","Error"))))) -> Medium
B19: RR014 | H19: Possible | I19: =VLOOKUP(Tbl_RiskRegister[[#This Row],[Likelihood]],KEY!$G$3:$H$7,2,) -> 3 | J19: Substanative Impact | K19: =VLOOKUP(Tbl_RiskRegister[[#This Row],[Impact]],KEY!$J$3:$K$7,2,0) -> 5 | L19: =Tbl_RiskRegister[[#This Row],[SCORE Likelihood]]*Tbl_RiskRegister[[#This Row],[SCORE Impact]] -> 15 | M19: =IF(Tbl_RiskRegister[[#This Row],[SCORE Risk]]<=7,"Low",(IF(Tbl_RiskRegister[[#This Row],[SCORE Risk]]<=19,"Medium",(IF(Tbl_RiskRegister[[#This Row],[SCORE Risk]]>19,"High","Error"))))) -> Medium
B20: RR015 | H20: Possible | I20: =VLOOKUP(Tbl_RiskRegister[[#This Row],[Likelihood]],KEY!$G$3:$H$7,2,) -> 3 | J20: Substanative Impact | K20: =VLOOKUP(Tbl_RiskRegister[[#This Row],[Impact]],KEY!$J$3:$K$7,2,0) -> 5 | L20: =Tbl_RiskRegister[[#This Row],[SCORE Likelihood]]*Tbl_RiskRegister[[#This Row],[SCORE Impact]] -> 15 | M20: =IF(Tbl_RiskRegister[[#This Row],[SCORE Risk]]<=7,"Low",(IF(Tbl_RiskRegister[[#This Row],[SCORE Risk]]<=19,"Medium",(IF(Tbl_RiskRegister[[#This Row],[SCORE Risk]]>19,"High","Error"))))) -> Medium
B21: RR016 | H21: Possible | I21: =VLOOKUP(Tbl_RiskRegister[[#This Row],[Likelihood]],KEY!$G$3:$H$7,2,) -> 3 | J21: Substanative Impact | K21: =VLOOKUP(Tbl_RiskRegister[[#This Row],[Impact]],KEY!$J$3:$K$7,2,0) -> 5 | L21: =Tbl_RiskRegister[[#This Row],[SCORE Likelihood]]*Tbl_RiskRegister[[#This Row],[SCORE Impact]] -> 15 | M21: =IF(Tbl_RiskRegister[[#This Row],[SCORE Risk]]<=7,"Low",(IF(Tbl_RiskRegister[[#This Row],[SCORE Risk]]<=19,"Medium",(IF(Tbl_RiskRegister[[#This Row],[SCORE Risk]]>19,"High","Error"))))) -> Medium
B22: RR017 | H22: Possible | I22: =VLOOKUP(Tbl_RiskRegister[[#This Row],[Likelihood]],KEY!$G$3:$H$7,2,) -> 3 | J22: Substanative Impact | K22: =VLOOKUP(Tbl_RiskRegister[[#This Row],[Impact]],KEY!$J$3:$K$7,2,0) -> 5 | L22: =Tbl_RiskRegister[[#This Row],[SCORE Likelihood]]*Tbl_RiskRegister[[#This Row],[SCORE Impact]] -> 15 | M22: =IF(Tbl_RiskRegister[[#This Row],[SCORE Risk]]<=7,"Low",(IF(Tbl_RiskRegister[[#This Row],[SCORE Risk]]<=19,"Medium",(IF(Tbl_RiskRegister[[#This Row],[SCORE Risk]]>19,"High","Error"))))) -> Medium
B23: RR018 | H23: Possible | I23: =VLOOKUP(Tbl_RiskRegister[[#This Row],[Likelihood]],KEY!$G$3:$H$7,2,) -> 3 | J23: Substanative Impact | K23: =VLOOKUP(Tbl_RiskRegister[[#This Row],[Impact]],KEY!$J$3:$K$7,2,0) -> 5 | L23: =Tbl_RiskRegister[[#This Row],[SCORE Likelihood]]*Tbl_RiskRegister[[#This Row],[SCORE Impact]] -> 15 | M23: =IF(Tbl_RiskRegister[[#This Row],[SCORE Risk]]<=7,"Low",(IF(Tbl_RiskRegister[[#This Row],[SCORE Risk]]<=19,"Medium",(IF(Tbl_RiskRegister[[#This Row],[SCORE Risk]]>19,"High","Error"))))) -> Medium
B24: RR019 | H24: Possible | I24: =VLOOKUP(Tbl_RiskRegister[[#This Row],[Likelihood]],KEY!$G$3:$H$7,2,) -> 3 | J24: Substanative Impact | K24: =VLOOKUP(Tbl_RiskRegister[[#This Row],[Impact]],KEY!$J$3:$K$7,2,0) -> 5 | L24: =Tbl_RiskRegister[[#This Row],[SCORE Likelihood]]*Tbl_RiskRegister[[#This Row],[SCORE Impact]] -> 15 | M24: =IF(Tbl_RiskRegister[[#This Row],[SCORE Risk]]<=7,"Low",(IF(Tbl_RiskRegister[[#This Row],[SCORE Risk]]<=19,"Medium",(IF(Tbl_RiskRegister[[#This Row],[SCORE Risk]]>19,"High","Error"))))) -> Medium
... B55: RR050 | H55: Improbable | I55: =VLOOKUP(Tbl_RiskRegister[[#This Row],[Likelihood]],KEY!$G$3:$H$7,2,) -> 1 | J55: Substanative Impact | K55: =VLOOKUP(Tbl_RiskRegister[[#This Row],[Impact]],KEY!$J$3:$K$7,2,0) -> 5 | L55: =Tbl_RiskRegister[[#This Row],[SCORE Likelihood]]*Tbl_RiskRegister[[#This Row],[SCORE Impact]] -> 5 | M55: =IF(Tbl_RiskRegister[[#This Row],[SCORE Risk]]<=7,"Low",(IF(Tbl_RiskRegister[[#This Row],[SCORE Risk]]<=19,"Medium",(IF(Tbl_RiskRegister[[#This Row],[SCORE Risk]]>19,"High","Error"))))) -> Low
B57: Last Revised
B58: =TODAY() -> 44426

Sheet Controls Lib.
B1: CONTROLS Library
B5: Control ID | C5: Control Name | D5: Description | E5: Control TYPE | F5: Control FUNCTION | G5: Frequency | H5: Owner | I5: Evidence | J5: Risk Mapping | K5: Compliance Mapping | L5: Status | M5: DATE Implementation | N5: DATE Review or Validation | O5: Review Needed?
B6: VC001 | C6: Employee Handbook | D6: Personnel are reguired to read and accept the Employee Handbook upon hire. | E6: Administrative | F6: Preventative | G6: N/A | H6: HR | I6: Employee Handbook Signed Acknowledgements | J6: RR003 | K6: CC 1.1.1 | L6: Implemented | M6: 43494 | N6: 44343 | O6: =IF(Tbl_ControlLib[[#This Row],[DATE Review or Validation]]=0,"",(IF((TODAY()-Tbl_ControlLib[[#This Row],[DATE Review or Validation]])>365,"YES","No"))) -> No
B7: VC002 | O7: =IF(Tbl_ControlLib[[#This Row],[DATE Review or Validation]]=0,"",(IF((TODAY()-Tbl_ControlLib[[#This Row],[DATE Review or Validation]])>365,"YES","No")))
B8: VC003 | O8: =IF(Tbl_ControlLib[[#This Row],[DATE Review or Validation]]=0,"",(IF((TODAY()-Tbl_ControlLib[[#This Row],[DATE Review or Validation]])>365,"YES","No")))
B9: VC004 | O9: =IF(Tbl_ControlLib[[#This Row],[DATE Review or Validation]]=0,"",(IF((TODAY()-Tbl_ControlLib[[#This Row],[DATE Review or Validation]])>365,"YES","No")))
B10: VC005 | O10: =IF(Tbl_ControlLib[[#This Row],[DATE Review or Validation]]=0,"",(IF((TODAY()-Tbl_ControlLib[[#This Row],[DATE Review or Validation]])>365,"YES","No")))
B11: VC006 | O11: =IF(Tbl_ControlLib[[#This Row],[DATE Review or Validation]]=0,"",(IF((TODAY()-Tbl_ControlLib[[#This Row],[DATE Review or Validation]])>365,"YES","No")))
B12: VC007 | C12: IR Plan | D12: Incident Response plan is exercised and updated and/or reviewed annually | E12: Administrative | F12: Recovery | G12: 1yr | H12: SC | I12: IR Plan (with revision block) Notes/Lessons Learned for IR exercies | K12: CC 2.2.5 | L12: Draft | O12: =IF(Tbl_ControlLib[[#This Row],[DATE Review or Validation]]=0,"",(IF((TODAY()-Tbl_ControlLib[[#This Row],[DATE Review or Validation]])>365,"YES","No")))
B13: VC008 | C13: Risk Mgmt | D13: Risk Mgmt Policy and Risk Assessment/Mitigation tracking | E13: Administrative | F13: Preventative | G13: 1mo | H13: SC | I13: IS Policy Risk Register Monthly Agenda's | K13: CC 3.1.1 CC 3.1.2 | L13: Draft | O13: =IF(Tbl_ControlLib[[#This Row],[DATE Review or Validation]]=0,"",(IF((TODAY()-Tbl_ControlLib[[#This Row],[DATE Review or Validation]])>365,"YES","No")))
B14: VC009 | O14: =IF(Tbl_ControlLib[[#This Row],[DATE Review or Validation]]=0,"",(IF((TODAY()-Tbl_ControlLib[[#This Row],[DATE Review or Validation]])>365,"YES","No")))
B15: VC010 | O15: =IF(Tbl_ControlLib[[#This Row],[DATE Review or Validation]]=0,"",(IF((TODAY()-Tbl_ControlLib[[#This Row],[DATE Review or Validation]])>365,"YES","No")))
B16: VC011 | O16: =IF(Tbl_ControlLib[[#This Row],[DATE Review or Validation]]=0,"",(IF((TODAY()-Tbl_ControlLib[[#This Row],[DATE Review or Validation]])>365,"YES","No")))
B17: VC012 | O17: =IF(Tbl_ControlLib[[#This Row],[DATE Review or Validation]]=0,"",(IF((TODAY()-Tbl_ControlLib[[#This Row],[DATE Review or Validation]])>365,"YES","No")))
B18: VC013 | O18: =IF(Tbl_ControlLib[[#This Row],[DATE Review or Validation]]=0,"",(IF((TODAY()-Tbl_ControlLib[[#This Row],[DATE Review or Validation]])>365,"YES","No")))
B19: VC014 | O19: =IF(Tbl_ControlLib[[#This Row],[DATE Review or Validation]]=0,"",(IF((TODAY()-Tbl_ControlLib[[#This Row],[DATE Review or Validation]])>365,"YES","No")))
B20: VC015 | O20: =IF(Tbl_ControlLib[[#This Row],[DATE Review or Validation]]=0,"",(IF((TODAY()-Tbl_ControlLib[[#This Row],[DATE Review or Validation]])>365,"YES","No")))
B21: VC016 | O21: =IF(Tbl_ControlLib[[#This Row],[DATE Review or Validation]]=0,"",(IF((TODAY()-Tbl_ControlLib[[#This Row],[DATE Review or Validation]])>365,"YES","No")))
B22: VC017 | O22: =IF(Tbl_ControlLib[[#This Row],[DATE Review or Validation]]=0,"",(IF((TODAY()-Tbl_ControlLib[[#This Row],[DATE Review or Validation]])>365,"YES","No")))
B23: VC018 | O23: =IF(Tbl_ControlLib[[#This Row],[DATE Review or Validation]]=0,"",(IF((TODAY()-Tbl_ControlLib[[#This Row],[DATE Review or Validation]])>365,"YES","No")))
B24: VC019 | O24: =IF(Tbl_ControlLib[[#This Row],[DATE Review or Validation]]=0,"",(IF((TODAY()-Tbl_ControlLib[[#This Row],[DATE Review or Validation]])>365,"YES","No")))
B25: VC020 | O25: =IF(Tbl_ControlLib[[#This Row],[DATE Review or Validation]]=0,"",(IF((TODAY()-Tbl_ControlLib[[#This Row],[DATE Review or Validation]])>365,"YES","No")))
... B55: VC050 | O55: =IF(Tbl_ControlLib[[#This Row],[DATE Review or Validation]]=0,"",(IF((TODAY()-Tbl_ControlLib[[#This Row],[DATE Review or Validation]])>365,"YES","No")))
B57: Last Revised
B58: =TODAY() -> 44426

Sheet SOC Obj.
A1: TSC Ref. # | B1: TSC | C1: Points of Focus | D1: NIST CSF
A2: CC 1 | B2: CONTROL ENVIRONMENT
A3: CC 1.1 | B3: COSO Principle 1: The entity demonstrates a commitment to integrity and ethical values.
A4: CC 1.1.1 | C4: Sets the Tone at the Top—The board of directors and management, at all levels, demonstrate through their directives, actions, and behavior the importance of integrity and ethical values to support the functioning of the system of internal control. | D4: PR.AT-4
A5: CC 1.1.2 | C5: Establishes Standards of Conduct—The expectations of the board of directors and senior management concerning integrity and ethical values are defined in the entity’s standards of conduct and understood at all levels of the entity and by outsourced service providers and business partners.
A6: CC 1.1.3 | C6: Evaluates Adherence to Standards of Conduct—Processes are in place to evaluate the performance of individuals and teams against the entity’s expected standards of conduct.
A7: CC 1.1.4 | C7: Addresses Deviations in a Timely Manner—Deviations from the entity’s expected standards of conduct are identified and remedied in a timely and consistent manner.
A8: CC 1.1.5 | C8: Considers Contractors and Vendor Employees in Demonstrating Its Commitment—Management and the board of directors consider the use of contractors and vendor employees in its processes for establishing standards of conduct, evaluating adherence to those standards, and addressing deviations in a timely manner.
A9: CC 1.2 | B9: COSO Principle 2: The board of directors demonstrates independence from management and exercises oversight of the development and performance of internal control.
A10: CC 1.2.1 | C10: Establishes Oversight Responsibilities—The board of directors identifies and accepts its oversight responsibilities in relation to established requirements and expectations.
A11: CC 1.2.2 | C11: Applies Relevant Expertise—The board of directors defines, maintains, and periodically evaluates the skills and expertise needed among its members to enable them to ask probing questions of senior management and take commensurate action.
A12: CC 1.2.3 | C12: Operates Independently—The board of directors has sufficient members who are independent from management and objective in evaluations and decision making.
A13: CC 1.2.4 | C13: Supplements Board Expertise—The board of directors supplements its expertise relevant to security, availability, processing integrity, confidentiality, and privacy, as needed, through the use of a subcommittee or consultants.
A14: CC 1.3 | B14: COSO Principle 3: Management establishes, with board oversight, structures, reporting lines, and appropriate authorities and responsibilities in the pursuit of objectives.
A15: CC 1.3.1 | C15: Considers All Structures of the Entity—Management and the board of directors consider the multiple structures used (including operating units, legal entities, geographic distribution, and outsourced service providers) to support the achievement of objectives.
A16: CC 1.3.2 | C16: Establishes Reporting Lines—Management designs and evaluates lines of reporting for each entity structure to enable execution of authorities and responsibilities and flow of information to manage the activities of the entity.
A17: CC 1.3.3 | C17: Defines, Assigns, and Limits Authorities and Responsibilities—Management and the board of directors delegate authority, define responsibilities, and use appropriate processes and technology to assign responsibility and segregate duties as necessary at the various levels of the organization. | D17: ID.AM-6
A18: CC 1.3.4 | C18: Addresses Specific Requirements When Defining Authorities and Responsibilities—Management and the board of directors consider requirements relevant to security, availability, processing integrity, confidentiality, and privacy when defining authorities and responsibilities.
A19: CC 1.3.5 | C19: Considers Interactions With External Parties When Establishing Structures, Reporting Lines, Authorities, and Responsibilities—Management and the board of directors consider the need for the entity to interact with and monitor the activities of external parties when establishing structures, reporting lines, authorities, and responsibilities.
A20: CC 1.4 | B20: COSO Principle 4: The entity demonstrates a commitment to attract, develop, and retain competent individuals in alignment with objectives.
A21: CC 1.4.1 | C21: Establishes Policies and Practices—Policies and practices reflect expectations of competence necessary to support the achievement of objectives.
A22: CC 1.4.2 | C22: Evaluates Competence and Addresses Shortcomings—The board of directors and management evaluate competence across the entity and in outsourced service providers in relation to established policies and practices and act as necessary to address shortcomings.
A23: CC 1.4.3 | C23: Attracts, Develops, and Retains Individuals—The entity provides the mentoring and training needed to attract, develop, and retain sufficient and competent personnel and outsourced service providers to support the achievement of objectives.
A24: CC 1.4.4 | C24: Plans and Prepares for Succession—Senior management and the board of directors develop contingency plans for assignments of responsibility important for internal control.
A25: CC 1.4.5 | C25: Considers the Background of Individuals—The entity considers the background of potential and existing personnel, contractors, and vendor employees when determining whether to employ and retain the individuals. | D25: PR.IP-11
A26: CC 1.4.6 | C26: Considers the Technical Competency of Individuals—The entity considers the technical competency of potential and existing personnel, contractors, and vendor employees when determining whether to employ and retain the individuals.
A27: CC 1.4.7 | C27: Provides Training to Maintain Technical Competencies— The entity provides training programs, including continuing education and training, to ensure skill sets and technical competency of existing personnel, contractors, and vendor employees are developed and maintained.
A28: CC 1.5 | B28: COSO Principle 5: The entity holds individuals accountable for their internal control responsibilities in the pursuit of objectives.
A29: CC 1.5.1 | C29: Enforces Accountability Through Structures, Authorities, and Responsibilities—Management and the board of directors establish the mechanisms to communicate and hold individuals accountable for performance of internal control responsibilities across the entity and implement corrective action as necessary.
A30: CC 1.5.2 | C30: Establishes Performance Measures, Incentives, and Rewards—Management and the board of directors establish performance measures, incentives, and other rewards appropriate for responsibilities at all levels of the entity, reflecting appropriate dimensions of performance and expected standards of conduct, and considering the achievement of both short-term and longer-term objectives.
A31: CC 1.5.3 | C31: Evaluates Performance Measures, Incentives, and Rewards for Ongoing Relevance—Management and the board of directors align incentives and rewards with the fulfillment of internal control responsibilities in the achievement of objectives.
A32: CC 1.5.4 | C32: Considers Excessive Pressures—Management and the board of directors evaluate and adjust pressures associated with the achievement of objectives as they assign responsibilities, develop performance measures, and evaluate performance.
A33: CC 1.5.5 | C33: Evaluates Performance and Rewards or Disciplines Individuals—Management and the board of directors evaluate performance of internal control responsibilities, including adherence to standards of conduct and expected levels of competence, and provide rewards or exercise disciplinary action, as appropriate.
A34: CC 2 | B34: COMMUNICATION AND INFORMATION
A35: CC 2.1 | B35: COSO Principle 13: The entity obtains or generates and uses relevant, quality information to support the functioning of internal control.
A36: CC 2.1.1 | C36: Identifies Information Requirements—A process is in place to identify the information required and expected to support the functioning of the other components of internal control and the achievement of the entity’s objectives.
A37: CC 2.1.2 | C37: Captures Internal and External Sources of Data—Information systems capture internal and external sources of data.
A38: CC 2.1.3 | C38: Processes Relevant Data Into Information—Information systems process and transform relevant data into information.
A39: CC 2.1.4 | C39: Maintains Quality Throughout Processing—Information systems produce information that is timely, current, accurate, complete, accessible, protected, verifiable, and retained. Information is reviewed to assess its relevance in supporting the internal control components.
A40: CC 2.2 | B40: COSO Principle 14: The entity internally communicates information, including objectives and responsibilities for internal control, necessary to support the functioning of internal control.
A41: CC 2.2.1 | C41: Communicates Internal Control Information—A process is in place to communicate required information to enable all personnel to understand and carry out their internal control responsibilities. | D41: PR.AT-1, PR.AT-2, PR.AT-5
A42: CC 2.2.2 | C42: Communicates With the Board of Directors—Communication exists between management and the board of directors so that both have information needed to fulfill their roles with respect to the entity’s objectives. | D42: PR.AT-4
A43: CC 2.2.3 | C43: Provides Separate Communication Lines—Separate communication channels, such as whistle-blower hotlines, are in place and serve as fail-safe mechanisms to enable anonymous or confidential communication when normal channels are inoperative or ineffective.
A44: CC 2.2.4 | C44: Selects Relevant Method of Communication—The method of communication considers the timing, audience, and nature of the information.
A45: CC 2.2.5 | C45: Communicates Responsibilities—Entity personnel with responsibility for designing, developing, implementing, operating, maintaining, or monitoring system controls receive communications about their responsibilities, including changes in their responsibilities, and have the information necessary to carry out those responsibilities. | D45: PR.AT-1, PR.AT-2
A46: CC 2.2.6 | C46: Communicates Information on Reporting Failures, Incidents, Concerns, and Other Matters—Entity personnel are provided with information on how to report systems failures, incidents, concerns, and other complaints to personnel. | D46: PR.AT-1
A47: CC 2.2.7 | C47: Communicates Objectives and Changes to Objectives —The entity communicates its objectives and changes to those objectives to personnel in a timely manner.
A48: CC 2.2.8 | C48: Communicates Information to Improve Security Knowledge and Awareness—The entity communicates information to improve security knowledge and awareness and to model appropriate security behaviors to personnel through a security awareness training program. | D48: PR.AT-1
A49: CC 2.2.9 | C49: Communicates Information About System Operation and Boundaries—The entity prepares and communicates information about the design and operation of the system and its boundaries to authorized personnel to enable them to understand their role in the system and the results of system operation.
A50: CC 2.2.10 | C50: Communicates System Objectives—The entity communicates its objectives to personnel to enable them to carry out their responsibilities. | D50: PR.AT-1
A51: CC 2.2.11 | C51: Communicates System Changes—System changes that affect responsibilities or the achievement of the entity's objectives are communicated in a timely manner.
A52: CC 2.3 | B52: COSO Principle 15: The entity communicates with external parties regarding matters affecting the functioning of internal control.
A53: CC 2.3.1 | C53: Communicates to External Parties—Processes are in place to communicate relevant and timely information to external parties, including shareholders, partners, owners, regulators, customers, financial analysts, and other external parties. | D53: PR.IP-8
A54: CC 2.3.2 | C54: Enables Inbound Communications—Open communication channels allow input from customers, consumers, suppliers, external auditors, regulators, financial analysts, and others, providing management and the board of directors with relevant information.
A55: CC 2.3.3 | C55: Communicates With the Board of Directors—Relevant information resulting from assessments conducted by external parties is communicated to the board of directors.
A56: CC 2.3.4 | C56: Provides Separate Communication Lines—Separate communication channels, such as whistle-blower hotlines, are in place and serve as fail-safe mechanisms to enable anonymous or confidential communication when normal channels are inoperative or ineffective.
A57: CC 2.3.5 | C57: Selects Relevant Method of Communication—The method of communication considers the timing, audience, and nature of the communication and legal, regulatory, and fiduciary requirements and expectations.
A58: CC 2.3.6 | C58: Communicates Objectives Related to Confidentiality and Changes to Objectives— The entity communicates, to external users, vendors, business partners and others whose products and services are part of the system, objectives and changes to objectives related to confidentiality.
A59: CC 2.3.7 | C59: Communicates Objectives Related to Privacy and Changes to Objectives—The entity communicates, to external users, vendors, business partners and others whose products and services are part of the system, objectives related to privacy and changes to those objectives.
A60: CC 2.3.8 | C60: Communicates Information About System Operation and Boundaries—The entity prepares and communicates information about the design and operation of the system and its boundaries to authorized external users to permit users to understand their role in the system and the results of system operation.
A61: CC 2.3.9 | C61: Communicates System Objectives—The entity communicates its system objectives to appropriate external users.
A62: CC 2.3.10 | C62: Communicates System Responsibilities—External users with responsibility for designing, developing, implementing, operating, maintaining, and monitoring system controls receive communications about their responsibilities and have the information necessary to carry out those responsibilities. | D62: PR.AT-1, PR.AT-3
A63: CC 2.3.11 | C63: Communicates Information on Reporting System Failures, Incidents, Concerns, and Other Matters—External users are provided with information on how to report systems failures, incidents, concerns, and other complaints to appropriate personnel. | D63: PR.AT-1
A64: CC 3 | B64: RISK ASSESSMENT
A65: CC 3.1 | B65: COSO Principle 6: The entity specifies objectives with sufficient clarity to enable the identification and assessment of risks relating to objectives.
A66: CC 3.1.1 | C66: Operations Ojectives
A67: CC 3.1.2 | C67: Reflects Management's Choices—Operations objectives reflect management's choices about structure, industry considerations, and performance of the entity. | D67: ID.BE-1, ID.BE-2, ID.BE-3, ID.BE-4, ID.BE-5
A68: CC 3.1.3 | C68: Considers Tolerances for Risk—Management considers the acceptable levels of variation relative to the achievement of operations objectives. | D68: ID.RM-2, ID.RM-3
A69: CC 3.1.4 | C69: Includes Operations and Financial Performance Goals—The organization reflects the desired level of operations and financial performance for the entity within operations objectives. | D69: ID.GV-4
A70: CC 3.1.5 | C70: Forms a Basis for Committing of Resources—Management uses operations objectives as a basis for allocating resources needed to attain desired operations and financial performance. | D70: ID.RM-3
A71: CC 3.1.6 | C71: External Financial Reporting Objectives
A72: CC 3.1.7 | C72: Complies With Applicable Accounting Standards—Financial reporting objectives are consistent with accounting principles suitable and available for that entity. The accounting principles selected are appropriate in the circumstances.
A73: CC 3.1.8 | C73: Considers Materiality—Management considers materiality in financial statement presentation. | D73: ID.RM-2
A74: CC 3.1.9 | C74: Reflects Entity Activities—External reporting reflects the underlying transactions and events to show qualitative characteristics and assertions.
A75: CC 3.1.10 | C75: External Nonfinancial Reporting Objectives
A76: CC 3.1.11 | C76: Complies With Externally Established Frameworks—Management establishes objectives consistent with laws and regulations or standards and frameworks of recognized external organizations.
A77: CC 3.1.12 | C77: Considers the Required Level of Precision—Management reflects the required level of precision and accuracy suitable for user needs and based on criteria established by third parties in nonfinancial reporting. | D77: ID.RM-2
A78: CC 3.1.13 | C78: Reflects Entity Activities—External reporting reflects the underlying transactions and events within a range of acceptable limits.
A79: CC 3.1.14 | C79: Internal Reporting Objectives
A80: CC 3.1.15 | C80: Reflects Management's Choices—Internal reporting provides management with accurate and complete information regarding management's choices and information needed in managing the entity.
A81: CC 3.1.16 | C81: Considers the Required Level of Precision—Management reflects the required level of precision and accuracy suitable for user needs in nonfinancial reporting objectives and materiality within financial reporting objectives.
A82: CC 3.1.17 | C82: Reflects Entity Activities—Internal reporting reflects the underlying transactions and events within a range of acceptable limits.
A83: CC 3.1.18 | C83: Compliance Objectives
A84: CC 3.1.19 | C84: Reflects External Laws and Regulations—Laws and regulations establish minimum standards of conduct, which the entity integrates into compliance objectives. | D84: ID.GV-3
A85: CC 3.1.20 | C85: Considers Tolerances for Risk—Management considers the acceptable levels of variation relative to the achievement of operations objectives. | D85: ID.RM-3
A86: CC 3.1.21 | C86: Establishes Sub-objectives to Support Objectives—Management identifies sub-objectives related to security, availability, processing integrity, confidentiality, and privacy to support the achievement of the entity’s objectives related to reporting, operations, and compliance. | D86: ID.RM-2
A87: CC 3.2 | B87: COSO Principle 7: The entity identifies risks to the achievement of its objectives across the entity and analyzes risks as a basis for determining how the risks should be managed.
A88: CC 3.2.1 | C88: Includes Entity, Subsidiary, Division, Operating Unit, and Functional Levels—The entity identifies and assesses risk at the entity, subsidiary, division, operating unit, and functional levels relevant to the achievement of objectives. | D88: ID.RA-1, ID.RA-2
A89: CC 3.2.2 | C89: Analyzes Internal and External Factors—Risk identification considers both internal and external factors and their impact on the achievement of objectives. | D89: ID.RA-1, ID.RA-2, ID.RA-3, ID.RA-5
A90: CC 3.2.3 | C90: Involves Appropriate Levels of Management—The entity puts into place effective risk assessment mechanisms that involve appropriate levels of management.
A91: CC 3.2.4 | C91: Estimates Significance of Risks Identified—Identified risks are analyzed through a process that includes estimating the potential significance of the risk. | D91: ID.RA-4
A92: CC 3.2.5 | C92: Determines How to Respond to Risks—Risk assessment includes considering how the risk should be managed and whether to accept, avoid, reduce, or share the risk. | D92: ID.RA-6
A93: CC 3.2.6 | C93: Identifies and Assesses Criticality of Information Assets and Identifies Threats and Vulnerabilities—The entity's risk identification and assessment process includes (1) identifying information assets, including physical devices and systems, virtual devices, software, data and data flows, external information systems, and organizational roles; (2) assessing the criticality of those information assets; (3) identifying the threats to the assets from intentional (including malicious) and unintentional acts and environmental events; and (4) identifying the vulnerabilities of the identified assets. | D93: ID.AM-1, ID.AM-2, ID.AM-3, ID.AM-4, ID.AM-5
A94: CC 3.2.7 | C94: Analyzes Threats and Vulnerabilities From Vendors, Business Partners, and Other Parties—The entity's risk assessment process includes the analysis of potential threats and vulnerabilities arising from vendors providing goods and services, as well as threats and vulnerabilities arising from business partners, customers, and others with access to the entity's information systems.
A95: CC 3.2.8 | C95: Considers the Significance of the Risk—The entity’s consideration of the potential significance of the identified risks includes (1) determining the criticality of identified assets in meeting objectives; (2) assessing the impact of identified threats and vulnerabilities in meeting objectives; (3) assessing the likelihood of identified threats; and (4) determining the risk associated with assets based on asset criticality, threat impact, and likelihood.
A96: CC 3.3 | B96: COSO Principle 8: The entity considers the potential for fraud in assessing risks to the achievement of objectives.
A97: CC 3.3.1 | C97: Considers Various Types of Fraud—The assessment of fraud considers fraudulent reporting, possible loss of assets, and corruption resulting from the various ways that fraud and misconduct can occur.
A98: CC 3.3.2 | C98: Assesses Incentives and Pressures—The assessment of fraud risks considers incentives and pressures.
A99: CC 3.3.3 | C99: Assesses Opportunities—The assessment of fraud risk considers opportunities for unauthorized acquisition, use, or disposal of assets, altering the entity’s reporting records, or committing other inappropriate acts.
A100: CC 3.3.4 | C100: Assesses Attitudes and Rationalizations—The assessment of fraud risk considers how management and other personnel might engage in or justify inappropriate actions.
...

Sheet AICPA TSC
A1: TSC REF | B1: Trust Services Criteria | C1: POINTS OF FOCUS | D1: NIST REF
B2: CONTROL ENVIRONMENT
A3: CC 1.1 | B3: COSO Principle 1: The entity demonstrates a commitment to integrity and ethical values.
A4: CC 1.1.1 | C4: Sets the Tone at the Top—The board of directors and management, at all levels, demonstrate through their directives, actions, and behavior the importance of integrity and ethical values to support the functioning of the system of internal control. | D4: PR.AT-4
A5: CC 1.1.2 | C5: Establishes Standards of Conduct—The expectations of the board of directors and senior management concerning integrity and ethical values are defined in the entity’s standards of conduct and understood at all levels of the entity and by outsourced service providers and business partners.
A6: CC 1.1.3 | C6: Evaluates Adherence to Standards of Conduct—Processes are in place to evaluate the performance of individuals and teams against the entity’s expected standards of conduct.
A7: CC 1.1.4 | C7: Addresses Deviations in a Timely Manner—Deviations from the entity’s expected standards of conduct are identified and remedied in a timely and consistent manner.
A8: CC 1.1.5 | C8: Considers Contractors and Vendor Employees in Demonstrating Its Commitment—Management and the board of directors consider the use of contractors and vendor employees in its processes for establishing standards of conduct, evaluating adherence to those standards, and addressing deviations in a timely manner.
A9: CC 1.2 | B9: COSO Principle 2: The board of directors demonstrates independence from management and exercises oversight of the development and performance of internal control.
A10: CC 1.2.1 | C10: Establishes Oversight Responsibilities—The board of directors identifies and accepts its oversight responsibilities in relation to established requirements and expectations.
A11: CC 1.2.2 | C11: Applies Relevant Expertise—The board of directors defines, maintains, and periodically evaluates the skills and expertise needed among its members to enable them to ask probing questions of senior management and take commensurate action.
A12: CC 1.2.3 | C12: Operates Independently—The board of directors has sufficient members who are independent from management and objective in evaluations and decision making.
A13: CC 1.2.4 | C13: Supplements Board Expertise—The board of directors supplements its expertise relevant to security, availability, processing integrity, confidentiality, and privacy, as needed, through the use of a subcommittee or consultants.
A14: CC 1.3 | B14: COSO Principle 3: Management establishes, with board oversight, structures, reporting lines, and appropriate authorities and responsibilities in the pursuit of objectives.
A15: CC 1.3.1 | C15: Considers All Structures of the Entity—Management and the board of directors consider the multiple structures used (including operating units, legal entities, geographic distribution, and outsourced service providers) to support the achievement of objectives.
A16: CC 1.3.2 | C16: Establishes Reporting Lines—Management designs and evaluates lines of reporting for each entity structure to enable execution of authorities and responsibilities and flow of information to manage the activities of the entity.
A17: CC 1.3.3 | C17: Defines, Assigns, and Limits Authorities and Responsibilities—Management and the board of directors delegate authority, define responsibilities, and use appropriate processes and technology to assign responsibility and segregate duties as necessary at the various levels of the organization. | D17: ID.AM-6
A18: CC 1.3.4 | C18: Addresses Specific Requirements When Defining Authorities and Responsibilities—Management and the board of directors consider requirements relevant to security, availability, processing integrity, confidentiality, and privacy when defining authorities and responsibilities.
A19: CC 1.3.5 | C19: Considers Interactions With External Parties When Establishing Structures, Reporting Lines, Authorities, and Responsibilities—Management and the board of directors consider the need for the entity to interact with and monitor the activities of external parties when establishing structures, reporting lines, authorities, and responsibilities.
A20: CC 1.4 | B20: COSO Principle 4: The entity demonstrates a commitment to attract, develop, and retain competent individuals in alignment with objectives.
A21: CC 1.4.1 | C21: Establishes Policies and Practices—Policies and practices reflect expectations of competence necessary to support the achievement of objectives.
A22: CC 1.4.2 | C22: Evaluates Competence and Addresses Shortcomings—The board of directors and management evaluate competence across the entity and in outsourced service providers in relation to established policies and practices and act as necessary to address shortcomings.
A23: CC 1.4.3 | C23: Attracts, Develops, and Retains Individuals—The entity provides the mentoring and training needed to attract, develop, and retain sufficient and competent personnel and outsourced service providers to support the achievement of objectives.
A24: CC 1.4.4 | C24: Plans and Prepares for Succession—Senior management and the board of directors develop contingency plans for assignments of responsibility important for internal control.
A25: CC 1.4.5 | C25: Considers the Background of Individuals—The entity considers the background of potential and existing personnel, contractors, and vendor employees when determining whether to employ and retain the individuals. | D25: PR.IP-11
A26: CC 1.4.6 | C26: Considers the Technical Competency of Individuals—The entity considers the technical competency of potential and existing personnel, contractors, and vendor employees when determining whether to employ and retain the individuals.
A27: CC 1.4.7 | C27: Provides Training to Maintain Technical Competencies— The entity provides training programs, including continuing education and training, to ensure skill sets and technical competency of existing personnel, contractors, and vendor employees are developed and maintained.
A28: CC 1.5 | B28: COSO Principle 5: The entity holds individuals accountable for their internal control responsibilities in the pursuit of objectives.
A29: CC 1.5.1 | C29: Enforces Accountability Through Structures, Authorities, and Responsibilities—Management and the board of directors establish the mechanisms to communicate and hold individuals accountable for performance of internal control responsibilities across the entity and implement corrective action as necessary.
A30: CC 1.5.2 | C30: Establishes Performance Measures, Incentives, and Rewards—Management and the board of directors establish performance measures, incentives, and other rewards appropriate for responsibilities at all levels of the entity, reflecting appropriate dimensions of performance and expected standards of conduct, and considering the achievement of both short-term and longer-term objectives.
A31: CC 1.5.3 | C31: Evaluates Performance Measures, Incentives, and Rewards for Ongoing Relevance—Management and the board of directors align incentives and rewards with the fulfillment of internal control responsibilities in the achievement of objectives.
A32: CC 1.5.4 | C32: Considers Excessive Pressures—Management and the board of directors evaluate and adjust pressures associated with the achievement of objectives as they assign responsibilities, develop performance measures, and evaluate performance.
A33: CC 1.5.5 | C33: Evaluates Performance and Rewards or Disciplines Individuals—Management and the board of directors evaluate performance of internal control responsibilities, including adherence to standards of conduct and expected levels of competence, and provide rewards or exercise disciplinary action, as appropriate.
B34: COMMUNICATION AND INFORMATION
A35: CC2.1 | B35: COSO Principle 13: The entity obtains or generates and uses relevant, quality information to support the functioning of internal control.
C36: Identifies Information Requirements—A process is in place to identify the information required and expected to support the functioning of the other components of internal control and the achievement of the entity’s objectives.
C37: Captures Internal and External Sources of Data—Information systems capture internal and external sources of data.
C38: Processes Relevant Data Into Information—Information systems process and transform relevant data into information.
C39: Maintains Quality Throughout Processing—Information systems produce information that is timely, current, accurate, complete, accessible, protected, verifiable, and retained. Information is reviewed to assess its relevance in supporting the internal control components.
A40: CC2.2 | B40: COSO Principle 14: The entity internally communicates information, including objectives and responsibilities for internal control, necessary to support the functioning of internal control.
C41: Communicates Internal Control Information—A process is in place to communicate required information to enable all personnel to understand and carry out their internal control responsibilities. | D41: PR.AT-1
D42: PR.AT-2
D43: PR.AT-5
C44: Communicates With the Board of Directors—Communication exists between management and the board of directors so that both have information needed to fulfill their roles with respect to the entity’s objectives. | D44: PR.AT-4
C45: Provides Separate Communication Lines—Separate communication channels, such as whistle-blower hotlines, are in place and serve as fail-safe mechanisms to enable anonymous or confidential communication when normal channels are inoperative or ineffective.
C46: Selects Relevant Method of Communication—The method of communication considers the timing, audience, and nature of the information.
C47: Communicates Responsibilities—Entity personnel with responsibility for designing, developing, implementing, operating, maintaining, or monitoring system controls receive communications about their responsibilities, including changes in their responsibilities, and have the information necessary to carry out those responsibilities. | D47: PR.AT-1
D48: PR.AT-2
C49: Communicates Information on Reporting Failures, Incidents, Concerns, and Other Matters—Entity personnel are provided with information on how to report systems failures, incidents, concerns, and other complaints to personnel. | D49: PR.AT-1
C50: Communicates Objectives and Changes to Objectives —The entity communicates its objectives and changes to those objectives to personnel in a timely manner.
C51: Communicates Information to Improve Security Knowledge and Awareness—The entity communicates information to improve security knowledge and awareness and to model appropriate security behaviors to personnel through a security awareness training program. | D51: PR.AT-1
C52: Communicates Information About System Operation and Boundaries—The entity prepares and communicates information about the design and operation of the system and its boundaries to authorized personnel to enable them to understand their role in the system and the results of system operation.
C53: Communicates System Objectives—The entity communicates its objectives to personnel to enable them to carry out their responsibilities. | D53: PR.AT-1
C54: Communicates System Changes—System changes that affect responsibilities or the achievement of the entity's objectives are communicated in a timely manner.
A55: CC2.3 | B55: COSO Principle 15: The entity communicates with external parties regarding matters affecting the functioning of internal control.
C56: Communicates to External Parties—Processes are in place to communicate relevant and timely information to external parties, including shareholders, partners, owners, regulators, customers, financial analysts, and other external parties. | D56: PR.IP-8
C57: Enables Inbound Communications—Open communication channels allow input from customers, consumers, suppliers, external auditors, regulators, financial analysts, and others, providing management and the board of directors with relevant information.
C58: Communicates With the Board of Directors—Relevant information resulting from assessments conducted by external parties is communicated to the board of directors.
C59: Provides Separate Communication Lines—Separate communication channels, such as whistle-blower hotlines, are in place and serve as fail-safe mechanisms to enable anonymous or confidential communication when normal channels are inoperative or ineffective.
C60: Selects Relevant Method of Communication—The method of communication considers the timing, audience, and nature of the communication and legal, regulatory, and fiduciary requirements and expectations.
C61: Communicates Objectives Related to Confidentiality and Changes to Objectives— The entity communicates, to external users, vendors, business partners and others whose products and services are part of the system, objectives and changes to objectives related to confidentiality.
C62: Communicates Objectives Related to Privacy and Changes to Objectives—The entity communicates, to external users, vendors, business partners and others whose products and services are part of the system, objectives related to privacy and changes to those objectives.
C63: Communicates Information About System Operation and Boundaries—The entity prepares and communicates information about the design and operation of the system and its boundaries to authorized external users to permit users to understand their role in the system and the results of system operation.
C64: Communicates System Objectives—The entity communicates its system objectives to appropriate external users.
C65: Communicates System Responsibilities—External users with responsibility for designing, developing, implementing, operating, maintaining, and monitoring system controls receive communications about their responsibilities and have the information necessary to carry out those responsibilities. | D65: PR.AT-1
D66: PR.AT-3
C67: Communicates Information on Reporting System Failures, Incidents, Concerns, and Other Matters—External users are provided with information on how to report systems failures, incidents, concerns, and other complaints to appropriate personnel. | D67: PR.AT-1
B68: RISK ASSESSMENT
A69: CC3.1 | B69: COSO Principle 6: The entity specifies objectives with sufficient clarity to enable the identification and assessment of risks relating to objectives.
C70: Operations Ojectives
C71: Reflects Management's Choices—Operations objectives reflect management's choices about structure, industry considerations, and performance of the entity. | D71: ID.BE-1
D72: ID.BE-2
D73: ID.BE-3
D74: ID.BE-4
D75: ID.BE-5
C76: Considers Tolerances for Risk—Management considers the acceptable levels of variation relative to the achievement of operations objectives. | D76: ID.RM-2
D77: ID.RM-3
C78: Includes Operations and Financial Performance Goals—The organization reflects the desired level of operations and financial performance for the entity within operations objectives. | D78: ID.GV-4
C79: Forms a Basis for Committing of Resources—Management uses operations objectives as a basis for allocating resources needed to attain desired operations and financial performance. | D79: ID.RM-3
C80: External Financial Reporting Objectives
C81: Complies With Applicable Accounting Standards—Financial reporting objectives are consistent with accounting principles suitable and available for that entity. The accounting principles selected are appropriate in the circumstances.
C82: Considers Materiality—Management considers materiality in financial statement presentation. | D82: ID.RM-2
C83: Reflects Entity Activities—External reporting reflects the underlying transactions and events to show qualitative characteristics and assertions.
C84: External Nonfinancial Reporting Objectives
C85: Complies With Externally Established Frameworks—Management establishes objectives consistent with laws and regulations or standards and frameworks of recognized external organizations.
C86: Considers the Required Level of Precision—Management reflects the required level of precision and accuracy suitable for user needs and based on criteria established by third parties in nonfinancial reporting. | D86: ID.RM-2
C87: Reflects Entity Activities—External reporting reflects the underlying transactions and events within a range of acceptable limits.
C88: Internal Reporting Objectives
C89: Reflects Management's Choices—Internal reporting provides management with accurate and complete information regarding management's choices and information needed in managing the entity.
C90: Considers the Required Level of Precision—Management reflects the required level of precision and accuracy suitable for user needs in nonfinancial reporting objectives and materiality within financial reporting objectives. | D90: ID.RM-2
C91: Reflects Entity Activities—Internal reporting reflects the underlying transactions and events within a range of acceptable limits.
C92: Compliance Objectives
C93: Reflects External Laws and Regulations—Laws and regulations establish minimum standards of conduct, which the entity integrates into compliance objectives. | D93: ID.GV-3
C94: Considers Tolerances for Risk—Management considers the acceptable levels of variation relative to the achievement of operations objectives. | D94: ID.RM-3
C95: Establishes Sub-objectives to Support Objectives—Management identifies sub-objectives related to security, availability, processing integrity, confidentiality, and privacy to support the achievement of the entity’s objectives related to reporting, operations, and compliance. | D95: ID.RM-2
A96: CC3.2 | B96: COSO Principle 7: The entity identifies risks to the achievement of its objectives across the entity and analyzes risks as a basis for determining how the risks should be managed.
C97: Includes Entity, Subsidiary, Division, Operating Unit, and Functional Levels—The entity identifies and assesses risk at the entity, subsidiary, division, operating unit, and functional levels relevant to the achievement of objectives. | D97: ID.RA-1
D98: ID.RA-2
C99: Analyzes Internal and External Factors—Risk identification considers both internal and external factors and their impact on the achievement of objectives. | D99: ID.RA-1
D100: ID.RA-2
...

Sheet NIST CSF
A1: Sort | B1: Function | C1: Function Desc. | D1: Category | E1: Category Desc. | F1: Subcategory | G1: SubCategory Desc. | H1: Ref: CIS | I1: Ref: ISO | J1: Ref: 800-53 R4 | K1: Ref: HIPAA | L1: Ref: HITRUST | M1: Ref: COBIT 5
A2: 1.1.1 | B2: ID | C2: Identify | D2: AM | E2: Asset Management (ID.AM): The data, personnel, devices, systems, and facilities that enable the organization to achieve business purposes are identified and managed consistent with their relative importance to organizational objectives and the organization’s risk strategy. | F2: ID.AM-1 | G2: Physical devices and systems within the organization are inventoried | H2: CIS CSC 1 | I2: A.8.1.1, A.8.1.2 | J2: CM-8, PM-5 | K2: 45 C.F.R. §§ 164.308(a)(1)(ii)(A), 164.310(a)(2)(ii), 164.310(d) | M2: BAI09.01, BAI09.02
A3: 1.1.2 | B3: ID | C3: Identify | D3: AM | E3: Asset Management (ID.AM): The data, personnel, devices, systems, and facilities that enable the organization to achieve business purposes are identified and managed consistent with their relative importance to organizational objectives and the organization’s risk strategy. | F3: ID.AM-2 | G3: Software platforms and applications within the organization are inventoried | H3: CIS CSC 2 | I3: A.8.1.1, A.8.1.2 | J3: CM-8, PM-5 | K3: 45 C.F.R. §§ 164.308(a)(1)(ii)(A), 164.308(a)(7)(ii)(E ) | M3: BAI09.01, BAI09.02, BAI09.05
A4: 1.1.3 | B4: ID | C4: Identify | D4: AM | E4: Asset Management (ID.AM): The data, personnel, devices, systems, and facilities that enable the organization to achieve business purposes are identified and managed consistent with their relative importance to organizational objectives and the organization’s risk strategy. | F4: ID.AM-3 | G4: Organizational communication and data flows are mapped | H4: CIS CSC 12 | I4: A.13.2.1 | J4: AC-4, CA-3, CA-9, PL-8 | K4: 45 C.F.R. §§ 164.308(a)(1)(ii)(A), 164.308(a)(3)(ii)(A), 164.308(a)(8), 164.310(d) | M4: DSS05.02
A5: 1.1.4 | B5: ID | C5: Identify | D5: AM | E5: Asset Management (ID.AM): The data, personnel, devices, systems, and facilities that enable the organization to achieve business purposes are identified and managed consistent with their relative importance to organizational objectives and the organization’s risk strategy. | F5: ID.AM-4 | G5: External information systems are catalogued | H5: CIS CSC 12 | I5: A.11.2.6 | J5: AC-20, SA-9 | K5: 45 C.F.R. §§ 164.308(a)(4)(ii)(A), 164.308(b), 164.314(a)(1), 164.314(a)(2)(i)(B), 164.314(a)(2)(ii), 164.316(b)(2) | M5: APO02.02
A6: 1.1.5 | B6: ID | C6: Identify | D6: AM | E6: Asset Management (ID.AM): The data, personnel, devices, systems, and facilities that enable the organization to achieve business purposes are identified and managed consistent with their relative importance to organizational objectives and the organization’s risk strategy. | F6: ID.AM-5 | G6: Resources (e.g., hardware, devices, data, time, personnel, and software) are prioritized based on their classification, criticality, and business value | H6: CIS CSC 13, 14 | I6: A.8.2.1 | J6: CP-2, RA-2, SA-14, SC-6 | K6: 45 C.F.R. § 164.308(a)(7)(ii)(E ) | M6: APO03.03, APO03.04, BAI09.02
A7: 1.1.6 | B7: ID | C7: Identify | D7: AM | E7: Asset Management (ID.AM): The data, personnel, devices, systems, and facilities that enable the organization to achieve business purposes are identified and managed consistent with their relative importance to organizational objectives and the organization’s risk strategy. | F7: ID.AM-6 | G7: Cybersecurity roles and responsibilities for the entire workforce and third-party stakeholders (e.g., suppliers, customers, partners) are established | H7: CIS CSC 17, 19 | I7: A.6.1.1 | J7: CP-2, PS-7, PM-11 | K7: 45 C.F.R. §§ 164.308(a)(2), 164.308(a)(3), 164.308(a)(4), 164.308(b)(1), 164.314 | M7: APO01.02, DSS06.03
A8: 1.2.1 | B8: ID | C8: Identify | D8: BE | E8: Business Environment (ID.BE): The organization’s mission, objectives, stakeholders, and activities are understood and prioritized; this information is used to inform cybersecurity roles, responsibilities, and risk management decisions. | F8: ID.BE-1 | G8: The organization’s role in the supply chain is identified and communicated | I8: A.15.1.3, A.15.2.1, A.15.2.2 | J8: CP-2, SA-12 | K8: 45 C.F.R. §§ 164.308(a)(1)(ii)(A), 164.308(a)(4)(ii), 164.308(a)(7)(ii)(C), 164.308(a)(7)(ii)(E), 164.308(a)(8), 164.310(a)(2)(i), 164.314, 164.316 | M8: APO08.04, APO08.05, APO10.03, APO10.04, APO10.05
A9: 1.2.2 | B9: ID | C9: Identify | D9: BE | E9: Business Environment (ID.BE): The organization’s mission, objectives, stakeholders, and activities are understood and prioritized; this information is used to inform cybersecurity roles, responsibilities, and risk management decisions. | F9: ID.BE-2 | G9: The organization’s place in critical infrastructure and its industry sector is identified and communicated | J9: PM-8 | K9: 45 C.F.R. §§ 164.308(a)(1)(ii)(A), 164.308(a)(4)(ii), 164.308(a)(7)(ii)(C), 164.308(a)(7)(ii)(E), 164.308(a)(8), 164.310(a)(2)(i), 164.314, 164.316 | M9: APO02.06, APO03.01
A10: 1.2.3 | B10: ID | C10: Identify | D10: BE | E10: Business Environment (ID.BE): The organization’s mission, objectives, stakeholders, and activities are understood and prioritized; this information is used to inform cybersecurity roles, responsibilities, and risk management decisions. | F10: ID.BE-3 | G10: Priorities for organizational mission, objectives, and activities are established and communicated | J10: PM-11, SA-14 | K10: 45 C.F.R. §§ 164.308(a)(7)(ii)(B), 164.308(a)(7)(ii)(C), 164.308(a)(7)(ii)(D),164.308(a)(7)(ii)(E), 164.310(a)(2)(i), 164.316 | M10: APO02.01, APO02.06, APO03.01
A11: 1.2.4 | B11: ID | C11: Identify | D11: BE | E11: Business Environment (ID.BE): The organization’s mission, objectives, stakeholders, and activities are understood and prioritized; this information is used to inform cybersecurity roles, responsibilities, and risk management decisions. | F11: ID.BE-4 | G11: Dependencies and critical functions for delivery of critical services are established | I11: A.11.2.2, A.11.2.3, A.12.1.3 | J11: CP-8, PE-9, PE-11, PM-8, SA-14 | K11: 45 C.F.R. §§ 164.308(a)(7)(i), 164.308.(a)(7)(ii)(E), 164.310(a)(2)(i), 164.312(a)(2)(ii), 164.314(a)(1), 164.314(b)(2)(i)
A12: 1.2.5 | B12: ID | C12: Identify | D12: BE | E12: Business Environment (ID.BE): The organization’s mission, objectives, stakeholders, and activities are understood and prioritized; this information is used to inform cybersecurity roles, responsibilities, and risk management decisions. | F12: ID.BE-5 | G12: Resilience requirements to support delivery of critical services are established for all operating states (e.g. under duress/attack, during recovery, normal operations) | I12: A.11.1.4, A.17.1.1, A.17.1.2, A.17.2.1 | J12: CP-2, CP-11, SA-13, SA-14 | K12: 45 C.F.R. §§ 164.308(a)(1)(ii)(B), 164.308(a)(6)(ii), 164.308(a)(7), 164.308(a)(8), 164.310(a)(2)(i), 164.312(a)(2)(ii), 164.314(b)(2)(i) | M12: DSS04.02
A13: 1.3.1 | B13: ID | C13: Identify | D13: GV | E13: Governance (ID.GV): The policies, procedures, and processes to manage and monitor the organization’s regulatory, legal, risk, environmental, and operational requirements are understood and inform the management of cybersecurity risk. | F13: ID.GV-1 | G13: Organizational cybersecurity policy is established and communicated | H13: CIS CSC 19 | I13: A.5.1.1 | J13: -1 controls from all security control families | K13: 45 C.F.R. §§ 164.308(a)(1)(i), 164.316 | M13: APO01.03, EDM01.01, EDM01.02
A14: 1.3.2 | B14: ID | C14: Identify | D14: GV | E14: Governance (ID.GV): The policies, procedures, and processes to manage and monitor the organization’s regulatory, legal, risk, environmental, and operational requirements are understood and inform the management of cybersecurity risk. | F14: ID.GV-2 | G14: Cybersecurity roles and responsibilities are coordinated and aligned with internal roles and external partners | H14: CIS CSC 19 | I14: A.6.1.1, A.7.2.1 | J14: PS-7, PM-1, PM-2 | K14: 45 C.F.R. §§ 164.308(a)(1)(i), 164.308(a)(2), 164.308(a)(3), 164.308(a)(4), 164.308(b), 164.314 | M14: APO13.12
A15: 1.3.3 | B15: ID | C15: Identify | D15: GV | E15: Governance (ID.GV): The policies, procedures, and processes to manage and monitor the organization’s regulatory, legal, risk, environmental, and operational requirements are understood and inform the management of cybersecurity risk. | F15: ID.GV-3 | G15: Legal and regulatory requirements regarding cybersecurity, including privacy and civil liberties obligations, are understood and managed | H15: CIS CSC 19 | I15: A.18.1 | J15: -1 controls from all security control families | K15: 45 C.F.R. §§ 164.306, 164.308, 164.310, 164.312, 164.314, 164.316 | M15: MEA03.01, MEA03.04
A16: 1.3.4 | B16: ID | C16: Identify | D16: GV | E16: Governance (ID.GV): The policies, procedures, and processes to manage and monitor the organization’s regulatory, legal, risk, environmental, and operational requirements are understood and inform the management of cybersecurity risk. | F16: ID.GV-4 | G16: Governance and risk management processes address cybersecurity risks | J16: SA-2, PM-3, PM-7, PM-9, PM-10, PM-11 | K16: 45 C.F.R. §§ 164.308(a)(1), 164.308(b) | M16: DSS04.02
A17: 1.4.1 | B17: ID | C17: Identify | D17: RA | E17: Risk Assessment (ID.RA): The organization understands the cybersecurity risk to organizational operations (including mission, functions, image, or reputation), organizational assets, and individuals. | F17: ID.RA-1 | G17: Asset vulnerabilities are identified and documented | H17: CIS CSC 4 | I17: A.12.6.1, A.18.2.3 | J17: CA-2, CA-7, CA-8, RA-3, RA-5, SA-5, SA-11, SI-2, SI-4, SI-5 | K17: 45 C.F.R. §§ 164.308(a)(1)(ii)(A), 164.308(a)(7)(ii)(E), 164.308(a)(8), 164.310(a)(1), 164.312(a)(1), 164.316(b)(2)(iii) | M17: APO12.01, APO12.02, APO12.03, APO12.04
A18: 1.4.2 | B18: ID | C18: Identify | D18: RA | E18: Risk Assessment (ID.RA): The organization understands the cybersecurity risk to organizational operations (including mission, functions, image, or reputation), organizational assets, and individuals. | F18: ID.RA-2 | G18: Cyber threat intelligence is received from information sharing forums and sources. | H18: CIS CSC 4 | I18: A.6.1.4 | J18: SI-5, PM-15, PM-16
A19: 1.4.3 | B19: ID | C19: Identify | D19: RA | E19: Risk Assessment (ID.RA): The organization understands the cybersecurity risk to organizational operations (including mission, functions, image, or reputation), organizational assets, and individuals. | F19: ID.RA-3 | G19: Threats, both internal and external, are identified and documented | H19: CIS CSC 4 | J19: RA-3, SI-5, PM-12, PM-16 | K19: 45 C.F.R. §§ 164.308(a)(1)(ii)(A),164.308(a)(1)(ii)(D), 164.308(a)(3), 164.308(a)(4), 164.308(a)(5)(ii)(A),164.310(a)(1), 164.310(a)(2)(iii), 164.312(a)(1), 164.312(c), 164.312(e), 164.314, 164.316 | M19: APO12.01, APO12.02, APO12.03, APO12.04
A20: 1.4.4 | B20: ID | C20: Identify | D20: RA | E20: Risk Assessment (ID.RA): The organization understands the cybersecurity risk to organizational operations (including mission, functions, image, or reputation), organizational assets, and individuals. | F20: ID.RA-4 | G20: Potential business impacts and likelihoods are identified | H20: CIS CSC 4 | J20: RA-2, RA-3, SA-14, PM-9, PM-11 | K20: 45 C.F.R. §§ 164.308(a)(1)(i), 164.308(a)(1)(ii)(A), 164.308(a)(1)(ii)(B), 164.308(a)(6), 164.308(a)(7)(ii)(E), 164.308(a)(8), 164.316(a) | M20: DSS04.02
A21: 1.4.5 | B21: ID | C21: Identify | D21: RA | E21: Risk Assessment (ID.RA): The organization understands the cybersecurity risk to organizational operations (including mission, functions, image, or reputation), organizational assets, and individuals. | F21: ID.RA-5 | G21: Threats, vulnerabilities, likelihoods, and impacts are used to determine risk | H21: CIS CSC 4 | I21: A.12.6.1 | J21: RA-2, RA-3, PM-16 | K21: 45 C.F.R. §§ 164.308(a)(1)(ii)(A), 164.308(a)(1)(ii)(B), 164.308(a)(1)(ii)(D), 164.308(a)(7)(ii)(D), 164.308(a)(7)(ii)(E), 164.316(a) | M21: APO12.02
A22: 1.4.6 | B22: ID | C22: Identify | D22: RA | E22: Risk Assessment (ID.RA): The organization understands the cybersecurity risk to organizational operations (including mission, functions, image, or reputation), organizational assets, and individuals. | F22: ID.RA-6 | G22: Risk responses are identified and prioritized | H22: CIS CSC 4 | J22: PM-4, PM-9 | K22: 45 C.F.R. §§ 164.308(a)(1)(ii)(B), 164.314(a)(2)(i)(C), 164.314(b)(2)(iv) | M22: APO12.05, APO13.02
A23: 1.5.1 | B23: ID | C23: Identify | D23: RM | E23: Risk Management Strategy (ID.RM): The organization’s priorities, constraints, risk tolerances, and assumptions are established and used to support operational risk decisions. | F23: ID.RM-1 | G23: Risk management processes are established, managed, and agreed to by organizational stakeholders | H23: CIS CSC 4 | J23: PM-9 | K23: 45 C.F.R. § 164.308(a)(1)(ii)(B) | M23: APO12.04, APO12.05, APO13.02, BAI02.03, BAI04.02
A24: 1.5.2 | B24: ID | C24: Identify | D24: RM | E24: Risk Management Strategy (ID.RM): The organization’s priorities, constraints, risk tolerances, and assumptions are established and used to support operational risk decisions. | F24: ID.RM-2 | G24: Organizational risk tolerance is determined and clearly expressed | J24: PM-9 | K24: 45 C.F.R. § 164.308(a)(1)(ii)(B) | M24: APO12.06
A25: 1.5.3 | B25: ID | C25: Identify | D25: RM | E25: Risk Management Strategy (ID.RM): The organization’s priorities, constraints, risk tolerances, and assumptions are established and used to support operational risk decisions. | F25: ID.RM-3 | G25: The organization’s determination of risk tolerance is informed by its role in critical infrastructure and sector specific risk analysis | J25: SA-14, PM-8, PM-9, PM-11 | K25: 45 C.F.R. §§ 164.308(a)(1)(ii)(B), 164.308(a)(6)(ii), 164.308(a)(7)(i), 164.308(a)(7)(ii)(C),164.308(a)(7)(ii)(E), 164.310(a)(2)(i)
A26: 1.6.1 | B26: ID | C26: Identify | D26: SC | E26: Supply Chain Risk Management (ID.SC): The organization’s priorities, constraints, risk tolerances, and assumptions are established and used to support risk decisions associated with managing supply chain risk. The organization has established and implemented the processes to identify, assess and manage supply chain risks. | F26: ID.SC-1 | G26: Cyber supply chain risk management processes are identified, established, assessed, managed, and agreed to by organizational stakeholders | H26: CIS CSC 4 | I26: A.9.2.1, A.9.2.2, A.9.2.4, A.9.3.1, A.9.4.2, A.9.4.3 | J26: SA-9, SA-12, PM-9 | M26: DSS05.04, DSS06.03
A27: 1.6.2 | B27: ID | C27: Identify | D27: SC | E27: Supply Chain Risk Management (ID.SC): The organization’s priorities, constraints, risk tolerances, and assumptions are established and used to support risk decisions associated with managing supply chain risk. The organization has established and implemented the processes to identify, assess and manage supply chain risks. | F27: ID.SC-2 | G27: Suppliers and third party partners of information systems, components, and services are identified, prioritized, and assessed using a cyber supply chain risk assessment process | I27: A.11.1.1, A.11.1.2, A.11.1.4, A.11.1.6, A.11.2.3 | J27: RA-2, RA-3, SA-12, SA-14, SA-15, PM-9 | M27: DSS01.04, DSS05.05
A28: 1.6.3 | B28: ID | C28: Identify | D28: SC | E28: Supply Chain Risk Management (ID.SC): The organization’s priorities, constraints, risk tolerances, and assumptions are established and used to support risk decisions associated with managing supply chain risk. The organization has established and implemented the processes to identify, assess and manage supply chain risks. | F28: ID.SC-3 | G28: Contracts with suppliers and third-party partners are used to implement appropriate measures designed to meet the objectives of an organization’s cybersecurity program and Cyber Supply Chain Risk Management Plan. | I28: A.6.2.2, A.13.1.1, A.13.2.1 | J28: SA-9, SA-11, SA-12, PM-9 | M28: APO13.01, DSS01.04, DSS05.03
A29: 1.6.4 | B29: ID | C29: Identify | D29: SC | E29: Supply Chain Risk Management (ID.SC): The organization’s priorities, constraints, risk tolerances, and assumptions are established and used to support risk decisions associated with managing supply chain risk. The organization has established and implemented the processes to identify, assess and manage supply chain risks. | F29: ID.SC-4 | G29: Suppliers and third-party partners are routinely assessed using audits, test results, or other forms of evaluations to confirm they are meeting their contractual obligations. | I29: A.6.1.2, A.9.1.2, A.9.2.3, A.9.4.1, A.9.4.4 | J29: AU-2, AU-6, AU-12, AU-16, PS-7, SA-9, SA-12
A30: 1.6.5 | B30: ID | C30: Identify | D30: SC | E30: Supply Chain Risk Management (ID.SC): The organization’s priorities, constraints, risk tolerances, and assumptions are established and used to support risk decisions associated with managing supply chain risk. The organization has established and implemented the processes to identify, assess and manage supply chain risks. | F30: ID.SC-5 | G30: Response and recovery planning and testing are conducted with suppliers and third-party providers | H30: CIS CSC 19, 20 | I30: A.13.1.1, A.13.1.3, A.13.2.1 | J30: CP-2, CP-4, IR-3, IR-4, IR-6, IR-8, IR-9
A31: 2.1.1 | B31: PR | C31: Protect | D31: AC | E31: Identity Management, Authentication and Access Control (PR.AC): Access to physical and logical assets and associated facilities is limited to authorized users, processes, and devices, and is managed consistent with the assessed risk of unauthorized access to authorized activities and transactions. | F31: PR.AC-1 | G31: Identities and credentials are issued, managed, verified, revoked, and audited for authorized devices, users and processes | H31: CIS CSC 1, 5, 15, 16 | I31: A.7.2.2 | J31: AC-1, AC-2, IA-1, IA-2, IA-3, IA-4, IA-5, IA-6, IA-7, IA-8, IA-9, IA-10, IA-11 | K31: 45 C.F.R. §§ 164.308(a)(3)(ii)(B), 164.308(a)(3)(ii)(C), 164.308(a)(4)(i), 164.308(a)(4)(ii)(B), 164.308(a)(4)(ii)(C ), 164.312(a)(2)(i), 164.312(a)(2)(ii),164.312(a)(2)(iii), 164.312(d) | M31: APO07.03, BAI05.07
A32: 2.1.2 | B32: PR | C32: Protect | D32: AC | E32: Identity Management, Authentication and Access Control (PR.AC): Access to physical and logical assets and associated facilities is limited to authorized users, processes, and devices, and is managed consistent with the assessed risk of unauthorized access to authorized activities and transactions. | F32: PR.AC-2 | G32: Physical access to assets is managed and protected | I32: A.6.1.1, A.7.2.2 | J32: PE-2, PE-3, PE-4, PE-5, PE-6, PE-8 | K32: 45 C.F.R. §§ 164.308(a)(1)(ii)(B), 164.308(a)(7)(i), 164.308(a)(7)(ii)(A), 164.310(a)(1), 164.310(a)(2)(i), 164.310(a)(2)(ii), 164.310(a)(2)(iii), 164.310(b), 164.310(c), 164.310(d)(1), 164.310(d)(2)(iii) | M32: APO07.02, DSS06.03
A33: 2.1.3 | B33: PR | C33: Protect | D33: AC | E33: Identity Management, Authentication and Access Control (PR.AC): Access to physical and logical assets and associated facilities is limited to authorized users, processes, and devices, and is managed consistent with the assessed risk of unauthorized access to authorized activities and transactions. | F33: PR.AC-3 | G33: Remote access is managed | H33: CIS CSC 12 | I33: A.6.1.1, A.7.2.2 | J33: AC-1, AC-17, AC-19, AC-20, SC-15 | K33: 45 C.F.R. §§ 164.308(a)(4)(i), 164.308(b)(1), 164.308(b)(3), 164.310(b), 164.312(e)(1), 164.312(e)(2)(ii) | M33: APO07.03, APO10.04, APO10.05
A34: 2.1.4 | B34: PR | C34: Protect | D34: AC | E34: Identity Management, Authentication and Access Control (PR.AC): Access to physical and logical assets and associated facilities is limited to authorized users, processes, and devices, and is managed consistent with the assessed risk of unauthorized access to authorized activities and transactions. | F34: PR.AC-4 | G34: Access permissions and authorizations are managed, incorporating the principles of least privilege and separation of duties | H34: CIS CSC 3, 5, 12, 14, 15, 16, 18 | I34: A.6.1.1, A.7.2.2, | J34: AC-1, AC-2, AC-3, AC-5, AC-6, AC-14, AC-16, AC-24 | K34: 45 C.F.R. §§ 164.308(a)(3), 164.308(a)(4), 164.310(a)(2)(iii), 164.310(b), 164.312(a)(1), 164.312(a)(2)(i), 164.312(a)(2)(ii) | M34: APO07.03
A35: 2.1.5 | B35: PR | C35: Protect | D35: AC | E35: Identity Management, Authentication and Access Control (PR.AC): Access to physical and logical assets and associated facilities is limited to authorized users, processes, and devices, and is managed consistent with the assessed risk of unauthorized access to authorized activities and transactions. | F35: PR.AC-5 | G35: Network integrity is protected (e.g., network segregation, network segmentation) | H35: CIS CSC 9, 14, 15, 18 | I35: A.6.1.1, A.7.2.2, | J35: AC-4, AC-10, SC-7 | K35: 45 C.F.R. §§ 164.308(a)(4)(ii)(B), 164.310(a)(1), 164.310(b), 164.312(a)(1), 164.312(b), 164.312(c), 164.312(e) | M35: APO07.03
A36: 2.1.6 | B36: PR | C36: Protect | D36: AC | E36: Identity Management, Authentication and Access Control (PR.AC): Access to physical and logical assets and associated facilities is limited to authorized users, processes, and devices, and is managed consistent with the assessed risk of unauthorized access to authorized activities and transactions. | F36: PR.AC-6 | G36: Identities are proofed and bound to credentials and asserted in interactions | H36: CIS CSC, 16 | I36: A.8.2.3 | J36: AC-1, AC-2, AC-3, AC-16, AC-19, AC-24, IA-1, IA-2, IA-4, IA-5, IA-8, PE-2, PS-3 | M36: APO01.06, BAI02.01, BAI06.01, DSS06.06
A37: 2.1.7 | B37: PR | C37: Protect | D37: AC | E37: Identity Management, Authentication and Access Control (PR.AC): Access to physical and logical assets and associated facilities is limited to authorized users, processes, and devices, and is managed consistent with the assessed risk of unauthorized access to authorized activities and transactions. | F37: PR.AC-7 | G37: Users, devices, and other assets are authenticated (e.g., single-factor, multi-factor) commensurate with the risk of the transaction (e.g., individuals’ security and privacy risks and other organizational risks) | H37: CIS CSC 1, 12, 15, 16 | I37: A.8.2.3, A.13.1.1, A.13.2.1, A.13.2.3, A.14.1.2, A.14.1.3 | J37: AC-7, AC-8, AC-9, AC-11, AC-12, AC-14, IA-1, IA-2, IA-3, IA-4, IA-5, IA-8, IA-9, IA-10, IA-11 | M37: APO01.06, DSS06.06
A38: 2.2.1 | B38: PR | C38: Protect | D38: AT | E38: The organization’s personnel and partners are provided cybersecurity awareness education and are trained to perform their cybersecurity-related duties and responsibilities consistent with related policies, procedures, and agreements | F38: PR.AT-1 | G38: All users are informed and trained | H38: CIS CSC 17, 18 | I38: A.8.2.3, A.8.3.1, A.8.3.2, A.8.3.3, A.11.2.7 | J38: AT-2, PM-13 | K38: 45 C.F.R. § 164.308(a)(5) | M38: BAI09.03
A39: 2.2.2 | B39: PR | C39: Protect | D39: AT | E39: The organization’s personnel and partners are provided cybersecurity awareness education and are trained to perform their cybersecurity-related duties and responsibilities consistent with related policies, procedures, and agreements | F39: PR.AT-2 | G39: Privileged users understand their roles and responsibilities | H39: CIS CSC 5, 17, 18 | I39: A.12.3.1 | J39: AT-3, PM-13 | K39: 5 C.F.R. §§ 164.308(a)(2), 164.308(a)(3)(i), 164.308(a)(5)(i), 164.308(a)(5)(ii)(A), 164.308(a)(5)(ii)(B), 164.308(a)(5)(ii)(C), 164.308(a)(5)(ii)(D) | M39: APO13.01
A40: 2.2.3 | B40: PR | C40: Protect | D40: AT | E40: The organization’s personnel and partners are provided cybersecurity awareness education and are trained to perform their cybersecurity-related duties and responsibilities consistent with related policies, procedures, and agreements | F40: PR.AT-3 | G40: Third-party stakeholders (e.g., suppliers, customers, partners) understand their roles and responsibilities | H40: CIS CSC 17 | I40: A.6.1.2, A.7.1.1, A.7.1.2, A.7.3.1, A.8.2.2, A.8.2.3, A.9.1.1, A.9.1.2, A.9.2.3, A.9.4.1, A.9.4.4, A.9.4.5, A.13.1.3, A.13.2.1, A.13.2.3, A.13.2.4, A.14.1.2, A.14.1.3 | J40: PS-7, SA-9, SA-16 | K40: 45 C.F.R. §§ 164.308(b), 164.314(a)(1), 164.314(a)(2)(i), 164.314(a)(2)(ii) | M40: APO01.06
A41: 2.2.4 | B41: PR | C41: Protect | D41: AT | E41: The organization’s personnel and partners are provided cybersecurity awareness education and are trained to perform their cybersecurity-related duties and responsibilities consistent with related policies, procedures, and agreements | F41: PR.AT-4 | G41: Senior executives understand their roles and responsibilities | H41: CIS CSC 17, 19 | I41: A.12.2.1, A.12.5.1, A.14.1.2, A.14.1.3 | J41: AT-3, PM-13 | K41: 45 C.F.R. §§ 164.308(a)(2), 164.308(a)(3)(i), 164.308(a)(5)(i), 164.308(a)(5)(ii)(A),164.308(a)(5)(ii)(B), 164.308(a)(5)(ii)(C), 164.308(a)(5)(ii)(D)
A42: 2.2.5 | B42: PR | C42: Protect | D42: AT | E42: The organization’s personnel and partners are provided cybersecurity awareness education and are trained to perform their cybersecurity-related duties and responsibilities consistent with related policies, procedures, and agreements | F42: PR.AT-5 | G42: Physical and cybersecurity personnel understand their roles and responsibilities | H42: CIS CSC 17 | I42: A.12.1.4 | J42: AT-3, IR-2, PM-13 | K42: 45 C.F.R. §§ 164.308(a)(2), 164.308(a)(3)(i), 164.308(a)(5)(i), 164.308(a)(5)(ii)(A), 164.308(a)(5)(ii)(B), 164.308(a)(5)(ii)(C), 164.308(a)(5)(ii)(D), 164.530(b)(1) | M42: BAI07.04
A43: 2.3.1 | B43: PR | C43: Protect | D43: DS | E43: Information and records (data) are managed consistent with the organization’s risk strategy to protect the confidentiality, integrity, and availability of information. | F43: PR.DS-1 | G43: Data-at-rest is protected | H43: CIS CSC 13, 14 | I43: A.12.1.2, A.12.5.1, A.12.6.2, A.14.2.2, A.14.2.3, A.14.2.4 | J43: MP-8, SC-12, SC-28 | K43: 45 C.F.R. §§ 164.308(a)(1)(ii)(D), 164.308(b)(1), 164.310(d), 164.312(a)(1), 164.312(a)(2)(iii), 164.312(a)(2)(iv), 164.312(b), 164.312(c), 164.314(b)(2)(i), 164.312(d) | M43: BAI10.01, BAI10.02, BAI10.03, BAI10.05
A44: 2.3.2 | B44: PR | C44: Protect | D44: DS | E44: Information and records (data) are managed consistent with the organization’s risk strategy to protect the confidentiality, integrity, and availability of information. | F44: PR.DS-2 | G44: Data-in-transit is protected | H44: CIS CSC 13, 14 | I44: A.6.1.5, A.14.1.1, A.14.2.1, A.14.2.5 | J44: SC-8, SC-11, SC-12 | K44: 45 C.F.R. §§ 164.308(b)(1), 164.308(b)(2), 164.312(e)(1), 164.312(e)(2)(i), 164.312(e)(2)(ii), 164.314(b)(2)(i) | M44: APO13.01
A45: 2.3.3 | B45: PR | C45: Protect | D45: DS | E45: Information and records (data) are managed consistent with the organization’s risk strategy to protect the confidentiality, integrity, and availability of information. | F45: PR.DS-3 | G45: Assets are formally managed throughout removal, transfers, and disposition | H45: CIS CSC 1 | I45: A.12.1.2, A.12.5.1, A.12.6.2, A.14.2.2, A.14.2.3, A.14.2.4 | J45: CM-8, MP-6, PE-16 | K45: 45 C.F.R. §§ 164.308(a)(1)(ii)(A), 164.310(a)(2)(ii), 164.310(a)(2)(iii), 164.310(a)(2)(iv), 164.310(d)(1), 164.310(d)(2) | M45: BAI06.01, BAI01.06
A46: 2.3.4 | B46: PR | C46: Protect | D46: DS | E46: Information and records (data) are managed consistent with the organization’s risk strategy to protect the confidentiality, integrity, and availability of information. | F46: PR.DS-4 | G46: Adequate capacity to ensure availability is maintained | H46: CIS CSC 1, 2, 13 | I46: A.12.3.1, A.17.1.2A.17.1.3, A.18.1.3 | J46: AU-4, CP-2, SC-5 | K46: 45 C.F.R. §§ 164.308(a)(1)(ii)(A), 164.308(a)(1)(ii)(B), 164.308(a)(7), 164.310(a)(2)(i), 164.310(d)(2)(iv), 164.312(a)(2)(ii) | M46: APO13.01
A47: 2.3.5 | B47: PR | C47: Protect | D47: DS | E47: Information and records (data) are managed consistent with the organization’s risk strategy to protect the confidentiality, integrity, and availability of information. | F47: PR.DS-5 | G47: Protections against data leaks are implemented | H47: CIS CSC 13 | I47: A.11.1.4, A.11.2.1, A.11.2.2, A.11.2.3 | J47: AC-4, AC-5, AC-6, PE-19, PS-3, PS-6, SC-7, SC-8, SC-13, SC-31, SI-4 | K47: 45 C.F.R. §§ 164.308(a)(1)(ii)(D), 164.308(a)(3), 164.308(a)(4), 164.310(b), 164.310(c), 164.312(a), 164.312(e) | M47: DSS01.04, DSS05.05
A48: 2.3.6 | B48: PR | C48: Protect | D48: DS | E48: Information and records (data) are managed consistent with the organization’s risk strategy to protect the confidentiality, integrity, and availability of information. | F48: PR.DS-6 | G48: Integrity checking mechanisms are used to verify software, firmware, and information integrity | H48: CIS CSC 2, 3 | I48: A.8.2.3, A.8.3.1, A.8.3.2, A.11.2.7 | J48: SC-16, SI-7 | K48: 45 C.F.R. §§ 164.308(a)(1)(ii)(D), 164.312(b), 164.312(c)(1), 164.312(c)(2), 164.312(e)(2)(i) | M48: BAI09.03
A49: 2.3.7 | B49: PR | C49: Protect | D49: DS | E49: Information and records (data) are managed consistent with the organization’s risk strategy to protect the confidentiality, integrity, and availability of information. | F49: PR.DS-7 | G49: The development and testing environment(s) are separate from the production environment | H49: CIS CSC 18, 20 | J49: CM-2 | K49: 45 C.F.R. § 164.308(a)(4)4 | M49: APO11.06, DSS04.05
A50: 2.3.8 | B50: PR | C50: Protect | D50: DS | E50: Information and records (data) are managed consistent with the organization’s risk strategy to protect the confidentiality, integrity, and availability of information. | F50: PR.DS-8 | G50: Integrity checking mechanisms are used to verify hardware integrity | I50: A.16.1.6 | J50: SA-10, SI-7
A51: 2.4.01 | B51: PR | C51: Protect | D51: IP | E51: Security policies (that address purpose, scope, roles, responsibilities, management commitment, and coordination among organizational entities), processes, and procedures are maintained and used to manage protection of information systems and assets. | F51: PR.IP-1 | G51: A baseline configuration of information technology/industrial control systems is created and maintained incorporating security principles (e.g. concept of least functionality) | H51: CIS CSC 3, 9, 11 | I51: A.16.1.1, A.17.1.1, A.17.1.2 | J51: CM-2, CM-3, CM-4, CM-5, CM-6, CM-7, CM-9, SA-10 | K51: 45 C.F.R. §§ 164.308(a)(8), 164.308(a)(7)(i), 164.308(a)(7)(ii) | M51: DSS04.03
A52: 2.4.02 | B52: PR | C52: Protect | D52: IP | E52: Security policies (that address purpose, scope, roles, responsibilities, management commitment, and coordination among organizational entities), processes, and procedures are maintained and used to manage protection of information systems and assets. | F52: PR.IP-2 | G52: A System Development Life Cycle to manage systems is implemented | H52: CIS CSC 18 | I52: A.17.1.3 | J52: PL-8, SA-3, SA-4, SA-8, SA-10, SA-11, SA-12, SA-15, SA-17, SI-12, SI-13, SI-14, SI-16, SI-17 | K52: 45 C.F.R. § 164.308(a)(1)(i)
A53: 2.4.03 | B53: PR | C53: Protect | D53: IP | E53: Security policies (that address purpose, scope, roles, responsibilities, management commitment, and coordination among organizational entities), processes, and procedures are maintained and used to manage protection of information systems and assets. | F53: PR.IP-3 | G53: Configuration change control processes are in place | H53: CIS CSC 3, 11 | I53: A.7.1.1, A.7.3.1, A.8.1.4 | J53: CM-3, CM-4, SA-10 | K53: 45 C.F.R. § 164.308(a)(8) | M53: APO07.01, APO07.02, APO07.03, APO07.04, APO07.05
A54: 2.4.04 | B54: PR | C54: Protect | D54: IP | E54: Security policies (that address purpose, scope, roles, responsibilities, management commitment, and coordination among organizational entities), processes, and procedures are maintained and used to manage protection of information systems and assets. | F54: PR.IP-4 | G54: Backups of information are conducted, maintained, and tested | H54: CIS CSC 10 | I54: A.12.6.1, A.18.2.2 | J54: CP-4, CP-6, CP-9 | K54: 45 C.F.R. §§ 164.308(a)(7)(ii)(A), 164.308(a)(7)(ii)(B), 164.308(a)(7)(ii)(D), 164.310(a)(2)(i), 164.310(d)(2)(iv)
A55: 2.4.05 | B55: PR | C55: Protect | D55: IP | E55: Security policies (that address purpose, scope, roles, responsibilities, management commitment, and coordination among organizational entities), processes, and procedures are maintained and used to manage protection of information systems and assets. | F55: PR.IP-5 | G55: Policy and regulations regarding the physical operating environment for organizational assets are met | I55: A.11.1.2, A.11.2.4, A.11.2.5 | J55: PE-10, PE-12, PE-13, PE-14, PE-15, PE-18 | K55: 45 C.F.R. §§ 164.308(a)(7)(i), 164.308(a)(7)(ii)(C), 164.310, 164.316(b)(2)(iii) | M55: BAI09.03
A56: 2.4.06 | B56: PR | C56: Protect | D56: IP | E56: Security policies (that address purpose, scope, roles, responsibilities, management commitment, and coordination among organizational entities), processes, and procedures are maintained and used to manage protection of information systems and assets. | F56: PR.IP-6 | G56: Data is destroyed according to policy | I56: A.11.2.4, A.15.1.1, A.15.2.1 | J56: MP-6 | K56: 45 C.F.R. §§ 164.310(d)(2)(i), 164.310(d)(2)(ii) | M56: DSS05.04
A57: 2.4.07 | B57: PR | C57: Protect | D57: IP | E57: Security policies (that address purpose, scope, roles, responsibilities, management commitment, and coordination among organizational entities), processes, and procedures are maintained and used to manage protection of information systems and assets. | F57: PR.IP-7 | G57: Protection processes are improved | I57: A.12.4.1, A.12.4.2, A.12.4.3, A.12.4.4, A.12.7.1 | J57: CA-2, CA-7, CP-2, IR-8, PL-2, PM-6 | K57: 45 C.F.R. §§ 164.306(e), 164.308(a)(7)(ii)(D), 164.308(a)(8), 164.316(b)(2)(iii) | M57: APO11.04
A58: 2.4.08 | B58: PR | C58: Protect | D58: IP | E58: Security policies (that address purpose, scope, roles, responsibilities, management commitment, and coordination among organizational entities), processes, and procedures are maintained and used to manage protection of information systems and assets. | F58: PR.IP-8 | G58: Effectiveness of protection technologies is shared | I58: A.8.2.2, A.8.2.3, A.8.3.1, A.8.3.3, A.11.2.9 | J58: AC-21, CA-7, SI-4 | K58: 45 C.F.R. § 164.308(a)(6)(ii) | M58: DSS05.02, APO13.01
A59: 2.4.09 | B59: PR | C59: Protect | D59: IP | E59: Security policies (that address purpose, scope, roles, responsibilities, management commitment, and coordination among organizational entities), processes, and procedures are maintained and used to manage protection of information systems and assets. | F59: PR.IP-9 | G59: Response plans (Incident Response and Business Continuity) and recovery plans (Incident Recovery and Disaster Recovery) are in place and managed | H59: CIS CSC 19 | I59: A.9.1.2 | J59: CP-2, CP-7, CP-12, CP-13, IR-7, IR-8, IR-9, PE-17 | K59: 45 C.F.R. §§ 164.308(a)(6), 164.308(a)(7), 164.310(a)(2)(i), 164.312(a)(2)(ii) | M59: DSS05.02
A60: 2.4.10 | B60: PR | C60: Protect | D60: IP | E60: Security policies (that address purpose, scope, roles, responsibilities, management commitment, and coordination among organizational entities), processes, and procedures are maintained and used to manage protection of information systems and assets. | F60: PR.IP-10 | G60: Response and recovery plans are tested | H60: CIS CSC 19, 20 | I60: A.13.1.1, A.13.2.1 | J60: CP-4, IR-3, PM-14 | K60: 45 C.F.R. § 164.308(a)(7)(ii)(D) | M60: DSS05.02, APO13.01
A61: 2.4.11 | B61: PR | C61: Protect | D61: IP | E61: Security policies (that address purpose, scope, roles, responsibilities, management commitment, and coordination among organizational entities), processes, and procedures are maintained and used to manage protection of information systems and assets. | F61: PR.IP-11 | G61: Cybersecurity is included in human resources practices (e.g., deprovisioning, personnel screening) | H61: CIS CSC 5, 16 | J61: PS-1, PS-2, PS-3, PS-4, PS-5, PS-6, PS-7, PS-8, SA-21 | K61: 45 C.F.R. §§ 164.308(a)(1)(ii)(C), 164.308(a)(3) | M61: DSS03.01
A62: 2.4.12 | B62: PR | C62: Protect | D62: IP | E62: Security policies (that address purpose, scope, roles, responsibilities, management commitment, and coordination among organizational entities), processes, and procedures are maintained and used to manage protection of information systems and assets. | F62: PR.IP-12 | G62: A vulnerability management plan is developed and implemented | H62: CIS CSC 4, 18, 20 | I62: A.16.1.1, A.16.1.4 | J62: RA-3, RA-5, SI-2 | K62: 45 C.F.R. §§ 164.308(a)(1)(i), 164.308(a)(1)(ii)(A), 164.308(a)(1)(ii)(B)
A63: 2.5.1 | B63: PR | C63: Protect | D63: MA | E63: Maintenance and repairs of industrial control and information system components areperformed consistent with policies and procedures. | F63: PR.MA-1 | G63: Maintenance and repair of organizational assets are performed and logged, with approved and controlled tools | J63: MA-2, MA-3, MA-5, MA-6 | K63: 45 C.F.R. §§ 164.308(a)(3)(ii)(A), 164.310(a)(2)(iv)
A64: 2.5.2 | B64: PR | C64: Protect | D64: MA | E64: Maintenance and repairs of industrial control and information system components areperformed consistent with policies and procedures. | F64: PR.MA-2 | G64: Remote maintenance of organizational assets is approved, logged, and performed in a manner that prevents unauthorized access | H64: CIS CSC 3, 5 | J64: MA-4 | K64: 45 C.F.R. §§ 164.308(a)(3)(ii)(A), 164.310(d)(1),164.310(d)(2)(ii), 164.310(d)(2)(iii), 164.312(a), 164.312(a)(2)(ii), 164.312(a)(2)(iv), 164.312(b), 164.312(d), 164.312(e), 164.308(a)(1)(ii)(D) | M64: APO12.06
A65: 2.6.1 | B65: PR | C65: Protect | D65: PT | E65: Technical security solutions are managed to ensure the security and resilience of systems and assets, consistent with related policies, procedures, and agreements. | F65: PR.PT-1 | G65: Audit/log records are determined, documented, implemented, and reviewed in accordance with policy | H65: CIS CSC 1, 3, 5, 6, 14, 15, 16 | J65: AU Family | K65: 45 C.F.R. §§ 164.308(a)(1)(ii)(D), 164.308(a)(5)(ii)(C), 164.310(a)(2)(iv), 164.310(d)(2)(iii), 164.312(b) | M65: APO12.06
A66: 2.6.2 | B66: PR | C66: Protect | D66: PT | E66: Technical security solutions are managed to ensure the security and resilience of systems and assets, consistent with related policies, procedures, and agreements. | F66: PR.PT-2 | G66: Removable media is protected and its use restricted according to policy | H66: CIS CSC 8, 13 | J66: MP-2, MP-3, MP-4, MP-5, MP-7, MP-8 | K66: 45 C.F.R. §§ 164.308(a)(3)(i), 164.308(a)(3)(ii)(A), 164.310(d)(1), 164.310(d)(2), 164.312(a)(1), 164.312(a)(2)(iv), 164.312(b) | M66: DSS05.07
A67: 2.6.3 | B67: PR | C67: Protect | D67: PT | E67: Technical security solutions are managed to ensure the security and resilience of systems and assets, consistent with related policies, procedures, and agreements. | F67: PR.PT-3 | G67: The principle of least functionality is incorporated by configuring systems to provide only essential capabilities | H67: CIS CSC 3, 11, 14 | J67: AC-3, CM-7 | K67: 45 C.F.R. §§ 164.308(a)(3), 164.308(a)(4), 164.310(a)(2)(iii), 164.310(b), 164.310(c), 164.312(a)(1), 164.312(a)(2)(i), 164.312(a)(2)(ii), 164.312(a)(2)(iv)
A68: 2.6.4 | B68: PR | C68: Protect | D68: PT | E68: Technical security solutions are managed to ensure the security and resilience of systems and assets, consistent with related policies, procedures, and agreements. | F68: PR.PT-4 | G68: Communications and control networks are protected | H68: CIS CSC 8, 12, 15 | I68: A.12.4.1 | J68: AC-4, AC-17, AC-18, CP-8, SC-7, SC-19, SC-20, SC-21, SC-22, SC-23, SC-24, SC-25, SC-29, SC-32, SC-36, SC-37, SC-38, SC-39, SC-40, SC-41, SC-43 | K68: 45 C.F.R. §§ 164.308(a)(1)(ii)(D), 164.312(a)(1), 164.312(b), 164.312(e)
A69: 2.6.5 | B69: PR | C69: Protect | D69: PT | E69: Technical security solutions are managed to ensure the security and resilience of systems and assets, consistent with related policies, procedures, and agreements. | F69: PR.PT-5 | G69: Mechanisms (e.g., failsafe, load balancing, hot swap) are implemented to achieve resilience requirements in normal and adverse situations | I69: A.12.2.1 | J69: CP-7, CP-8, CP-11, CP-13, PL-8, SA-14, SC-6 | M69: DSS05.01
A70: 3.1.1 | B70: DE | C70: Detect | D70: AE | E70: Anomalies and Events (DE.AE): Anomalous activity is detected and the potential impact of events is understood. | F70: DE.AE-1 | G70: A baseline of network operations and expected data flows for users and systems is established and managed | H70: CIS CSC 1, 4, 6, 12, 13, 15, 16 | I70: A.12.5.1 | J70: AC-4, CA-3, CM-2, SI-4 | K70: 45 C.F.R. §§164.308(a)(1)(ii)(D), 164.312(b)
A71: 3.1.2 | B71: DE | C71: Detect | D71: AE | E71: Anomalies and Events (DE.AE): Anomalous activity is detected and the potential impact of events is understood. | F71: DE.AE-2 | G71: Detected events are analyzed to understand attack targets and methods | H71: CIS CSC 3, 6, 13, 15 | I71: A.14.2.7, A.15.2.1 | J71: AU-6, CA-7, IR-4, SI-4 | K71: 45 C.F.R. §164.308(6)(i) | M71: APO07.06
A72: 3.1.3 | B72: DE | C72: Detect | D72: AE | E72: Anomalies and Events (DE.AE): Anomalous activity is detected and the potential impact of events is understood. | F72: DE.AE-3 | G72: Event data are collected and correlated from multiple sources and sensors | H72: CIS CSC 1, 3, 4, 5, 6, 7, 8, 11, 12, 13, 14, 15, 16 | J72: AU-6, CA-7, IR-4, IR-5, IR-8, SI-4 | K72: 45 C.F.R. §§ 164.308(a)(1)(ii)(D), 164.308(a)(5)(ii)(B), 164.308(a)(5)(ii)(C), 164.308(a)(6)(ii), 164.308(a)(8), 164.310(d)(2)(iii), 164.312(b), 164.314(a)(2)(i)(C), 164.314(a)(2)(iii)
A73: 3.1.4 | B73: DE | C73: Detect | D73: AE | E73: Anomalies and Events (DE.AE): Anomalous activity is detected and the potential impact of events is understood. | F73: DE.AE-4 | G73: Impact of events is determined | H73: CIS CSC 4, 6 | I73: A.12.6.1 | J73: CP-2, IR-4, RA-3, SI-4 | K73: 45 C.F.R. § 164.308(a)(6)(ii) | M73: BAI03.10
A74: 3.1.5 | B74: DE | C74: Detect | D74: AE | E74: Anomalies and Events (DE.AE): Anomalous activity is detected and the potential impact of events is understood. | F74: DE.AE-5 | G74: Incident alert thresholds are established | H74: CIS CSC 6, 19 | I74: A.6.1.1 | J74: IR-4, IR-5, IR-8 | K74: 45 C.F.R. § 164.308(a)(6)(i) | M74: DSS05.01
A75: 3.2.1 | B75: DE | C75: Detect | D75: CM | E75: Security Continuous Monitoring (DE.CM): The information system and assets are monitored to identify cybersecurity events and verify the effectiveness of protective measures. | F75: DE.CM-1 | G75: The network is monitored to detect potential cybersecurity events | H75: CIS CSC 1, 7, 8, 12, 13, 15, 16 | I75: A.18.1.4 | J75: AC-2, AU-12, CA-7, CM-3, SC-5, SC-7, SI-4 | K75: 45 C.F.R. §§ 164.308(a)(1)(ii)(D), 164.308(a)(5)(ii)(B), 164.308(a)(5)(ii)(C), 164.308(a)(8), 164.312(b), 164.312(e)(2)(i)
A76: 3.2.2 | B76: DE | C76: Detect | D76: CM | E76: Security Continuous Monitoring (DE.CM): The information system and assets are monitored to identify cybersecurity events and verify the effectiveness of protective measures. | F76: DE.CM-2 | G76: The physical environment is monitored to detect potential cybersecurity events | I76: A.14.2.8 | J76: CA-7, PE-3, PE-6, PE-20 | K76: 45 C.F.R. §§ 164.310(a)(2)(ii), 164.310(a)(2)(iii) | M76: APO13.02
A77: 3.2.3 | B77: DE | C77: Detect | D77: CM | E77: Security Continuous Monitoring (DE.CM): The information system and assets are monitored to identify cybersecurity events and verify the effectiveness of protective measures. | F77: DE.CM-3 | G77: Personnel activity is monitored to detect potential cybersecurity events | H77: CIS CSC 5, 7, 14, 16 | I77: A.16.1.2 | J77: AC-2, AU-12, AU-13, CA-7, CM-10, CM-11 | K77: 45 C.F.R. §§ 164.308(a)(1)(ii)(D), 164.308(a)(3)(ii)(A),164.308(a)(5)(ii)(C), 164.312(a)(2)(i), 164.312(b), 164.312(d), 164.312(e) | M77: APO12.06
A78: 3.2.4 | B78: DE | C78: Detect | D78: CM | E78: Security Continuous Monitoring (DE.CM): The information system and assets are monitored to identify cybersecurity events and verify the effectiveness of protective measures. | F78: DE.CM-4 | G78: Malicious code is detected | H78: CIS CSC 4, 7, 8, 12 | I78: A.16.1.6 | J78: SI-3, SI-8 | K78: 45 C.F.R. §§ 164.308(a)(1)(ii)(D), 164.308(a)(5)(ii)(B) | M78: APO11.06, DSS04.05
A79: 3.2.5 | B79: DE | C79: Detect | D79: CM | E79: Security Continuous Monitoring (DE.CM): The information system and assets are monitored to identify cybersecurity events and verify the effectiveness of protective measures. | F79: DE.CM-5 | G79: Unauthorized mobile code is detected | H79: CIS CSC 7, 8 | I79: A.16.1.5 | J79: SC-18, SI-4, SC-44 | K79: 45 C.F.R. §§ 164.308(a)(1)(ii)(D), 164.308(a)(5)(ii)(B) | M79: BAI01.10
A80: 3.2.6 | B80: DE | C80: Detect | D80: CM | E80: Security Continuous Monitoring (DE.CM): The information system and assets are monitored to identify cybersecurity events and verify the effectiveness of protective measures. | F80: DE.CM-6 | G80: External service provider activity is monitored to detect potential cybersecurity events | I80: A.6.1.1, A.16.1.1 | J80: CA-7, PS-7, SA-4, SA-9, SI-4 | K80: 45 C.F.R. § 164.308(a)(1)(ii)(D)
A81: 3.2.7 | B81: DE | C81: Detect | D81: CM | E81: Security Continuous Monitoring (DE.CM): The information system and assets are monitored to identify cybersecurity events and verify the effectiveness of protective measures. | F81: DE.CM-7 | G81: Monitoring for unauthorized personnel, connections, devices, and software is performed | H81: CIS CSC 1, 2, 3, 5, 9, 12, 13, 15, 16 | I81: A.6.1.3, A.16.1.2 | J81: AU-12, CA-7, CM-3, CM-8, PE-3, PE-6, PE-20, SI-4 | K81: 45 C.F.R. §§ 164.308(a)(1)(ii)(D), 164.308(a)(5)(ii)(B), 164.308(a)(5)(ii)(C), 164.310(a)(1), 164.310(a)(2)(ii), 164.310(a)(2)(iii), 164.310(b), 164.310(c), 164.310(d)(1), 164.310(d)(2)(iii), 164.312(b), 164.314(b)(2)(i)
A82: 3.2.8 | B82: DE | C82: Detect | D82: CM | E82: Security Continuous Monitoring (DE.CM): The information system and assets are monitored to identify cybersecurity events and verify the effectiveness of protective measures. | F82: DE.CM-8 | G82: Vulnerability scans are performed | H82: CIS CSC 4, 20 | I82: A.16.1.2 | J82: RA-5 | K82: 45 C.F.R. §§164.308(a)(1)(i), 164.308(a)(8)
A83: 3.3.1 | B83: DE | C83: Detect | D83: DP | E83: Detection Processes (DE.DP): Detection processes and procedures are maintained and tested to ensure awareness of anomalous events. | F83: DE.DP-1 | G83: Roles and responsibilities for detection are well defined to ensure accountability | H83: CIS CSC 19 | J83: CA-2, CA-7, PM-14 | K83: 45 C.F.R. §§ 164.308(a)(2), 164.308(a)(3)(ii)(A), 164.308(a)(3)(ii)(B), 164.308(a)(4), 164.310(a)(2)(iii), 164.312(a)(1), 164.312(a)(2)(ii)
A84: 3.3.2 | B84: DE | C84: Detect | D84: DP | E84: Detection Processes (DE.DP): Detection processes and procedures are maintained and tested to ensure awareness of anomalous events. | F84: DE.DP-2 | G84: Detection activities comply with all applicable requirements | J84: AC-25, CA-2, CA-7, SA-18, SI-4, PM-14 | K84: 45 C.F.R. §§ 164.308(a)(1)(i), 164.308(a)(8)
A85: 3.3.3 | B85: DE | C85: Detect | D85: DP | E85: Detection Processes (DE.DP): Detection processes and procedures are maintained and tested to ensure awareness of anomalous events. | F85: DE.DP-3 | G85: Detection processes are tested | I85: A.12.4.1, A.12.4.3, A.16.1.5 | J85: CA-2, CA-7, PE-3, SI-3, SI-4, PM-14 | K85: 45 C.F.R. § 164.306(e) | M85: DSS02.07
A86: 3.3.4 | B86: DE | C86: Detect | D86: DP | E86: Detection Processes (DE.DP): Detection processes and procedures are maintained and tested to ensure awareness of anomalous events. | F86: DE.DP-4 | G86: Event detection information is communicated | H86: CIS CSC 19 | I86: A.16.1.6 | J86: AU-6, CA-2, CA-7, RA-5, SI-4 | K86: 45 C.F.R. §§ 164.308(a)(6)(ii), 164.314(a)(2)(i)(C), 164.314(a)(2)(iii)
A87: 3.3.5 | B87: DE | C87: Detect | D87: DP | E87: Detection Processes (DE.DP): Detection processes and procedures are maintained and tested to ensure awareness of anomalous events. | F87: DE.DP-5 | G87: Detection processes are continuously improved | I87: A.16.1.7 | J87: , CA-2, CA-7, PL-2, RA-5, SI-4, PM-14 | K87: 45 C.F.R. §§ 164.306(e), 164.308(a)(8)
A88: 4.1.1 | B88: RS | C88: Respond | D88: RP | E88: Response Planning (RS.RP): Response processes and procedures are executed and maintained, to ensure response to detected cybersecurity incidents. | F88: RS.RP-1 | G88: Response plan is executed during or after an incident | H88: CIS CSC 19 | I88: A.16.1.4 | J88: CP-2, CP-10, IR-4, IR-8 | K88: 45 C.F.R. §§ 164.308(a)(6)(ii), 164.308(a)(7)(i), 164.308(a)(7)(ii)(A), 164.308(a)(7)(ii)(B), 164.308(a)(7)(ii)(C), 164.310(a)(2)(i), 164.312(a)(2)(ii)
A89: 4.2.1 | B89: RS | C89: Respond | D89: CO | E89: Communications (RS.CO): Response activities are coordinated with internal and external stakeholders (e.g. external support from law enforcement agencies). | F89: RS.CO-1 | G89: Personnel know their roles and order of operations when a response is needed | H89: CIS CSC 19 | I89: A.16.1.5 | J89: CP-2, CP-3, IR-3, IR-8 | K89: 45 C.F.R. §§ 164.308(a)(2), 164.308(a)(7)(ii)(A), 164.308(a)(7)(ii)(B), 164.308(a)(7)(ii)(C), 164.310(a)(2)(i), 164.308(a)(6)(i), 164.312(a)(2)(ii)
A90: 4.2.2 | B90: RS | C90: Respond | D90: CO | E90: Communications (RS.CO): Response activities are coordinated with internal and external stakeholders (e.g. external support from law enforcement agencies). | F90: RS.CO-2 | G90: Incidents are reported consistent with established criteria | H90: CIS CSC 19 | I90: A.12.2.1, A.16.1.5 | J90: AU-6, IR-6, IR-8 | K90: 45 C.F.R. §§ 164.308(a)(5)(ii)(B), 164.308(a)(5)(ii)(C), 164.308(a)(6)(ii), 164.314(a)(2)(i)(C), 164.314(a)(2)(iii)
A91: 4.2.3 | B91: RS | C91: Respond | D91: CO | E91: Communications (RS.CO): Response activities are coordinated with internal and external stakeholders (e.g. external support from law enforcement agencies). | F91: RS.CO-3 | G91: Information is shared consistent with response plans | H91: CIS CSC 19 | I91: A.12.6.1 | J91: CA-2, CA-7, CP-2, IR-4, IR-8, PE-6, RA-5, SI-4 | K91: 45 C.F.R. §§ 164.308(a)(5)(ii)(B), 164.308(a)(5)(ii)(C), 164.308(a)(6)(ii), 164.314(a)(2)(i)(C)
A92: 4.2.4 | B92: RS | C92: Respond | D92: CO | E92: Communications (RS.CO): Response activities are coordinated with internal and external stakeholders (e.g. external support from law enforcement agencies). | F92: RS.CO-4 | G92: Coordination with stakeholders occurs consistent with response plans | H92: CIS CSC 19 | I92: A.16.1.6 | J92: CP-2, IR-4, IR-8 | K92: 45 C.F.R. §§ 164.308(a)(6), 164.308(a)(7), 164.310(a)(2)(i), 164.312(a)(2)(ii) | M92: BAI01.13
A93: 4.2.5 | B93: RS | C93: Respond | D93: CO | E93: Communications (RS.CO): Response activities are coordinated with internal and external stakeholders (e.g. external support from law enforcement agencies). | F93: RS.CO-5 | G93: Voluntary information sharing occurs with external stakeholders to achieve broader cybersecurity situational awareness | H93: CIS CSC 19 | J93: SI-5, PM-15 | K93: 45 C.F.R. § 164.308(a)(6)
A94: 4.3.1 | B94: RS | C94: Respond | D94: AN | E94: Analysis (RS.AN): Analysis is conducted to ensure effective response and support recovery activities. | F94: RS.AN-1 | G94: Notifications from detection systems are investigated | H94: CIS CSC 4, 6, 8, 19 | I94: A.16.1.5 | J94: AU-6, CA-7, IR-4, IR-5, PE-6, SI-4 | K94: 45 C.F.R. §§ 164.308(a)(1)(i), 164.308(a)(1)(ii)(D),164.308(a)(5)(ii)(B), 164.308(a)(5)(ii)(C), 164.308(a)(6)(ii), 164.312(b) | M94: DSS02.05, DSS03.04
A95: 4.3.2 | B95: RS | C95: Respond | D95: AN | E95: Analysis (RS.AN): Analysis is conducted to ensure effective response and support recovery activities. | F95: RS.AN-2 | G95: The impact of the incident is understood | J95: CP-2, IR-4 | K95: 45 C.F.R. §§ 164.308(a)(6)(ii), 164.308(a)(7)(ii)(B), 164.308(a)(7)(ii)(C), 164.308(a)(7)(ii)(E) | M95: BAI05.07
A96: 4.3.3 | B96: RS | C96: Respond | D96: AN | E96: Analysis (RS.AN): Analysis is conducted to ensure effective response and support recovery activities. | F96: RS.AN-3 | G96: Forensics are performed | J96: AU-7, IR-4 | K96: 45 C.F.R. § 164.308(a)(6) | M96: BAI07.08
A97: 4.3.4 | B97: RS | C97: Respond | D97: AN | E97: Analysis (RS.AN): Analysis is conducted to ensure effective response and support recovery activities. | F97: RS.AN-4 | G97: Incidents are categorized consistent with response plans | H97: CIS CSC 19 | J97: CP-2, IR-4, IR-5, IR-8 | K97: 45 C.F.R. § 164.308(a)(6)(ii) | M97: EDM03.02
A98: 4.3.5 | B98: RS | C98: Respond | D98: AN | E98: Analysis (RS.AN): Analysis is conducted to ensure effective response and support recovery activities. | F98: RS.AN-5 | G98: Processes are established to receive, analyze and respond to vulnerabilities disclosed to the organization from internal and external sources (e.g. internal testing, security bulletins, or security researchers) | H98: CIS CSC 4, 19 | J98: SI-5, PM-15 | M98: MEA03.02
A99: 4.4.1 | B99: RS | C99: Respond | D99: MI | E99: Mitigation (RS.MI): Activities are performed to prevent expansion of an event, mitigate its effects, and resolve the incident. | F99: RS.MI-1 | G99: Incidents are contained | H99: CIS CSC 19 | J99: IR-4 | K99: 45 C.F.R. § 164.308(a)(6)(ii)
A100: 4.4.2 | B100: RS | C100: Respond | D100: MI | E100: Mitigation (RS.MI): Activities are performed to prevent expansion of an event, mitigate its effects, and resolve the incident. | F100: RS.MI-2 | G100: Incidents are mitigated | H100: CIS CSC 4, 19 | J100: IR-4 | K100: 45 C.F.R. § 164.308(a)(6)(ii)
...

Sheet NIST 800-53
A1: Control Identifier | B1: Control (or Control Enhancement) Name | C1: Control (or Control Enhancement) | D1: Discussion | E1: Related Controls
A2: AC-1 | B2: Policy and Procedures | C2: a. Develop, document, and disseminate to [Assignment: organization-defined personnel or roles]: 1. [Selection (one or more): organization-level; mission/business process-level; system-level] access control policy that: (a) Addresses purpose, scope, roles, responsibilities, management commitment, coordination among organizational entities, and compliance; and (b) Is consistent with applicable laws, executive orders, directives, regulations, policies, standards, and guidelines; and 2. Procedures to facilitate the implementation of the access control policy and the associated access controls; b. Designate an [Assignment: organization-defined official] to manage the development, documentation, and dissemination of the access control policy and procedures; and c. Review and update the current access control: 1. Policy [Assignment: organization-defined frequency] and following [Assignment: organization-defined events]; and 2. Procedures [Assignment: organization-defined frequency] and following [Assignment: organization-defined events]. | D2: Access control policy and procedures address the controls in the AC family that are implemented within systems and organizations. The risk management strategy is an important factor in establishing such policies and procedures. Policies and procedures contribute to security and privacy assurance. Therefore, it is important that security and privacy programs collaborate on the development of access control policy and procedures. Security and privacy program policies and procedures at the organization level are preferable, in general, and may obviate the need for mission- or system-specific policies and procedures. The policy can be included as part of the general security and privacy policy or be represented by multiple policies reflecting the complex nature of organizations. Procedures can be established for security and privacy programs, for mission or business processes, and for systems, if needed. Procedures describe how the policies or controls are implemented and can be directed at the individual or role that is the object of the procedure. Procedures can be documented in system security and privacy plans or in one or more separate documents. Events that may precipitate an update to access control policy and procedures include assessment or audit findings, security or privacy incidents, or changes in laws, executive orders, directives, regulations, policies, standards, and guidelines. Simply restating controls does not constitute an organizational policy or procedure. | E2: IA-1, PM-9, PM-24, PS-8, SI-12
A3: AC-2 | B3: Account Management | C3: a. Define and document the types of accounts allowed and specifically prohibited for use within the system; b. Assign account managers; c. Require [Assignment: organization-defined prerequisites and criteria] for group and role membership; d. Specify: 1. Authorized users of the system; 2. Group and role membership; and 3. Access authorizations (i.e., privileges) and [Assignment: organization-defined attributes (as required)] for each account; e. Require approvals by [Assignment: organization-defined personnel or roles] for requests to create accounts; f. Create, enable, modify, disable, and remove accounts in accordance with [Assignment: organization-defined policy, procedures, prerequisites, and criteria]; g. Monitor the use of accounts; h. Notify account managers and [Assignment: organization-defined personnel or roles] within: 1. [Assignment: organization-defined time period] when accounts are no longer required; 2. [Assignment: organization-defined time period] when users are terminated or transferred; and 3. [Assignment: organization-defined time period] when system usage or need-to-know changes for an individual; i. Authorize access to the system based on: 1. A valid access authorization; 2. Intended system usage; and 3. [Assignment: organization-defined attributes (as required)]; j. Review accounts for compliance with account management requirements [Assignment: organization-defined frequency]; k. Establish and implement a process for changing shared or group account authenticators (if deployed) when individuals are removed from the group; and l. Align account management processes with personnel termination and transfer processes. | D3: Examples of system account types include individual, shared, group, system, guest, anonymous, emergency, developer, temporary, and service. Identification of authorized system users and the specification of access privileges reflect the requirements in other controls in the security plan. Users requiring administrative privileges on system accounts receive additional scrutiny by organizational personnel responsible for approving such accounts and privileged access, including system owner, mission or business owner, senior agency information security officer, or senior agency official for privacy. Types of accounts that organizations may wish to prohibit due to increased risk include shared, group, emergency, anonymous, temporary, and guest accounts. Where access involves personally identifiable information, security programs collaborate with the senior agency official for privacy to establish the specific conditions for group and role membership; specify authorized users, group and role membership, and access authorizations for each account; and create, adjust, or remove system accounts in accordance with organizational policies. Policies can include such information as account expiration dates or other factors that trigger the disabling of accounts. Organizations may choose to define access privileges or other attributes by account, type of account, or a combination of the two. Examples of other attributes required for authorizing access include restrictions on time of day, day of week, and point of origin. In defining other system account attributes, organizations consider system-related requirements and mission/business requirements. Failure to consider these factors could affect system availability. Temporary and emergency accounts are intended for short-term use. Organizations establish temporary accounts as part of normal account activation procedures when there is a need for short-term accounts without the demand for immediacy in account activation. Organizations establish emergency accounts in response to crisis situations and with the need for rapid account activation. Therefore, emergency account activation may bypass normal account authorization processes. Emergency and temporary accounts are not to be confused with infrequently used accounts, including local logon accounts used for special tasks or when network resources are unavailable (may also be known as accounts of last resort). Such accounts remain available and are not subject to automatic disabling or removal dates. Conditions for disabling or deactivating accounts include when shared/group, emergency, or temporary accounts are no longer required and when individuals are transferred or terminated. Changing shared/group authenticators when members leave the group is intended to ensure that former group members do not retain access to the shared or group account. Some types of system accounts may require specialized training. | E3: AC-3, AC-5, AC-6, AC-17, AC-18, AC-20, AC-24, AU-2, AU-12, CM-5, IA-2, IA-4, IA-5, IA-8, MA-3, MA-5, PE-2, PL-4, PS-2, PS-4, PS-5, PS-7, PT-2, PT-3, SC-7, SC-12, SC-13, SC-37
A4: AC-2(1) | B4: Account Management | Automated System Account Management | C4: Support the management of system accounts using [Assignment: organization-defined automated mechanisms]. | D4: Automated system account management includes using automated mechanisms to create, enable, modify, disable, and remove accounts; notify account managers when an account is created, enabled, modified, disabled, or removed, or when users are terminated or transferred; monitor system account usage; and report atypical system account usage. Automated mechanisms can include internal system functions and email, telephonic, and text messaging notifications.
A5: AC-2(2) | B5: Account Management | Automated Temporary and Emergency Account Management | C5: Automatically [Selection: remove; disable] temporary and emergency accounts after [Assignment: organization-defined time period for each type of account]. | D5: Management of temporary and emergency accounts includes the removal or disabling of such accounts automatically after a predefined time period rather than at the convenience of the system administrator. Automatic removal or disabling of accounts provides a more consistent implementation.
A6: AC-2(3) | B6: Account Management | Disable Accounts | C6: Disable accounts within [Assignment: organization-defined time period] when the accounts: (a) Have expired; (b) Are no longer associated with a user or individual; (c) Are in violation of organizational policy; or (d) Have been inactive for [Assignment: organization-defined time period]. | D6: Disabling expired, inactive, or otherwise anomalous accounts supports the concepts of least privilege and least functionality which reduce the attack surface of the system.
A7: AC-2(4) | B7: Account Management | Automated Audit Actions | C7: Automatically audit account creation, modification, enabling, disabling, and removal actions. | D7: Account management audit records are defined in accordance with AU-2 and reviewed, analyzed, and reported in accordance with AU-6. | E7: AU-2, AU-6
A8: AC-2(5) | B8: Account Management | Inactivity Logout | C8: Require that users log out when [Assignment: organization-defined time period of expected inactivity or description of when to log out]. | D8: Inactivity logout is behavior- or policy-based and requires users to take physical action to log out when they are expecting inactivity longer than the defined period. Automatic enforcement of inactivity logout is addressed by AC-11. | E8: AC-11
A9: AC-2(6) | B9: Account Management | Dynamic Privilege Management | C9: Implement [Assignment: organization-defined dynamic privilege management capabilities]. | D9: In contrast to access control approaches that employ static accounts and predefined user privileges, dynamic access control approaches rely on runtime access control decisions facilitated by dynamic privilege management, such as attribute-based access control. While user identities remain relatively constant over time, user privileges typically change more frequently based on ongoing mission or business requirements and the operational needs of organizations. An example of dynamic privilege management is the immediate revocation of privileges from users as opposed to requiring that users terminate and restart their sessions to reflect changes in privileges. Dynamic privilege management can also include mechanisms that change user privileges based on dynamic rules as opposed to editing specific user profiles. Examples include automatic adjustments of user privileges if they are operating out of their normal work times, if their job function or assignment changes, or if systems are under duress or in emergency situations. Dynamic privilege management includes the effects of privilege changes, for example, when there are changes to encryption keys used for communications. | E9: AC-16
A10: AC-2(7) | B10: Account Management | Privileged User Accounts | C10: (a) Establish and administer privileged user accounts in accordance with [Selection: a role-based access scheme; an attribute-based access scheme]; (b) Monitor privileged role or attribute assignments; (c) Monitor changes to roles or attributes; and (d) Revoke access when privileged role or attribute assignments are no longer appropriate. | D10: Privileged roles are organization-defined roles assigned to individuals that allow those individuals to perform certain security-relevant functions that ordinary users are not authorized to perform. Privileged roles include key management, account management, database administration, system and network administration, and web administration. A role-based access scheme organizes permitted system access and privileges into roles. In contrast, an attribute-based access scheme specifies allowed system access and privileges based on attributes.
A11: AC-2(8) | B11: Account Management | Dynamic Account Management | C11: Create, activate, manage, and deactivate [Assignment: organization-defined system accounts] dynamically. | D11: Approaches for dynamically creating, activating, managing, and deactivating system accounts rely on automatically provisioning the accounts at runtime for entities that were previously unknown. Organizations plan for the dynamic management, creation, activation, and deactivation of system accounts by establishing trust relationships, business rules, and mechanisms with appropriate authorities to validate related authorizations and privileges. | E11: AC-16
A12: AC-2(9) | B12: Account Management | Restrictions on Use of Shared and Group Accounts | C12: Only permit the use of shared and group accounts that meet [Assignment: organization-defined conditions for establishing shared and group accounts]. | D12: Before permitting the use of shared or group accounts, organizations consider the increased risk due to the lack of accountability with such accounts.
A13: AC-2(10) | B13: Account Management | Shared and Group Account Credential Change
A14: AC-2(11) | B14: Account Management | Usage Conditions | C14: Enforce [Assignment: organization-defined circumstances and/or usage conditions] for [Assignment: organization-defined system accounts]. | D14: Specifying and enforcing usage conditions helps to enforce the principle of least privilege, increase user accountability, and enable effective account monitoring. Account monitoring includes alerts generated if the account is used in violation of organizational parameters. Organizations can describe specific conditions or circumstances under which system accounts can be used, such as by restricting usage to certain days of the week, time of day, or specific durations of time.
A15: AC-2(12) | B15: Account Management | Account Monitoring for Atypical Usage | C15: (a) Monitor system accounts for [Assignment: organization-defined atypical usage]; and (b) Report atypical usage of system accounts to [Assignment: organization-defined personnel or roles]. | D15: Atypical usage includes accessing systems at certain times of the day or from locations that are not consistent with the normal usage patterns of individuals. Monitoring for atypical usage may reveal rogue behavior by individuals or an attack in progress. Account monitoring may inadvertently create privacy risks since data collected to identify atypical usage may reveal previously unknown information about the behavior of individuals. Organizations assess and document privacy risks from monitoring accounts for atypical usage in their privacy impact assessment and make determinations that are in alignment with their privacy program plan. | E15: AU-6, AU-7, CA-7, IR-8, SI-4
A16: AC-2(13) | B16: Account Management | Disable Accounts for High-risk Individuals | C16: Disable accounts of individuals within [Assignment: organization-defined time period] of discovery of [Assignment: organization-defined significant risks]. | D16: Users who pose a significant security and/or privacy risk include individuals for whom reliable evidence indicates either the intention to use authorized access to systems to cause harm or through whom adversaries will cause harm. Such harm includes adverse impacts to organizational operations, organizational assets, individuals, other organizations, or the Nation. Close coordination among system administrators, legal staff, human resource managers, and authorizing officials is essential when disabling system accounts for high-risk individuals. | E16: AU-6, SI-4
A17: AC-3 | B17: Access Enforcement | C17: Enforce approved authorizations for logical access to information and system resources in accordance with applicable access control policies. | D17: Access control policies control access between active entities or subjects (i.e., users or processes acting on behalf of users) and passive entities or objects (i.e., devices, files, records, domains) in organizational systems. In addition to enforcing authorized access at the system level and recognizing that systems can host many applications and services in support of mission and business functions, access enforcement mechanisms can also be employed at the application and service level to provide increased information security and privacy. In contrast to logical access controls that are implemented within the system, physical access controls are addressed by the controls in the Physical and Environmental Protection (PE) family. | E17: AC-2, AC-4, AC-5, AC-6, AC-16, AC-17, AC-18, AC-19, AC-20, AC-21, AC-22, AC-24, AC-25, AT-2, AT-3, AU-9, CA-9, CM-5, CM-11, IA-2, IA-5, IA-6, IA-7, IA-11, MA-3, MA-4, MA-5, MP-4, PM-2, PS-3, PT-2, PT-3, SA-17, SC-2, SC-3, SC-4, SC-12, SC-13, SC-28, SC-31, SC-34, SI-4, SI-8
A18: AC-3(1) | B18: Access Enforcement | Restricted Access to Privileged Functions
A19: AC-3(2) | B19: Access Enforcement | Dual Authorization | C19: Enforce dual authorization for [Assignment: organization-defined privileged commands and/or other organization-defined actions]. | D19: Dual authorization, also known as two-person control, reduces risk related to insider threats. Dual authorization mechanisms require the approval of two authorized individuals to execute. To reduce the risk of collusion, organizations consider rotating dual authorization duties to other individuals. Organizations consider the risk associated with implementing dual authorization mechanisms when immediate responses are necessary to ensure public and environmental safety. | E19: CP-9, MP-6
A20: AC-3(3) | B20: Access Enforcement | Mandatory Access Control | C20: Enforce [Assignment: organization-defined mandatory access control policy] over the set of covered subjects and objects specified in the policy, and where the policy: (a) Is uniformly enforced across the covered subjects and objects within the system; (b) Specifies that a subject that has been granted access to information is constrained from doing any of the following; (1) Passing the information to unauthorized subjects or objects; (2) Granting its privileges to other subjects; (3) Changing one or more security attributes (specified by the policy) on subjects, objects, the system, or system components; (4) Choosing the security attributes and attribute values (specified by the policy) to be associated with newly created or modified objects; and (5) Changing the rules governing access control; and (c) Specifies that [Assignment: organization-defined subjects] may explicitly be granted [Assignment: organization-defined privileges] such that they are not limited by any defined subset (or all) of the above constraints. | D20: Mandatory access control is a type of nondiscretionary access control. Mandatory access control policies constrain what actions subjects can take with information obtained from objects for which they have already been granted access. This prevents the subjects from passing the information to unauthorized subjects and objects. Mandatory access control policies constrain actions that subjects can take with respect to the propagation of access control privileges; that is, a subject with a privilege cannot pass that privilege to other subjects. The policy is uniformly enforced over all subjects and objects to which the system has control. Otherwise, the access control policy can be circumvented. This enforcement is provided by an implementation that meets the reference monitor concept as described in AC-25. The policy is bounded by the system (i.e., once the information is passed outside of the control of the system, additional means may be required to ensure that the constraints on the information remain in effect). The trusted subjects described above are granted privileges consistent with the concept of least privilege (see AC-6). Trusted subjects are only given the minimum privileges necessary for satisfying organizational mission/business needs relative to the above policy. The control is most applicable when there is a mandate that establishes a policy regarding access to controlled unclassified information or classified information and some users of the system are not authorized access to all such information resident in the system. Mandatory access control can operate in conjunction with discretionary access control as described in AC-3(4). A subject constrained in its operation by mandatory access control policies can still operate under the less rigorous constraints of AC-3(4), but mandatory access control policies take precedence over the less rigorous constraints of AC-3(4). For example, while a mandatory access control policy imposes a constraint that prevents a subject from passing information to another subject operating at a different impact or classification level, AC-3(4) permits the subject to pass the information to any other subject with the same impact or classification level as the subject. Examples of mandatory access control policies include the Bell-LaPadula policy to protect confidentiality of information and the Biba policy to protect the integrity of information. | E20: SC-7
A21: AC-3(4) | B21: Access Enforcement | Discretionary Access Control | C21: Enforce [Assignment: organization-defined discretionary access control policy] over the set of covered subjects and objects specified in the policy, and where the policy specifies that a subject that has been granted access to information can do one or more of the following: (a) Pass the information to any other subjects or objects; (b) Grant its privileges to other subjects; (c) Change security attributes on subjects, objects, the system, or the system’s components; (d) Choose the security attributes to be associated with newly created or revised objects; or (e) Change the rules governing access control. | D21: When discretionary access control policies are implemented, subjects are not constrained with regard to what actions they can take with information for which they have already been granted access. Thus, subjects that have been granted access to information are not prevented from passing the information to other subjects or objects (i.e., subjects have the discretion to pass). Discretionary access control can operate in conjunction with mandatory access control as described in AC-3(3) and AC-3(15). A subject that is constrained in its operation by mandatory access control policies can still operate under the less rigorous constraints of discretionary access control. Therefore, while AC-3(3) imposes constraints that prevent a subject from passing information to another subject operating at a different impact or classification level, AC-3(4) permits the subject to pass the information to any subject at the same impact or classification level. The policy is bounded by the system. Once the information is passed outside of system control, additional means may be required to ensure that the constraints remain in effect. While traditional definitions of discretionary access control require identity-based access control, that limitation is not required for this particular use of discretionary access control.
A22: AC-3(5) | B22: Access Enforcement | Security-relevant Information | C22: Prevent access to [Assignment: organization-defined security-relevant information] except during secure, non-operable system states. | D22: Security-relevant information is information within systems that can potentially impact the operation of security functions or the provision of security services in a manner that could result in failure to enforce system security and privacy policies or maintain the separation of code and data. Security-relevant information includes access control lists, filtering rules for routers or firewalls, configuration parameters for security services, and cryptographic key management information. Secure, non-operable system states include the times in which systems are not performing mission or business-related processing, such as when the system is offline for maintenance, boot-up, troubleshooting, or shut down. | E22: CM-6, SC-39
A23: AC-3(6) | B23: Access Enforcement | Protection of User and System Information
A24: AC-3(7) | B24: Access Enforcement | Role-based Access Control | C24: Enforce a role-based access control policy over defined subjects and objects and control access based upon [Assignment: organization-defined roles and users authorized to assume such roles]. | D24: Role-based access control (RBAC) is an access control policy that enforces access to objects and system functions based on the defined role (i.e., job function) of the subject. Organizations can create specific roles based on job functions and the authorizations (i.e., privileges) to perform needed operations on the systems associated with the organization-defined roles. When users are assigned to specific roles, they inherit the authorizations or privileges defined for those roles. RBAC simplifies privilege administration for organizations because privileges are not assigned directly to every user (which can be a large number of individuals) but are instead acquired through role assignments. RBAC can also increase privacy and security risk if individuals assigned to a role are given access to information beyond what they need to support organizational missions or business functions. RBAC can be implemented as a mandatory or discretionary form of access control. For organizations implementing RBAC with mandatory access controls, the requirements in AC-3(3) define the scope of the subjects and objects covered by the policy.
A25: AC-3(8) | B25: Access Enforcement | Revocation of Access Authorizations | C25: Enforce the revocation of access authorizations resulting from changes to the security attributes of subjects and objects based on [Assignment: organization-defined rules governing the timing of revocations of access authorizations]. | D25: Revocation of access rules may differ based on the types of access revoked. For example, if a subject (i.e., user or process acting on behalf of a user) is removed from a group, access may not be revoked until the next time the object is opened or the next time the subject attempts to access the object. Revocation based on changes to security labels may take effect immediately. Organizations provide alternative approaches on how to make revocations immediate if systems cannot provide such capability and immediate revocation is necessary.
A26: AC-3(9) | B26: Access Enforcement | Controlled Release | C26: Release information outside of the system only if: (a) The receiving [Assignment: organization-defined system or system component] provides [Assignment: organization-defined controls]; and (b) [Assignment: organization-defined controls] are used to validate the appropriateness of the information designated for release. | D26: Organizations can only directly protect information when it resides within the system. Additional controls may be needed to ensure that organizational information is adequately protected once it is transmitted outside of the system. In situations where the system is unable to determine the adequacy of the protections provided by external entities, as a mitigating control, organizations procedurally determine whether the external systems are providing adequate controls. The means used to determine the adequacy of controls provided by external systems include conducting periodic assessments (inspections/tests), establishing agreements between the organization and its counterpart organizations, or some other process. The means used by external entities to protect the information received need not be the same as those used by the organization, but the means employed are sufficient to provide consistent adjudication of the security and privacy policy to protect the information and individuals’ privacy. Controlled release of information requires systems to implement technical or procedural means to validate the information prior to releasing it to external systems. For example, if the system passes information to a system controlled by another organization, technical means are employed to validate that the security and privacy attributes associated with the exported information are appropriate for the receiving system. Alternatively, if the system passes information to a printer in organization-controlled space, procedural means can be employed to ensure that only authorized individuals gain access to the printer. | E26: CA-3, PT-7, PT-8, SA-9, SC-16
A27: AC-3(10) | B27: Access Enforcement | Audited Override of Access Control Mechanisms | C27: Employ an audited override of automated access control mechanisms under [Assignment: organization-defined conditions] by [Assignment: organization-defined roles]. | D27: In certain situations, such as when there is a threat to human life or an event that threatens the organization’s ability to carry out critical missions or business functions, an override capability for access control mechanisms may be needed. Override conditions are defined by organizations and used only in those limited circumstances. Audit events are defined in AU-2. Audit records are generated in AU-12. | E27: AU-2, AU-6, AU-10, AU-12, AU-14
A28: AC-3(11) | B28: Access Enforcement | Restrict Access to Specific Information Types | C28: Restrict access to data repositories containing [Assignment: organization-defined information types]. | D28: Restricting access to specific information is intended to provide flexibility regarding access control of specific information types within a system. For example, role-based access could be employed to allow access to only a specific type of personally identifiable information within a database rather than allowing access to the database in its entirety. Other examples include restricting access to cryptographic keys, authentication information, and selected system information. | E28: CM-8, CM-12, CM-13, PM-5
A29: AC-3(12) | B29: Access Enforcement | Assert and Enforce Application Access | C29: (a) Require applications to assert, as part of the installation process, the access needed to the following system applications and functions: [Assignment: organization-defined system applications and functions]; (b) Provide an enforcement mechanism to prevent unauthorized access; and (c) Approve access changes after initial installation of the application. | D29: Asserting and enforcing application access is intended to address applications that need to access existing system applications and functions, including user contacts, global positioning systems, cameras, keyboards, microphones, networks, phones, or other files. | E29: CM-7
A30: AC-3(13) | B30: Access Enforcement | Attribute-based Access Control | C30: Enforce attribute-based access control policy over defined subjects and objects and control access based upon [Assignment: organization-defined attributes to assume access permissions]. | D30: Attribute-based access control is an access control policy that restricts system access to authorized users based on specified organizational attributes (e.g., job function, identity), action attributes (e.g., read, write, delete), environmental attributes (e.g., time of day, location), and resource attributes (e.g., classification of a document). Organizations can create rules based on attributes and the authorizations (i.e., privileges) to perform needed operations on the systems associated with organization-defined attributes and rules. When users are assigned to attributes defined in attribute-based access control policies or rules, they can be provisioned to a system with the appropriate privileges or dynamically granted access to a protected resource. Attribute-based access control can be implemented as either a mandatory or discretionary form of access control. When implemented with mandatory access controls, the requirements in AC-3(3) define the scope of the subjects and objects covered by the policy.
A31: AC-3(14) | B31: Access Enforcement | Individual Access | C31: Provide [Assignment: organization-defined mechanisms] to enable individuals to have access to the following elements of their personally identifiable information: [Assignment: organization-defined elements]. | D31: Individual access affords individuals the ability to review personally identifiable information about them held within organizational records, regardless of format. Access helps individuals to develop an understanding about how their personally identifiable information is being processed. It can also help individuals ensure that their data is accurate. Access mechanisms can include request forms and application interfaces. For federal agencies, [PRIVACT] processes can be located in systems of record notices and on agency websites. Access to certain types of records may not be appropriate (e.g., for federal agencies, law enforcement records within a system of records may be exempt from disclosure under the [PRIVACT]) or may require certain levels of authentication assurance. Organizational personnel consult with the senior agency official for privacy and legal counsel to determine appropriate mechanisms and access rights or limitations. | E31: IA-8, PM-22, PM-20, PM-21
A32: AC-3(15) | B32: Access Enforcement | Discretionary and Mandatory Access Control | C32: (a) Enforce [Assignment: organization-defined mandatory access control policy] over the set of covered subjects and objects specified in the policy; and (b) Enforce [Assignment: organization-defined discretionary access control policy] over the set of covered subjects and objects specified in the policy. | D32: Simultaneously implementing a mandatory access control policy and a discretionary access control policy can provide additional protection against the unauthorized execution of code by users or processes acting on behalf of users. This helps prevent a single compromised user or process from compromising the entire system. | E32: SC-2, SC-3, AC-4
A33: AC-4 | B33: Information Flow Enforcement | C33: Enforce approved authorizations for controlling the flow of information within the system and between connected systems based on [Assignment: organization-defined information flow control policies]. | D33: Information flow control regulates where information can travel within a system and between systems (in contrast to who is allowed to access the information) and without regard to subsequent accesses to that information. Flow control restrictions include blocking external traffic that claims to be from within the organization, keeping export-controlled information from being transmitted in the clear to the Internet, restricting web requests that are not from the internal web proxy server, and limiting information transfers between organizations based on data structures and content. Transferring information between organizations may require an agreement specifying how the information flow is enforced (see CA-3). Transferring information between systems in different security or privacy domains with different security or privacy policies introduces the risk that such transfers violate one or more domain security or privacy policies. In such situations, information owners/stewards provide guidance at designated policy enforcement points between connected systems. Organizations consider mandating specific architectural solutions to enforce specific security and privacy policies. Enforcement includes prohibiting information transfers between connected systems (i.e., allowing access only), verifying write permissions before accepting information from another security or privacy domain or connected system, employing hardware mechanisms to enforce one-way information flows, and implementing trustworthy regrading mechanisms to reassign security or privacy attributes and labels. Organizations commonly employ information flow control policies and enforcement mechanisms to control the flow of information between designated sources and destinations within systems and between connected systems. Flow control is based on the characteristics of the information and/or the information path. Enforcement occurs, for example, in boundary protection devices that employ rule sets or establish configuration settings that restrict system services, provide a packet-filtering capability based on header information, or provide a message-filtering capability based on message content. Organizations also consider the trustworthiness of filtering and/or inspection mechanisms (i.e., hardware, firmware, and software components) that are critical to information flow enforcement. Control enhancements 3 through 32 primarily address cross-domain solution needs that focus on more advanced filtering techniques, in-depth analysis, and stronger flow enforcement mechanisms implemented in cross-domain products, such as high-assurance guards. Such capabilities are generally not available in commercial off-the-shelf products. Information flow enforcement also applies to control plane traffic (e.g., routing and DNS). | E33: AC-3, AC-6, AC-16, AC-17, AC-19, AC-21, AU-10, CA-3, CA-9, CM-7, PL-9, PM-24, SA-17, SC-4, SC-7, SC-16, SC-31
A34: AC-4(1) | B34: Information Flow Enforcement | Object Security and Privacy Attributes | C34: Use [Assignment: organization-defined security and privacy attributes] associated with [Assignment: organization-defined information, source, and destination objects] to enforce [Assignment: organization-defined information flow control policies] as a basis for flow control decisions. | D34: Information flow enforcement mechanisms compare security and privacy attributes associated with information (i.e., data content and structure) and source and destination objects and respond appropriately when the enforcement mechanisms encounter information flows not explicitly allowed by information flow policies. For example, an information object labeled Secret would be allowed to flow to a destination object labeled Secret, but an information object labeled Top Secret would not be allowed to flow to a destination object labeled Secret. A dataset of personally identifiable information may be tagged with restrictions against combining with other types of datasets and, thus, would not be allowed to flow to the restricted dataset. Security and privacy attributes can also include source and destination addresses employed in traffic filter firewalls. Flow enforcement using explicit security or privacy attributes can be used, for example, to control the release of certain types of information.
A35: AC-4(2) | B35: Information Flow Enforcement | Processing Domains | C35: Use protected processing domains to enforce [Assignment: organization-defined information flow control policies] as a basis for flow control decisions. | D35: Protected processing domains within systems are processing spaces that have controlled interactions with other processing spaces, enabling control of information flows between these spaces and to/from information objects. A protected processing domain can be provided, for example, by implementing domain and type enforcement. In domain and type enforcement, system processes are assigned to domains, information is identified by types, and information flows are controlled based on allowed information accesses (i.e., determined by domain and type), allowed signaling among domains, and allowed process transitions to other domains. | E35: SC-39
A36: AC-4(3) | B36: Information Flow Enforcement | Dynamic Information Flow Control | C36: Enforce [Assignment: organization-defined information flow control policies]. | D36: Organizational policies regarding dynamic information flow control include allowing or disallowing information flows based on changing conditions or mission or operational considerations. Changing conditions include changes in risk tolerance due to changes in the immediacy of mission or business needs, changes in the threat environment, and detection of potentially harmful or adverse events. | E36: SI-4
A37: AC-4(4) | B37: Information Flow Enforcement | Flow Control of Encrypted Information | C37: Prevent encrypted information from bypassing [Assignment: organization-defined information flow control mechanisms] by [Selection (one or more): decrypting the information; blocking the flow of the encrypted information; terminating communications sessions attempting to pass encrypted information; [Assignment: organization-defined procedure or method] ]. | D37: Flow control mechanisms include content checking, security policy filters, and data type identifiers. The term encryption is extended to cover encoded data not recognized by filtering mechanisms. | E37: SI-4
A38: AC-4(5) | B38: Information Flow Enforcement | Embedded Data Types | C38: Enforce [Assignment: organization-defined limitations] on embedding data types within other data types. | D38: Embedding data types within other data types may result in reduced flow control effectiveness. Data type embedding includes inserting files as objects within other files and using compressed or archived data types that may include multiple embedded data types. Limitations on data type embedding consider the levels of embedding and prohibit levels of data type embedding that are beyond the capability of the inspection tools.
A39: AC-4(6) | B39: Information Flow Enforcement | Metadata | C39: Enforce information flow control based on [Assignment: organization-defined metadata]. | D39: Metadata is information that describes the characteristics of data. Metadata can include structural metadata describing data structures or descriptive metadata describing data content. Enforcement of allowed information flows based on metadata enables simpler and more effective flow control. Organizations consider the trustworthiness of metadata regarding data accuracy (i.e., knowledge that the metadata values are correct with respect to the data), data integrity (i.e., protecting against unauthorized changes to metadata tags), and the binding of metadata to the data payload (i.e., employing sufficiently strong binding techniques with appropriate assurance). | E39: AC-16, SI-7
A40: AC-4(7) | B40: Information Flow Enforcement | One-way Flow Mechanisms | C40: Enforce one-way information flows through hardware-based flow control mechanisms. | D40: One-way flow mechanisms may also be referred to as a unidirectional network, unidirectional security gateway, or data diode. One-way flow mechanisms can be used to prevent data from being exported from a higher impact or classified domain or system while permitting data from a lower impact or unclassified domain or system to be imported.
A41: AC-4(8) | B41: Information Flow Enforcement | Security and Privacy Policy Filters | C41: (a) Enforce information flow control using [Assignment: organization-defined security or privacy policy filters] as a basis for flow control decisions for [Assignment: organization-defined information flows]; and (b) [Selection (one or more): Block; Strip; Modify; Quarantine] data after a filter processing failure in accordance with [Assignment: organization-defined security or privacy policy]. | D41: Organization-defined security or privacy policy filters can address data structures and content. For example, security or privacy policy filters for data structures can check for maximum file lengths, maximum field sizes, and data/file types (for structured and unstructured data). Security or privacy policy filters for data content can check for specific words, enumerated values or data value ranges, and hidden content. Structured data permits the interpretation of data content by applications. Unstructured data refers to digital information without a data structure or with a data structure that does not facilitate the development of rule sets to address the impact or classification level of the information conveyed by the data or the flow enforcement decisions. Unstructured data consists of bitmap objects that are inherently non-language-based (i.e., image, video, or audio files) and textual objects that are based on written or printed languages. Organizations can implement more than one security or privacy policy filter to meet information flow control objectives.
A42: AC-4(9) | B42: Information Flow Enforcement | Human Reviews | C42: Enforce the use of human reviews for [Assignment: organization-defined information flows] under the following conditions: [Assignment: organization-defined conditions]. | D42: Organizations define security or privacy policy filters for all situations where automated flow control decisions are possible. When a fully automated flow control decision is not possible, then a human review may be employed in lieu of or as a complement to automated security or privacy policy filtering. Human reviews may also be employed as deemed necessary by organizations.
A43: AC-4(10) | B43: Information Flow Enforcement | Enable and Disable Security or Privacy Policy Filters | C43: Provide the capability for privileged administrators to enable and disable [Assignment: organization-defined security or privacy policy filters] under the following conditions: [Assignment: organization-defined conditions]. | D43: For example, as allowed by the system authorization, administrators can enable security or privacy policy filters to accommodate approved data types. Administrators also have the capability to select the filters that are executed on a specific data flow based on the type of data that is being transferred, the source and destination security domains, and other security or privacy relevant features, as needed.
A44: AC-4(11) | B44: Information Flow Enforcement | Configuration of Security or Privacy Policy Filters | C44: Provide the capability for privileged administrators to configure [Assignment: organization-defined security or privacy policy filters] to support different security or privacy policies. | D44: Documentation contains detailed information for configuring security or privacy policy filters. For example, administrators can configure security or privacy policy filters to include the list of inappropriate words that security or privacy policy mechanisms check in accordance with the definitions provided by organizations.
A45: AC-4(12) | B45: Information Flow Enforcement | Data Type Identifiers | C45: When transferring information between different security domains, use [Assignment: organization-defined data type identifiers] to validate data essential for information flow decisions. | D45: Data type identifiers include filenames, file types, file signatures or tokens, and multiple internal file signatures or tokens. Systems only allow transfer of data that is compliant with data type format specifications. Identification and validation of data types is based on defined specifications associated with each allowed data format. The filename and number alone are not used for data type identification. Content is validated syntactically and semantically against its specification to ensure that it is the proper data type.
A46: AC-4(13) | B46: Information Flow Enforcement | Decomposition into Policy-relevant Subcomponents | C46: When transferring information between different security domains, decompose information into [Assignment: organization-defined policy-relevant subcomponents] for submission to policy enforcement mechanisms. | D46: Decomposing information into policy-relevant subcomponents prior to information transfer facilitates policy decisions on source, destination, certificates, classification, attachments, and other security- or privacy-related component differentiators. Policy enforcement mechanisms apply filtering, inspection, and/or sanitization rules to the policy-relevant subcomponents of information to facilitate flow enforcement prior to transferring such information to different security domains.
A47: AC-4(14) | B47: Information Flow Enforcement | Security or Privacy Policy Filter Constraints | C47: When transferring information between different security domains, implement [Assignment: organization-defined security or privacy policy filters] requiring fully enumerated formats that restrict data structure and content. | D47: Data structure and content restrictions reduce the range of potential malicious or unsanctioned content in cross-domain transactions. Security or privacy policy filters that restrict data structures include restricting file sizes and field lengths. Data content policy filters include encoding formats for character sets, restricting character data fields to only contain alpha-numeric characters, prohibiting special characters, and validating schema structures.
A48: AC-4(15) | B48: Information Flow Enforcement | Detection of Unsanctioned Information | C48: When transferring information between different security domains, examine the information for the presence of [Assignment: organization-defined unsanctioned information] and prohibit the transfer of such information in accordance with the [Assignment: organization-defined security or privacy policy]. | D48: Unsanctioned information includes malicious code, information that is inappropriate for release from the source network, or executable code that could disrupt or harm the services or systems on the destination network. | E48: SI-3
A49: AC-4(16) | B49: Information Flow Enforcement | Information Transfers on Interconnected Systems
A50: AC-4(17) | B50: Information Flow Enforcement | Domain Authentication | C50: Uniquely identify and authenticate source and destination points by [Selection (one or more): organization; system; application; service; individual] for information transfer. | D50: Attribution is a critical component of a security and privacy concept of operations. The ability to identify source and destination points for information flowing within systems allows the forensic reconstruction of events and encourages policy compliance by attributing policy violations to specific organizations or individuals. Successful domain authentication requires that system labels distinguish among systems, organizations, and individuals involved in preparing, sending, receiving, or disseminating information. Attribution also allows organizations to better maintain the lineage of personally identifiable information processing as it flows through systems and can facilitate consent tracking, as well as correction, deletion, or access requests from individuals. | E50: IA-2, IA-3, IA-9
A51: AC-4(18) | B51: Information Flow Enforcement | Security Attribute Binding
A52: AC-4(19) | B52: Information Flow Enforcement | Validation of Metadata | C52: When transferring information between different security domains, implement [Assignment: organization-defined security or privacy policy filters] on metadata. | D52: All information (including metadata and the data to which the metadata applies) is subject to filtering and inspection. Some organizations distinguish between metadata and data payloads (i.e., only the data to which the metadata is bound). Other organizations do not make such distinctions and consider metadata and the data to which the metadata applies to be part of the payload.
A53: AC-4(20) | B53: Information Flow Enforcement | Approved Solutions | C53: Employ [Assignment: organization-defined solutions in approved configurations] to control the flow of [Assignment: organization-defined information] across security domains. | D53: Organizations define approved solutions and configurations in cross-domain policies and guidance in accordance with the types of information flows across classification boundaries. The National Security Agency (NSA) National Cross Domain Strategy and Management Office provides a listing of approved cross-domain solutions. Contact ncdsmo@nsa.gov for more information.
A54: AC-4(21) | B54: Information Flow Enforcement | Physical or Logical Separation of Information Flows | C54: Separate information flows logically or physically using [Assignment: organization-defined mechanisms and/or techniques] to accomplish [Assignment: organization-defined required separations by types of information]. | D54: Enforcing the separation of information flows associated with defined types of data can enhance protection by ensuring that information is not commingled while in transit and by enabling flow control by transmission paths that are not otherwise achievable. Types of separable information include inbound and outbound communications traffic, service requests and responses, and information of differing security impact or classification levels. | E54: SC-32
A55: AC-4(22) | B55: Information Flow Enforcement | Access Only | C55: Provide access from a single device to computing platforms, applications, or data residing in multiple different security domains, while preventing information flow between the different security domains. | D55: The system provides a capability for users to access each connected security domain without providing any mechanisms to allow users to transfer data or information between the different security domains. An example of an access-only solution is a terminal that provides a user access to information with different security classifications while assuredly keeping the information separate.
A56: AC-4(23) | B56: Information Flow Enforcement | Modify Non-releasable Information | C56: When transferring information between different security domains, modify non-releasable information by implementing [Assignment: organization-defined modification action]. | D56: Modifying non-releasable information can help prevent a data spill or attack when information is transferred across security domains. Modification actions include masking, permutation, alteration, removal, or redaction.
A57: AC-4(24) | B57: Information Flow Enforcement | Internal Normalized Format | C57: When transferring information between different security domains, parse incoming data into an internal normalized format and regenerate the data to be consistent with its intended specification. | D57: Converting data into normalized forms is one of most of effective mechanisms to stop malicious attacks and large classes of data exfiltration.
A58: AC-4(25) | B58: Information Flow Enforcement | Data Sanitization | C58: When transferring information between different security domains, sanitize data to minimize [Selection (one or more): delivery of malicious content, command and control of malicious code, malicious code augmentation, and steganography encoded data; spillage of sensitive information] in accordance with [Assignment: organization-defined policy]]. | D58: Data sanitization is the process of irreversibly removing or destroying data stored on a memory device (e.g., hard drives, flash memory/solid state drives, mobile devices, CDs, and DVDs) or in hard copy form. | E58: MP-6
A59: AC-4(26) | B59: Information Flow Enforcement | Audit Filtering Actions | C59: When transferring information between different security domains, record and audit content filtering actions and results for the information being filtered. | D59: Content filtering is the process of inspecting information as it traverses a cross-domain solution and determines if the information meets a predefined policy. Content filtering actions and the results of filtering actions are recorded for individual messages to ensure that the correct filter actions were applied. Content filter reports are used to assist in troubleshooting actions by, for example, determining why message content was modified and/or why it failed the filtering process. Audit events are defined in AU-2. Audit records are generated in AU-12. | E59: AU-2, AU-3, AU-12
A60: AC-4(27) | B60: Information Flow Enforcement | Redundant/independent Filtering Mechanisms | C60: When transferring information between different security domains, implement content filtering solutions that provide redundant and independent filtering mechanisms for each data type. | D60: Content filtering is the process of inspecting information as it traverses a cross-domain solution and determines if the information meets a predefined policy. Redundant and independent content filtering eliminates a single point of failure filtering system. Independence is defined as the implementation of a content filter that uses a different code base and supporting libraries (e.g., two JPEG filters using different vendors’ JPEG libraries) and multiple, independent system processes.
A61: AC-4(28) | B61: Information Flow Enforcement | Linear Filter Pipelines | C61: When transferring information between different security domains, implement a linear content filter pipeline that is enforced with discretionary and mandatory access controls. | D61: Content filtering is the process of inspecting information as it traverses a cross-domain solution and determines if the information meets a predefined policy. The use of linear content filter pipelines ensures that filter processes are non-bypassable and always invoked. In general, the use of parallel filtering architectures for content filtering of a single data type introduces bypass and non-invocation issues.
A62: AC-4(29) | B62: Information Flow Enforcement | Filter Orchestration Engines | C62: When transferring information between different security domains, employ content filter orchestration engines to ensure that: (a) Content filtering mechanisms successfully complete execution without errors; and (b) Content filtering actions occur in the correct order and comply with [Assignment: organization-defined policy]. | D62: Content filtering is the process of inspecting information as it traverses a cross-domain solution and determines if the information meets a predefined security policy. An orchestration engine coordinates the sequencing of activities (manual and automated) in a content filtering process. Errors are defined as either anomalous actions or unexpected termination of the content filter process. This is not the same as a filter failing content due to non-compliance with policy. Content filter reports are a commonly used mechanism to ensure that expected filtering actions are completed successfully.
A63: AC-4(30) | B63: Information Flow Enforcement | Filter Mechanisms Using Multiple Processes | C63: When transferring information between different security domains, implement content filtering mechanisms using multiple processes. | D63: The use of multiple processes to implement content filtering mechanisms reduces the likelihood of a single point of failure.
A64: AC-4(31) | B64: Information Flow Enforcement | Failed Content Transfer Prevention | C64: When transferring information between different security domains, prevent the transfer of failed content to the receiving domain. | D64: Content that failed filtering checks can corrupt the system if transferred to the receiving domain.
A65: AC-4(32) | B65: Information Flow Enforcement | Process Requirements for Information Transfer | C65: When transferring information between different security domains, the process that transfers information between filter pipelines: (a) Does not filter message content; (b) Validates filtering metadata; (c) Ensures the content associated with the filtering metadata has successfully completed filtering; and (d) Transfers the content to the destination filter pipeline. | D65: The processes transferring information between filter pipelines have minimum complexity and functionality to provide assurance that the processes operate correctly.
A66: AC-5 | B66: Separation of Duties | C66: a. Identify and document [Assignment: organization-defined duties of individuals requiring separation]; and b. Define system access authorizations to support separation of duties. | D66: Separation of duties addresses the potential for abuse of authorized privileges and helps to reduce the risk of malevolent activity without collusion. Separation of duties includes dividing mission or business functions and support functions among different individuals or roles, conducting system support functions with different individuals, and ensuring that security personnel who administer access control functions do not also administer audit functions. Because separation of duty violations can span systems and application domains, organizations consider the entirety of systems and system components when developing policy on separation of duties. Separation of duties is enforced through the account management activities in AC-2, access control mechanisms in AC-3, and identity management activities in IA-2, IA-4, and IA-12. | E66: AC-2, AC-3, AC-6, AU-9, CM-5, CM-11, CP-9, IA-2, IA-4, IA-5, IA-12, MA-3, MA-5, PS-2, SA-8, SA-17
A67: AC-6 | B67: Least Privilege | C67: Employ the principle of least privilege, allowing only authorized accesses for users (or processes acting on behalf of users) that are necessary to accomplish assigned organizational tasks. | D67: Organizations employ least privilege for specific duties and systems. The principle of least privilege is also applied to system processes, ensuring that the processes have access to systems and operate at privilege levels no higher than necessary to accomplish organizational missions or business functions. Organizations consider the creation of additional processes, roles, and accounts as necessary to achieve least privilege. Organizations apply least privilege to the development, implementation, and operation of organizational systems. | E67: AC-2, AC-3, AC-5, AC-16, CM-5, CM-11, PL-2, PM-12, SA-8, SA-15, SA-17, SC-38
A68: AC-6(1) | B68: Least Privilege | Authorize Access to Security Functions | C68: Authorize access for [Assignment: organization-defined individuals or roles] to: (a) [Assignment: organization-defined security functions (deployed in hardware, software, and firmware)]; and (b) [Assignment: organization-defined security-relevant information]. | D68: Security functions include establishing system accounts, configuring access authorizations (i.e., permissions, privileges), configuring settings for events to be audited, and establishing intrusion detection parameters. Security-relevant information includes filtering rules for routers or firewalls, configuration parameters for security services, cryptographic key management information, and access control lists. Authorized personnel include security administrators, system administrators, system security officers, system programmers, and other privileged users. | E68: AC-17, AC-18, AC-19, AU-9, PE-2
A69: AC-6(2) | B69: Least Privilege | Non-privileged Access for Nonsecurity Functions | C69: Require that users of system accounts (or roles) with access to [Assignment: organization-defined security functions or security-relevant information] use non-privileged accounts or roles, when accessing nonsecurity functions. | D69: Requiring the use of non-privileged accounts when accessing nonsecurity functions limits exposure when operating from within privileged accounts or roles. The inclusion of roles addresses situations where organizations implement access control policies, such as role-based access control, and where a change of role provides the same degree of assurance in the change of access authorizations for the user and the processes acting on behalf of the user as would be provided by a change between a privileged and non-privileged account. | E69: AC-17, AC-18, AC-19, PL-4
A70: AC-6(3) | B70: Least Privilege | Network Access to Privileged Commands | C70: Authorize network access to [Assignment: organization-defined privileged commands] only for [Assignment: organization-defined compelling operational needs] and document the rationale for such access in the security plan for the system. | D70: Network access is any access across a network connection in lieu of local access (i.e., user being physically present at the device). | E70: AC-17, AC-18, AC-19
A71: AC-6(4) | B71: Least Privilege | Separate Processing Domains | C71: Provide separate processing domains to enable finer-grained allocation of user privileges. | D71: Providing separate processing domains for finer-grained allocation of user privileges includes using virtualization techniques to permit additional user privileges within a virtual machine while restricting privileges to other virtual machines or to the underlying physical machine, implementing separate physical domains, and employing hardware or software domain separation mechanisms. | E71: AC-4, SC-2, SC-3, SC-30, SC-32, SC-39
A72: AC-6(5) | B72: Least Privilege | Privileged Accounts | C72: Restrict privileged accounts on the system to [Assignment: organization-defined personnel or roles]. | D72: Privileged accounts, including super user accounts, are typically described as system administrator for various types of commercial off-the-shelf operating systems. Restricting privileged accounts to specific personnel or roles prevents day-to-day users from accessing privileged information or privileged functions. Organizations may differentiate in the application of restricting privileged accounts between allowed privileges for local accounts and for domain accounts provided that they retain the ability to control system configurations for key parameters and as otherwise necessary to sufficiently mitigate risk. | E72: IA-2, MA-3, MA-4
A73: AC-6(6) | B73: Least Privilege | Privileged Access by Non-organizational Users | C73: Prohibit privileged access to the system by non-organizational users. | D73: An organizational user is an employee or an individual considered by the organization to have the equivalent status of an employee. Organizational users include contractors, guest researchers, or individuals detailed from other organizations. A non-organizational user is a user who is not an organizational user. Policies and procedures for granting equivalent status of employees to individuals include a need-to-know, citizenship, and the relationship to the organization. | E73: AC-18, AC-19, IA-2, IA-8
A74: AC-6(7) | B74: Least Privilege | Review of User Privileges | C74: (a) Review [Assignment: organization-defined frequency] the privileges assigned to [Assignment: organization-defined roles or classes of users] to validate the need for such privileges; and (b) Reassign or remove privileges, if necessary, to correctly reflect organizational mission and business needs. | D74: The need for certain assigned user privileges may change over time to reflect changes in organizational mission and business functions, environments of operation, technologies, or threats. A periodic review of assigned user privileges is necessary to determine if the rationale for assigning such privileges remains valid. If the need cannot be revalidated, organizations take appropriate corrective actions. | E74: CA-7
A75: AC-6(8) | B75: Least Privilege | Privilege Levels for Code Execution | C75: Prevent the following software from executing at higher privilege levels than users executing the software: [Assignment: organization-defined software]. | D75: In certain situations, software applications or programs need to execute with elevated privileges to perform required functions. However, depending on the software functionality and configuration, if the privileges required for execution are at a higher level than the privileges assigned to organizational users invoking such applications or programs, those users may indirectly be provided with greater privileges than assigned.
A76: AC-6(9) | B76: Least Privilege | Log Use of Privileged Functions | C76: Log the execution of privileged functions. | D76: The misuse of privileged functions, either intentionally or unintentionally by authorized users or by unauthorized external entities that have compromised system accounts, is a serious and ongoing concern and can have significant adverse impacts on organizations. Logging and analyzing the use of privileged functions is one way to detect such misuse and, in doing so, help mitigate the risk from insider threats and the advanced persistent threat. | E76: AU-2, AU-3, AU-12
A77: AC-6(10) | B77: Least Privilege | Prohibit Non-privileged Users from Executing Privileged Functions | C77: Prevent non-privileged users from executing privileged functions. | D77: Privileged functions include disabling, circumventing, or altering implemented security or privacy controls, establishing system accounts, performing system integrity checks, and administering cryptographic key management activities. Non-privileged users are individuals who do not possess appropriate authorizations. Privileged functions that require protection from non-privileged users include circumventing intrusion detection and prevention mechanisms or malicious code protection mechanisms. Preventing non-privileged users from executing privileged functions is enforced by AC-3.
A78: AC-7 | B78: Unsuccessful Logon Attempts | C78: a. Enforce a limit of [Assignment: organization-defined number] consecutive invalid logon attempts by a user during a [Assignment: organization-defined time period]; and b. Automatically [Selection (one or more): lock the account or node for an [Assignment: organization-defined time period] ; lock the account or node until released by an administrator; delay next logon prompt per [Assignment: organization-defined delay algorithm] ; notify system administrator; take other [Assignment: organization-defined action] ] when the maximum number of unsuccessful attempts is exceeded. | D78: The need to limit unsuccessful logon attempts and take subsequent action when the maximum number of attempts is exceeded applies regardless of whether the logon occurs via a local or network connection. Due to the potential for denial of service, automatic lockouts initiated by systems are usually temporary and automatically release after a predetermined, organization-defined time period. If a delay algorithm is selected, organizations may employ different algorithms for different components of the system based on the capabilities of those components. Responses to unsuccessful logon attempts may be implemented at the operating system and the application levels. Organization-defined actions that may be taken when the number of allowed consecutive invalid logon attempts is exceeded include prompting the user to answer a secret question in addition to the username and password, invoking a lockdown mode with limited user capabilities (instead of full lockout), allowing users to only logon from specified Internet Protocol (IP) addresses, requiring a CAPTCHA to prevent automated attacks, or applying user profiles such as location, time of day, IP address, device, or Media Access Control (MAC) address. If automatic system lockout or execution of a delay algorithm is not implemented in support of the availability objective, organizations consider a combination of other actions to help prevent brute force attacks. In addition to the above, organizations can prompt users to respond to a secret question before the number of allowed unsuccessful logon attempts is exceeded. Automatically unlocking an account after a specified period of time is generally not permitted. However, exceptions may be required based on operational mission or need. | E78: AC-2, AC-9, AU-2, AU-6, IA-5
A79: AC-7(1) | B79: Unsuccessful Logon Attempts | Automatic Account Lock
A80: AC-7(2) | B80: Unsuccessful Logon Attempts | Purge or Wipe Mobile Device | C80: Purge or wipe information from [Assignment: organization-defined mobile devices] based on [Assignment: organization-defined purging or wiping requirements and techniques] after [Assignment: organization-defined number] consecutive, unsuccessful device logon attempts. | D80: A mobile device is a computing device that has a small form factor such that it can be carried by a single individual; is designed to operate without a physical connection; possesses local, non-removable or removable data storage; and includes a self-contained power source. Purging or wiping the device applies only to mobile devices for which the organization-defined number of unsuccessful logons occurs. The logon is to the mobile device, not to any one account on the device. Successful logons to accounts on mobile devices reset the unsuccessful logon count to zero. Purging or wiping may be unnecessary if the information on the device is protected with sufficiently strong encryption mechanisms. | E80: AC-19, MP-5, MP-6
A81: AC-7(3) | B81: Unsuccessful Logon Attempts | Biometric Attempt Limiting | C81: Limit the number of unsuccessful biometric logon attempts to [Assignment: organization-defined number]. | D81: Biometrics are probabilistic in nature. The ability to successfully authenticate can be impacted by many factors, including matching performance and presentation attack detection mechanisms. Organizations select the appropriate number of attempts for users based on organizationally-defined factors. | E81: IA-3
A82: AC-7(4) | B82: Unsuccessful Logon Attempts | Use of Alternate Authentication Factor | C82: (a) Allow the use of [Assignment: organization-defined authentication factors] that are different from the primary authentication factors after the number of organization-defined consecutive invalid logon attempts have been exceeded; and (b) Enforce a limit of [Assignment: organization-defined number] consecutive invalid logon attempts through use of the alternative factors by a user during a [Assignment: organization-defined time period]. | D82: The use of alternate authentication factors supports the objective of availability and allows a user who has inadvertently been locked out to use additional authentication factors to bypass the lockout. | E82: IA-3
A83: AC-8 | B83: System Use Notification | C83: a. Display [Assignment: organization-defined system use notification message or banner] to users before granting access to the system that provides privacy and security notices consistent with applicable laws, executive orders, directives, regulations, policies, standards, and guidelines and state that: 1. Users are accessing a U.S. Government system; 2. System usage may be monitored, recorded, and subject to audit; 3. Unauthorized use of the system is prohibited and subject to criminal and civil penalties; and 4. Use of the system indicates consent to monitoring and recording; b. Retain the notification message or banner on the screen until users acknowledge the usage conditions and take explicit actions to log on to or further access the system; and c. For publicly accessible systems: 1. Display system use information [Assignment: organization-defined conditions], before granting further access to the publicly accessible system; 2. Display references, if any, to monitoring, recording, or auditing that are consistent with privacy accommodations for such systems that generally prohibit those activities; and 3. Include a description of the authorized uses of the system. | D83: System use notifications can be implemented using messages or warning banners displayed before individuals log in to systems. System use notifications are used only for access via logon interfaces with human users. Notifications are not required when human interfaces do not exist. Based on an assessment of risk, organizations consider whether or not a secondary system use notification is needed to access applications or other system resources after the initial network logon. Organizations consider system use notification messages or banners displayed in multiple languages based on organizational needs and the demographics of system users. Organizations consult with the privacy office for input regarding privacy messaging and the Office of the General Counsel or organizational equivalent for legal review and approval of warning banner content. | E83: AC-14, PL-4, SI-4
A84: AC-9 | B84: Previous Logon Notification | C84: Notify the user, upon successful logon to the system, of the date and time of the last logon. | D84: Previous logon notification is applicable to system access via human user interfaces and access to systems that occurs in other types of architectures. Information about the last successful logon allows the user to recognize if the date and time provided is not consistent with the user’s last access. | E84: AC-7, PL-4
A85: AC-9(1) | B85: Previous Logon Notification | Unsuccessful Logons | C85: Notify the user, upon successful logon, of the number of unsuccessful logon attempts since the last successful logon. | D85: Information about the number of unsuccessful logon attempts since the last successful logon allows the user to recognize if the number of unsuccessful logon attempts is consistent with the user’s actual logon attempts.
A86: AC-9(2) | B86: Previous Logon Notification | Successful and Unsuccessful Logons | C86: Notify the user, upon successful logon, of the number of [Selection: successful logons; unsuccessful logon attempts; both] during [Assignment: organization-defined time period]. | D86: Information about the number of successful and unsuccessful logon attempts within a specified time period allows the user to recognize if the number and type of logon attempts are consistent with the user’s actual logon attempts.
A87: AC-9(3) | B87: Previous Logon Notification | Notification of Account Changes | C87: Notify the user, upon successful logon, of changes to [Assignment: organization-defined security-related characteristics or parameters of the user’s account] during [Assignment: organization-defined time period]. | D87: Information about changes to security-related account characteristics within a specified time period allows users to recognize if changes were made without their knowledge.
A88: AC-9(4) | B88: Previous Logon Notification | Additional Logon Information | C88: Notify the user, upon successful logon, of the following additional information: [Assignment: organization-defined additional information]. | D88: Organizations can specify additional information to be provided to users upon logon, including the location of the last logon. User location is defined as information that can be determined by systems, such as Internet Protocol (IP) addresses from which network logons occurred, notifications of local logons, or device identifiers.
A89: AC-10 | B89: Concurrent Session Control | C89: Limit the number of concurrent sessions for each [Assignment: organization-defined account and/or account type] to [Assignment: organization-defined number]. | D89: Organizations may define the maximum number of concurrent sessions for system accounts globally, by account type, by account, or any combination thereof. For example, organizations may limit the number of concurrent sessions for system administrators or other individuals working in particularly sensitive domains or mission-critical applications. Concurrent session control addresses concurrent sessions for system accounts. It does not, however, address concurrent sessions by single users via multiple system accounts. | E89: SC-23
A90: AC-11 | B90: Device Lock | C90: a. Prevent further access to the system by [Selection (one or more): initiating a device lock after [Assignment: organization-defined time period] of inactivity; requiring the user to initiate a device lock before leaving the system unattended]; and b. Retain the device lock until the user reestablishes access using established identification and authentication procedures. | D90: Device locks are temporary actions taken to prevent logical access to organizational systems when users stop work and move away from the immediate vicinity of those systems but do not want to log out because of the temporary nature of their absences. Device locks can be implemented at the operating system level or at the application level. A proximity lock may be used to initiate the device lock (e.g., via a Bluetooth-enabled device or dongle). User-initiated device locking is behavior or policy-based and, as such, requires users to take physical action to initiate the device lock. Device locks are not an acceptable substitute for logging out of systems, such as when organizations require users to log out at the end of workdays. | E90: AC-2, AC-7, IA-11, PL-4
A91: AC-11(1) | B91: Device Lock | Pattern-hiding Displays | C91: Conceal, via the device lock, information previously visible on the display with a publicly viewable image. | D91: The pattern-hiding display can include static or dynamic images, such as patterns used with screen savers, photographic images, solid colors, clock, battery life indicator, or a blank screen with the caveat that controlled unclassified information is not displayed.
A92: AC-12 | B92: Session Termination | C92: Automatically terminate a user session after [Assignment: organization-defined conditions, or trigger events requiring session disconnect]. | D92: Session termination addresses the termination of user-initiated logical sessions (in contrast to SC-10, which addresses the termination of network connections associated with communications sessions (i.e., network disconnect)). A logical session (for local, network, and remote access) is initiated whenever a user (or process acting on behalf of a user) accesses an organizational system. Such user sessions can be terminated without terminating network sessions. Session termination ends all processes associated with a user’s logical session except for those processes that are specifically created by the user (i.e., session owner) to continue after the session is terminated. Conditions or trigger events that require automatic termination of the session include organization-defined periods of user inactivity, targeted responses to certain types of incidents, or time-of-day restrictions on system use. | E92: MA-4, SC-10, SC-23
A93: AC-12(1) | B93: Session Termination | User-initiated Logouts | C93: Provide a logout capability for user-initiated communications sessions whenever authentication is used to gain access to [Assignment: organization-defined information resources]. | D93: Information resources to which users gain access via authentication include local workstations, databases, and password-protected websites or web-based services.
A94: AC-12(2) | B94: Session Termination | Termination Message | C94: Display an explicit logout message to users indicating the termination of authenticated communications sessions. | D94: Logout messages for web access can be displayed after authenticated sessions have been terminated. However, for certain types of sessions, including file transfer protocol (FTP) sessions, systems typically send logout messages as final messages prior to terminating sessions.
